Workbook
Name _ftn1: 'Törnqvist Methodology'!#REF!
Name _ftn2: 'Törnqvist Methodology'!#REF!
Name _ftn3: 'Törnqvist Methodology'!#REF!
Name _ftnref1: 'Törnqvist Methodology'!#REF!
Name _ftnref2: 'Törnqvist Methodology'!#REF!
Name _ftnref3: 'Törnqvist Methodology'!#REF!
Name _Toc166695565: 'Törnqvist Methodology'!#REF!
Name _Toc166695566: 'Törnqvist Methodology'!#REF!
Name _Toc166695567: 'Törnqvist Methodology'!#REF!

Sheet README
A1: The Changing Wealth of Nations 2024
A2: Citation: | B2: TBD
A3: Report (pdf): | B3: TBD | C3: SEGUIR ARREGLANDO ACA, TRAERMELO A LAS NOTAS, Y AL ES Y OVERVIEW
A4: Data and methods: | B4: https://datacatalog.worldbank.org/dataset/wealth-accounting | C4: The Törnqvist volume index it is 'chained' together to make a time series by selecting a base year (2019) and then expressing other years in terms relative to the base year. For the base year, the chained Törnqvist volume index is normalized to 100. To make the index easier to understand, the chained volume index is converted into monetary terms, referred to as real asset values and expressed in “chained 2019 prices.”
A5: Release date: | B5: 45573
A6: File version: | B6: 45573
A7: IMPORTANT NOTE: | B7: The trends in total wealth and asset categories (produced, human, renewable, and nonrenewable natural capital) are based on the Törnqvist index, where the change in physical volumes of individual assets is weighted by their value shares. “Volume” here refers to the physical quantity of each asset, or a proxy for that quantity. For example, the volume of timber assets is measured in hectares, while the volume of oil assets is measured in barrels. Because these assets are measured in different units, the Törnqvist index allows us to combine them by weighting the change in each asset by its value share, making the changes unitless and allowing the aggregation of different asset types to obtain an overall measure of how the total volume has changed. The Törnqvist volume index it is 'chained' together to make a time series by selecting a base year (2019) and then expressing other years in terms relative to the base year. For the base year, the chained Törnqvist volume index is normalized to 100. To make the index easier to interpret, the chained volume index is converted into monetary terms using 2019 US dollars, referred to as real asset values and expressed in “chained 2019 dollars”. This adjustment captures the "real" value of assets while removing the effect of inflation and other price changes. For each individual asset (sub-components of the aggregate categories), the change between 1995 and 2020 follows the trend in physical volumes, but unlike the aggregate asset categories, the changes over time in individual assets are not weighted by their shares in total wealth.
A9: Instructions | B9: On the "Select a Country" tab, select a country from the dropdown list at the top of the sheet. This automatically populates the data and figures on that sheet.
A11: Definitions
A12: Unit | B12: Values are measured at market exchange rates in chained 2019 US dollars, using a country-specific GDP deflator
A13: Country | B13: World Bank economy
A14: Income | B14: World Bank income group in 2020
A15: Region | B15: World Bank region (all income levels)
A16: Region_developing | B16: World Bank region (low income, lower middle income, and upper middle income economies)
A17: Total wealth | B17: Sum of produced capital, renewable and nonrenewable natural capital, human capital, and net foreign assets
A18: Produced capital | B18: Value of machinery, buildings, equipment, and residential and nonresidential urban land
A19: Renewable natural capital | B19: Valuation of agricultural land (cropland and pastureland), forests (timber and forest ecosystem services), mangroves, fisheries and hydropower
A20: Nonrenewable natural capital | B20: Valuation of fossil fuel energy (oil, gas, and coal) and minerals (bauxite, copper, gold, iron ore, lead, nickel, phosphate, silver, tin, zinc, cobalt, molybdenum, and lithuim)
A21: Human capital | B21: Present value of future earnings for the working population over their lifetimes
A22: Net foreign assets | B22: Foreign assets minus foreign liabilities
A24: * Will update the below series code once the WDI series code for CWON 2024 data is finalized
A25: Wealth Accounts Series Code and Name
A26: Series Code | B26: Series Name
A27: NW.PCA.TO | B27: Produced capital (real chained 2019 US$)
A28: NW.PCA.PC | B28: Produced capital per capita (real chained 2019 US$)
A29: NW.NFA.TO | B29: Foreign assets (real chained 2019 US$)
A30: NW.NFA.PC | B30: Foreign assets per capita (real chained 2019 US$)
A31: NW.NFL.TO | B31: Foreign liabilities (real chained 2019 US$)
A32: NW.NFL.PC | B32: Foreign liabilities per capita (real chained 2019 US$)
A33: NW.NCA.TOTL.TO | B33: Renewable natural capital, total (real chained 2019 US$)
A34: NW.NCA.TOTL.PC | B34: Renewable natural capital per capita, total (real chained 2019 US$)
A35: NW.NCA.AGRI.TO | B35: Renewable natural capital, agricultural land (real chained 2019 US$)
A36: NW.NCA.AGRI.PC | B36: Renewable natural capital per capita, agricultural land (real chained 2019 US$)
A37: NW.NCA.FTIM.TO | B37: Renewable natural capital, timber (real chained 2019 US$)
... A98: NW.TOW.PC.CD | B98: National comprehensive wealth per capita (current US$)

Sheet Select a Country
B1: IMPORTANT NOTE: | C1: The trends in total wealth and asset categories (produced, human, renewable, and nonrenewable natural capital) are based on the Törnqvist index, where the change in physical volumes of individual assets is weighted by their value shares. “Volume” here refers to the physical quantity of each asset, or a proxy for that quantity. For example, the volume of timber assets is measured in hectares, while the volume of oil assets is measured in barrels. Because these assets are measured in different units, the Törnqvist index allows us to combine them by weighting the change in each asset by its value share, making the changes unitless and allowing the aggregation of different asset types to obtain an overall measure of how the total volume has changed. The Törnqvist volume index it is 'chained' together to make a time series by selecting a base year (2019) and then expressing other years in terms relative to the base year. For the base year, the chained Törnqvist volume index is normalized to 100. To make the index easier to interpret, the chained volume index is converted into monetary terms using 2019 US dollars, referred to as real asset values and expressed in “chained 2019 dollars”. This adjustment captures the "real" value of assets while removing the effect of inflation and other price changes. For each individual asset (sub-components of the aggregate categories), the change between 1995 and 2020 follows the trend in physical volumes, but unlike the aggregate asset categories, the changes over time in individual assets are not weighted by their shares in total wealth.
B3: Select a country below:
A4: Country | B4: Argentina | C4: =VLOOKUP($B$4,class!$A:$F,2,FALSE) -> ARG
A5: Income | B5: =VLOOKUP($B$4,class!$A:$F,3,FALSE) -> Upper middle income
A6: Region | B6: =VLOOKUP($B$4,class!$A:$F,5,FALSE) -> Latin America and Caribbean
B8: Millions, chained 2019 USD | C8: 1995 | D8: 1996 | E8: 1997 | F8: 1998 | G8: 1999 | H8: 2000 | I8: 2001 | J8: 2002 | K8: 2003 | L8: 2004 | M8: 2005 | N8: 2006 | O8: 2007 | P8: 2008 | Q8: 2009 | R8: 2010 | S8: 2011 | T8: 2012 | U8: 2013 | V8: 2014 | W8: 2015 | X8: 2016 | Y8: 2017 | Z8: 2018 | AA8: 2019 | AB8: 2020 | AC8: Percent change (1995 to 2020)
A9: 36 | B9: National comprehensive wealth index | C9: =IFERROR(VLOOKUP(CONCATENATE($C$4,".",C$8),country!$G:$CD,$A9,FALSE)/1000000,"..") -> 1775865.6 | D9: =IFERROR(VLOOKUP(CONCATENATE($C$4,".",D$8),country!$G:$CD,$A9,FALSE)/1000000,"..") -> 1755387.1 | E9: =IFERROR(VLOOKUP(CONCATENATE($C$4,".",E$8),country!$G:$CD,$A9,FALSE)/1000000,"..") -> 1718201.8 | F9: =IFERROR(VLOOKUP(CONCATENATE($C$4,".",F$8),country!$G:$CD,$A9,FALSE)/1000000,"..") -> 1728758.8 | G9: =IFERROR(VLOOKUP(CONCATENATE($C$4,".",G$8),country!$G:$CD,$A9,FALSE)/1000000,"..") -> 1653061 | H9: =IFERROR(VLOOKUP(CONCATENATE($C$4,".",H$8),country!$G:$CD,$A9,FALSE)/1000000,"..") -> 1654586.9 | I9: =IFERROR(VLOOKUP(CONCATENATE($C$4,".",I$8),country!$G:$CD,$A9,FALSE)/1000000,"..") -> 1537978.1 | J9: =IFERROR(VLOOKUP(CONCATENATE($C$4,".",J$8),country!$G:$CD,$A9,FALSE)/1000000,"..") -> 2003756.1 | ... AB9: =IFERROR(VLOOKUP(CONCATENATE($C$4,".",AB$8),country!$G:$CD,$A9,FALSE)/1000000,"..") -> 3766127.3 | AC9: =IFERROR(AB9/C9-1,"..") -> 1.1207276
A10: 3 | B10: Produced capital | C10: =IFERROR(VLOOKUP(CONCATENATE($C$4,".",C$8),country!$G:$CD,$A10,FALSE)/1000000,"..") -> 391198.06 | D10: =IFERROR(VLOOKUP(CONCATENATE($C$4,".",D$8),country!$G:$CD,$A10,FALSE)/1000000,"..") -> 405064.18 | E10: =IFERROR(VLOOKUP(CONCATENATE($C$4,".",E$8),country!$G:$CD,$A10,FALSE)/1000000,"..") -> 423211.87 | F10: =IFERROR(VLOOKUP(CONCATENATE($C$4,".",F$8),country!$G:$CD,$A10,FALSE)/1000000,"..") -> 442622.75 | G10: =IFERROR(VLOOKUP(CONCATENATE($C$4,".",G$8),country!$G:$CD,$A10,FALSE)/1000000,"..") -> 456678.56 | H10: =IFERROR(VLOOKUP(CONCATENATE($C$4,".",H$8),country!$G:$CD,$A10,FALSE)/1000000,"..") -> 468128.76 | I10: =IFERROR(VLOOKUP(CONCATENATE($C$4,".",I$8),country!$G:$CD,$A10,FALSE)/1000000,"..") -> 474772.76 | J10: =IFERROR(VLOOKUP(CONCATENATE($C$4,".",J$8),country!$G:$CD,$A10,FALSE)/1000000,"..") -> 471844.11 | ... AB10: =IFERROR(VLOOKUP(CONCATENATE($C$4,".",AB$8),country!$G:$CD,$A10,FALSE)/1000000,"..") -> 827744.06 | AC10: =IFERROR(AB10/C10-1,"..") -> 1.1159207
A11: 33 | B11: Human capital | C11: =IFERROR(VLOOKUP(CONCATENATE($C$4,".",C$8),country!$G:$CD,$A11,FALSE)/1000000,"..") -> 1455187.3 | D11: =IFERROR(VLOOKUP(CONCATENATE($C$4,".",D$8),country!$G:$CD,$A11,FALSE)/1000000,"..") -> 1526475.9 | E11: =IFERROR(VLOOKUP(CONCATENATE($C$4,".",E$8),country!$G:$CD,$A11,FALSE)/1000000,"..") -> 1617412.2 | F11: =IFERROR(VLOOKUP(CONCATENATE($C$4,".",F$8),country!$G:$CD,$A11,FALSE)/1000000,"..") -> 1697522.9 | G11: =IFERROR(VLOOKUP(CONCATENATE($C$4,".",G$8),country!$G:$CD,$A11,FALSE)/1000000,"..") -> 1684917.5 | H11: =IFERROR(VLOOKUP(CONCATENATE($C$4,".",H$8),country!$G:$CD,$A11,FALSE)/1000000,"..") -> 1688360.8 | I11: =IFERROR(VLOOKUP(CONCATENATE($C$4,".",I$8),country!$G:$CD,$A11,FALSE)/1000000,"..") -> 1664920.6 | J11: =IFERROR(VLOOKUP(CONCATENATE($C$4,".",J$8),country!$G:$CD,$A11,FALSE)/1000000,"..") -> 1616374.1 | ... AB11: =IFERROR(VLOOKUP(CONCATENATE($C$4,".",AB$8),country!$G:$CD,$A11,FALSE)/1000000,"..") -> 2567714.5 | AC11: =IFERROR(AB11/C11-1,"..") -> 0.76452507
A12: 6 | B12: Renewable natural capital | C12: =IFERROR(VLOOKUP(CONCATENATE($C$4,".",C$8),country!$G:$CD,$A12,FALSE)/1000000,"..") -> 327340.87 | D12: =IFERROR(VLOOKUP(CONCATENATE($C$4,".",D$8),country!$G:$CD,$A12,FALSE)/1000000,"..") -> 319336.11 | E12: =IFERROR(VLOOKUP(CONCATENATE($C$4,".",E$8),country!$G:$CD,$A12,FALSE)/1000000,"..") -> 326455.81 | F12: =IFERROR(VLOOKUP(CONCATENATE($C$4,".",F$8),country!$G:$CD,$A12,FALSE)/1000000,"..") -> 322636.67 | G12: =IFERROR(VLOOKUP(CONCATENATE($C$4,".",G$8),country!$G:$CD,$A12,FALSE)/1000000,"..") -> 313995.9 | H12: =IFERROR(VLOOKUP(CONCATENATE($C$4,".",H$8),country!$G:$CD,$A12,FALSE)/1000000,"..") -> 324956.51 | I12: =IFERROR(VLOOKUP(CONCATENATE($C$4,".",I$8),country!$G:$CD,$A12,FALSE)/1000000,"..") -> 341265.34 | J12: =IFERROR(VLOOKUP(CONCATENATE($C$4,".",J$8),country!$G:$CD,$A12,FALSE)/1000000,"..") -> 338535.43 | ... AB12: =IFERROR(VLOOKUP(CONCATENATE($C$4,".",AB$8),country!$G:$CD,$A12,FALSE)/1000000,"..") -> 286052 | AC12: =IFERROR(AB12/C12-1,"..") -> -0.12613419
A13: 8 | B13: Forests, timber | C13: =IFERROR(VLOOKUP(CONCATENATE($C$4,".",C$8),country!$G:$CD,$A13,FALSE)/1000000,"..") -> 19882.89 | D13: =IFERROR(VLOOKUP(CONCATENATE($C$4,".",D$8),country!$G:$CD,$A13,FALSE)/1000000,"..") -> 19777.014 | E13: =IFERROR(VLOOKUP(CONCATENATE($C$4,".",E$8),country!$G:$CD,$A13,FALSE)/1000000,"..") -> 19671.137 | F13: =IFERROR(VLOOKUP(CONCATENATE($C$4,".",F$8),country!$G:$CD,$A13,FALSE)/1000000,"..") -> 19565.26 | G13: =IFERROR(VLOOKUP(CONCATENATE($C$4,".",G$8),country!$G:$CD,$A13,FALSE)/1000000,"..") -> 19459.384 | H13: =IFERROR(VLOOKUP(CONCATENATE($C$4,".",H$8),country!$G:$CD,$A13,FALSE)/1000000,"..") -> 19353.507 | I13: =IFERROR(VLOOKUP(CONCATENATE($C$4,".",I$8),country!$G:$CD,$A13,FALSE)/1000000,"..") -> 19170.049 | J13: =IFERROR(VLOOKUP(CONCATENATE($C$4,".",J$8),country!$G:$CD,$A13,FALSE)/1000000,"..") -> 18986.592 | ... AB13: =IFERROR(VLOOKUP(CONCATENATE($C$4,".",AB$8),country!$G:$CD,$A13,FALSE)/1000000,"..") -> 16567.432 | AC13: =IFERROR(AB13/C13-1,"..") -> -0.16674929
A14: 10 | B14: Forests, recreation, hunting, and fishing services (es1) | C14: =IFERROR(VLOOKUP(CONCATENATE($C$4,".",C$8),country!$G:$CD,$A14,FALSE)/1000000,"..") -> 4969.5562 | D14: =IFERROR(VLOOKUP(CONCATENATE($C$4,".",D$8),country!$G:$CD,$A14,FALSE)/1000000,"..") -> 4943.0933 | E14: =IFERROR(VLOOKUP(CONCATENATE($C$4,".",E$8),country!$G:$CD,$A14,FALSE)/1000000,"..") -> 4916.6303 | F14: =IFERROR(VLOOKUP(CONCATENATE($C$4,".",F$8),country!$G:$CD,$A14,FALSE)/1000000,"..") -> 4890.1674 | G14: =IFERROR(VLOOKUP(CONCATENATE($C$4,".",G$8),country!$G:$CD,$A14,FALSE)/1000000,"..") -> 4863.7044 | H14: =IFERROR(VLOOKUP(CONCATENATE($C$4,".",H$8),country!$G:$CD,$A14,FALSE)/1000000,"..") -> 4837.2415 | I14: =IFERROR(VLOOKUP(CONCATENATE($C$4,".",I$8),country!$G:$CD,$A14,FALSE)/1000000,"..") -> 4791.3878 | J14: =IFERROR(VLOOKUP(CONCATENATE($C$4,".",J$8),country!$G:$CD,$A14,FALSE)/1000000,"..") -> 4745.5342 | ... AB14: =IFERROR(VLOOKUP(CONCATENATE($C$4,".",AB$8),country!$G:$CD,$A14,FALSE)/1000000,"..") -> 4140.8862 | AC14: =IFERROR(AB14/C14-1,"..") -> -0.16674929
A15: 11 | B15: Forests, non-wood forest products (es2) | C15: =IFERROR(VLOOKUP(CONCATENATE($C$4,".",C$8),country!$G:$CD,$A15,FALSE)/1000000,"..") -> 9190.9726 | D15: =IFERROR(VLOOKUP(CONCATENATE($C$4,".",D$8),country!$G:$CD,$A15,FALSE)/1000000,"..") -> 9142.0306 | E15: =IFERROR(VLOOKUP(CONCATENATE($C$4,".",E$8),country!$G:$CD,$A15,FALSE)/1000000,"..") -> 9093.0885 | F15: =IFERROR(VLOOKUP(CONCATENATE($C$4,".",F$8),country!$G:$CD,$A15,FALSE)/1000000,"..") -> 9044.1465 | G15: =IFERROR(VLOOKUP(CONCATENATE($C$4,".",G$8),country!$G:$CD,$A15,FALSE)/1000000,"..") -> 8995.2044 | H15: =IFERROR(VLOOKUP(CONCATENATE($C$4,".",H$8),country!$G:$CD,$A15,FALSE)/1000000,"..") -> 8946.2624 | I15: =IFERROR(VLOOKUP(CONCATENATE($C$4,".",I$8),country!$G:$CD,$A15,FALSE)/1000000,"..") -> 8861.4581 | J15: =IFERROR(VLOOKUP(CONCATENATE($C$4,".",J$8),country!$G:$CD,$A15,FALSE)/1000000,"..") -> 8776.6538 | ... AB15: =IFERROR(VLOOKUP(CONCATENATE($C$4,".",AB$8),country!$G:$CD,$A15,FALSE)/1000000,"..") -> 7658.3844 | AC15: =IFERROR(AB15/C15-1,"..") -> -0.16674929
A16: 12 | B16: Forests, water retention services (es3) | C16: =IFERROR(VLOOKUP(CONCATENATE($C$4,".",C$8),country!$G:$CD,$A16,FALSE)/1000000,"..") -> 78348.703 | D16: =IFERROR(VLOOKUP(CONCATENATE($C$4,".",D$8),country!$G:$CD,$A16,FALSE)/1000000,"..") -> 77931.495 | E16: =IFERROR(VLOOKUP(CONCATENATE($C$4,".",E$8),country!$G:$CD,$A16,FALSE)/1000000,"..") -> 77514.287 | F16: =IFERROR(VLOOKUP(CONCATENATE($C$4,".",F$8),country!$G:$CD,$A16,FALSE)/1000000,"..") -> 77097.079 | G16: =IFERROR(VLOOKUP(CONCATENATE($C$4,".",G$8),country!$G:$CD,$A16,FALSE)/1000000,"..") -> 76679.872 | H16: =IFERROR(VLOOKUP(CONCATENATE($C$4,".",H$8),country!$G:$CD,$A16,FALSE)/1000000,"..") -> 76262.664 | I16: =IFERROR(VLOOKUP(CONCATENATE($C$4,".",I$8),country!$G:$CD,$A16,FALSE)/1000000,"..") -> 75539.747 | J16: =IFERROR(VLOOKUP(CONCATENATE($C$4,".",J$8),country!$G:$CD,$A16,FALSE)/1000000,"..") -> 74816.831 | ... AB16: =IFERROR(VLOOKUP(CONCATENATE($C$4,".",AB$8),country!$G:$CD,$A16,FALSE)/1000000,"..") -> 65284.112 | AC16: =IFERROR(AB16/C16-1,"..") -> -0.16674929
A17: 9 | B17: Mangroves | C17: =IFERROR(VLOOKUP(CONCATENATE($C$4,".",C$8),country!$G:$CD,$A17,FALSE)/1000000,"..") -> 0 | D17: =IFERROR(VLOOKUP(CONCATENATE($C$4,".",D$8),country!$G:$CD,$A17,FALSE)/1000000,"..") -> 0 | E17: =IFERROR(VLOOKUP(CONCATENATE($C$4,".",E$8),country!$G:$CD,$A17,FALSE)/1000000,"..") -> 0 | F17: =IFERROR(VLOOKUP(CONCATENATE($C$4,".",F$8),country!$G:$CD,$A17,FALSE)/1000000,"..") -> 0 | G17: =IFERROR(VLOOKUP(CONCATENATE($C$4,".",G$8),country!$G:$CD,$A17,FALSE)/1000000,"..") -> 0 | H17: =IFERROR(VLOOKUP(CONCATENATE($C$4,".",H$8),country!$G:$CD,$A17,FALSE)/1000000,"..") -> 0 | I17: =IFERROR(VLOOKUP(CONCATENATE($C$4,".",I$8),country!$G:$CD,$A17,FALSE)/1000000,"..") -> 0 | J17: =IFERROR(VLOOKUP(CONCATENATE($C$4,".",J$8),country!$G:$CD,$A17,FALSE)/1000000,"..") -> 0 | ... AB17: =IFERROR(VLOOKUP(CONCATENATE($C$4,".",AB$8),country!$G:$CD,$A17,FALSE)/1000000,"..") -> 0 | AC17: =IFERROR(AB17/C17-1,"..") -> ..
A18: 13 | B18: Fisheries | C18: =IFERROR(VLOOKUP(CONCATENATE($C$4,".",C$8),country!$G:$CD,$A18,FALSE)/1000000,"..") -> 2615.2576 | D18: =IFERROR(VLOOKUP(CONCATENATE($C$4,".",D$8),country!$G:$CD,$A18,FALSE)/1000000,"..") -> 2539.0788 | E18: =IFERROR(VLOOKUP(CONCATENATE($C$4,".",E$8),country!$G:$CD,$A18,FALSE)/1000000,"..") -> 2451.3813 | F18: =IFERROR(VLOOKUP(CONCATENATE($C$4,".",F$8),country!$G:$CD,$A18,FALSE)/1000000,"..") -> 2372.1139 | G18: =IFERROR(VLOOKUP(CONCATENATE($C$4,".",G$8),country!$G:$CD,$A18,FALSE)/1000000,"..") -> 2302.0723 | H18: =IFERROR(VLOOKUP(CONCATENATE($C$4,".",H$8),country!$G:$CD,$A18,FALSE)/1000000,"..") -> 2245.7755 | I18: =IFERROR(VLOOKUP(CONCATENATE($C$4,".",I$8),country!$G:$CD,$A18,FALSE)/1000000,"..") -> 2221.4369 | J18: =IFERROR(VLOOKUP(CONCATENATE($C$4,".",J$8),country!$G:$CD,$A18,FALSE)/1000000,"..") -> 2214.2776 | ... AB18: =IFERROR(VLOOKUP(CONCATENATE($C$4,".",AB$8),country!$G:$CD,$A18,FALSE)/1000000,"..") -> 2450.3742 | AC18: =IFERROR(AB18/C18-1,"..") -> -0.06304673
A19: 7 | B19: Agricultural land | C19: =IFERROR(VLOOKUP(CONCATENATE($C$4,".",C$8),country!$G:$CD,$A19,FALSE)/1000000,"..") -> 208047.46 | D19: =IFERROR(VLOOKUP(CONCATENATE($C$4,".",D$8),country!$G:$CD,$A19,FALSE)/1000000,"..") -> 208205.06 | E19: =IFERROR(VLOOKUP(CONCATENATE($C$4,".",E$8),country!$G:$CD,$A19,FALSE)/1000000,"..") -> 208356.17 | F19: =IFERROR(VLOOKUP(CONCATENATE($C$4,".",F$8),country!$G:$CD,$A19,FALSE)/1000000,"..") -> 208510.53 | G19: =IFERROR(VLOOKUP(CONCATENATE($C$4,".",G$8),country!$G:$CD,$A19,FALSE)/1000000,"..") -> 208643.76 | H19: =IFERROR(VLOOKUP(CONCATENATE($C$4,".",H$8),country!$G:$CD,$A19,FALSE)/1000000,"..") -> 208802.99 | I19: =IFERROR(VLOOKUP(CONCATENATE($C$4,".",I$8),country!$G:$CD,$A19,FALSE)/1000000,"..") -> 208958.97 | J19: =IFERROR(VLOOKUP(CONCATENATE($C$4,".",J$8),country!$G:$CD,$A19,FALSE)/1000000,"..") -> 209127.95 | ... AB19: =IFERROR(VLOOKUP(CONCATENATE($C$4,".",AB$8),country!$G:$CD,$A19,FALSE)/1000000,"..") -> 176098.63 | AC19: =IFERROR(AB19/C19-1,"..") -> -0.15356508
A20: 14 | B20: Hydropower energy | C20: =IFERROR(VLOOKUP(CONCATENATE($C$4,".",C$8),country!$G:$CD,$A20,FALSE)/1000000,"..") -> 12104.577 | D20: =IFERROR(VLOOKUP(CONCATENATE($C$4,".",D$8),country!$G:$CD,$A20,FALSE)/1000000,"..") -> 10309.927 | E20: =IFERROR(VLOOKUP(CONCATENATE($C$4,".",E$8),country!$G:$CD,$A20,FALSE)/1000000,"..") -> 12640.594 | F20: =IFERROR(VLOOKUP(CONCATENATE($C$4,".",F$8),country!$G:$CD,$A20,FALSE)/1000000,"..") -> 11927.848 | G20: =IFERROR(VLOOKUP(CONCATENATE($C$4,".",G$8),country!$G:$CD,$A20,FALSE)/1000000,"..") -> 9719.6352 | H20: =IFERROR(VLOOKUP(CONCATENATE($C$4,".",H$8),country!$G:$CD,$A20,FALSE)/1000000,"..") -> 13064.207 | I20: =IFERROR(VLOOKUP(CONCATENATE($C$4,".",I$8),country!$G:$CD,$A20,FALSE)/1000000,"..") -> 16831.348 | J20: =IFERROR(VLOOKUP(CONCATENATE($C$4,".",J$8),country!$G:$CD,$A20,FALSE)/1000000,"..") -> 16294.099 | ... AB20: =IFERROR(VLOOKUP(CONCATENATE($C$4,".",AB$8),country!$G:$CD,$A20,FALSE)/1000000,"..") -> 12132.576 | AC20: =IFERROR(AB20/C20-1,"..") -> 0.0023131473
... A28: 2 | B28: Population (millions) | C28: =IFERROR(VLOOKUP(CONCATENATE($C$4,".",C$8),country!$G:$CD,$A28,FALSE)/1000000,"..") -> 34.94611 | D28: =IFERROR(VLOOKUP(CONCATENATE($C$4,".",D$8),country!$G:$CD,$A28,FALSE)/1000000,"..") -> 35.389362 | E28: =IFERROR(VLOOKUP(CONCATENATE($C$4,".",E$8),country!$G:$CD,$A28,FALSE)/1000000,"..") -> 35.815971 | F28: =IFERROR(VLOOKUP(CONCATENATE($C$4,".",F$8),country!$G:$CD,$A28,FALSE)/1000000,"..") -> 36.233195 | G28: =IFERROR(VLOOKUP(CONCATENATE($C$4,".",G$8),country!$G:$CD,$A28,FALSE)/1000000,"..") -> 36.653031 | H28: =IFERROR(VLOOKUP(CONCATENATE($C$4,".",H$8),country!$G:$CD,$A28,FALSE)/1000000,"..") -> 37.070774 | I28: =IFERROR(VLOOKUP(CONCATENATE($C$4,".",I$8),country!$G:$CD,$A28,FALSE)/1000000,"..") -> 37.480493 | J28: =IFERROR(VLOOKUP(CONCATENATE($C$4,".",J$8),country!$G:$CD,$A28,FALSE)/1000000,"..") -> 37.885028 | ... AB28: =IFERROR(VLOOKUP(CONCATENATE($C$4,".",AB$8),country!$G:$CD,$A28,FALSE)/1000000,"..") -> 45.376763 | AC28: =IFERROR(AB28/C28-1,"..") -> 0.29847823
B30: Per Capita, chained 2019 USD | C30: 1995 | D30: 1996 | E30: 1997 | F30: 1998 | G30: 1999 | H30: 2000 | I30: 2001 | J30: 2002 | K30: 2003 | L30: 2004 | M30: 2005 | N30: 2006 | O30: 2007 | P30: 2008 | Q30: 2009 | R30: 2010 | S30: 2011 | T30: 2012 | U30: 2013 | V30: 2014 | W30: 2015 | X30: 2016 | Y30: 2017 | Z30: 2018 | AA30: 2019 | AB30: 2020 | AC30: Percent change (1995 to 2020)
B31: National comprehensive wealth index | C31: =IFERROR(C9/C$28,"..") -> 50817.262 | D31: =IFERROR(D9/D$28,"..") -> 49602.113 | E31: =IFERROR(E9/E$28,"..") -> 47973.063 | F31: =IFERROR(F9/F$28,"..") -> 47712.016 | G31: =IFERROR(G9/G$28,"..") -> 45100.255 | H31: =IFERROR(H9/H$28,"..") -> 44633.189 | I31: =IFERROR(I9/I$28,"..") -> 41034.095 | J31: =IFERROR(J9/J$28,"..") -> 52890.447 | ... AB31: =IFERROR(AB9/AB$28,"..") -> 82996.827 | AC31: =IFERROR(AB31/C31-1,"..") -> 0.63324081
B32: Produced capital | C32: =IFERROR(C10/C$28,"..") -> 11194.323 | D32: =IFERROR(D10/D$28,"..") -> 11445.93 | E32: =IFERROR(E10/E$28,"..") -> 11816.289 | F32: =IFERROR(F10/F$28,"..") -> 12215.946 | G32: =IFERROR(G10/G$28,"..") -> 12459.503 | H32: =IFERROR(H10/H$28,"..") -> 12627.974 | I32: =IFERROR(I10/I$28,"..") -> 12667.196 | J32: =IFERROR(J10/J$28,"..") -> 12454.633 | ... AB32: =IFERROR(AB10/AB$28,"..") -> 18241.585 | AC32: =IFERROR(AB32/C32-1,"..") -> 0.62953882
B33: Human capital | C33: =IFERROR(C11/C$28,"..") -> 41640.895 | D33: =IFERROR(D11/D$28,"..") -> 43133.749 | E33: =IFERROR(E11/E$28,"..") -> 45158.964 | F33: =IFERROR(F11/F$28,"..") -> 46849.938 | G33: =IFERROR(G11/G$28,"..") -> 45969.39 | H33: =IFERROR(H11/H$28,"..") -> 45544.256 | I33: =IFERROR(I11/I$28,"..") -> 44420.989 | J33: =IFERROR(J11/J$28,"..") -> 42665.249 | ... AB33: =IFERROR(AB11/AB$28,"..") -> 56586.551 | AC33: =IFERROR(AB33/C33-1,"..") -> 0.35891772
B34: Renewable natural capital | C34: =IFERROR(C12/C$28,"..") -> 9367.0189 | D34: =IFERROR(D12/D$28,"..") -> 9023.5058 | E34: =IFERROR(E12/E$28,"..") -> 9114.8111 | F34: =IFERROR(F12/F$28,"..") -> 8904.45 | G34: =IFERROR(G12/G$28,"..") -> 8566.7103 | H34: =IFERROR(H12/H$28,"..") -> 8765.8409 | I34: =IFERROR(I12/I$28,"..") -> 9105.1455 | J34: =IFERROR(J12/J$28,"..") -> 8935.8633 | ... AB34: =IFERROR(AB12/AB$28,"..") -> 6303.9313 | AC34: =IFERROR(AB34/C34-1,"..") -> -0.32700773
B35: Forests, timber | C35: =IFERROR(C13/C$28,"..") -> 568.95861 | D35: =IFERROR(D13/D$28,"..") -> 558.84064 | E35: =IFERROR(E13/E$28,"..") -> 549.22808 | F35: =IFERROR(F13/F$28,"..") -> 539.98165 | G35: =IFERROR(G13/G$28,"..") -> 530.9079 | H35: =IFERROR(H13/H$28,"..") -> 522.06914 | I35: =IFERROR(I13/I$28,"..") -> 511.46737 | J35: =IFERROR(J13/J$28,"..") -> 501.16346 | ... AB35: =IFERROR(AB13/AB$28,"..") -> 365.10829 | AC35: =IFERROR(AB35/C35-1,"..") -> -0.35828673
B36: Forests, recreation, hunting, and fishing services (es1) | C36: =IFERROR(C14/C$28,"..") -> 142.20628 | D36: =IFERROR(D14/D$28,"..") -> 139.67738 | E36: =IFERROR(E14/E$28,"..") -> 137.2748 | F36: =IFERROR(F14/F$28,"..") -> 134.96374 | G36: =IFERROR(G14/G$28,"..") -> 132.69583 | H36: =IFERROR(H14/H$28,"..") -> 130.48666 | I36: =IFERROR(I14/I$28,"..") -> 127.83684 | J36: =IFERROR(J14/J$28,"..") -> 125.26147 | ... AB36: =IFERROR(AB14/AB$28,"..") -> 91.255655 | AC36: =IFERROR(AB36/C36-1,"..") -> -0.35828673
B37: Forests, non-wood forest products (es2) | C37: =IFERROR(C15/C$28,"..") -> 263.00417 | D37: =IFERROR(D15/D$28,"..") -> 258.32708 | E37: =IFERROR(E15/E$28,"..") -> 253.88362 | F37: =IFERROR(F15/F$28,"..") -> 249.60941 | G37: =IFERROR(G15/G$28,"..") -> 245.41502 | H37: =IFERROR(H15/H$28,"..") -> 241.32926 | I37: =IFERROR(I15/I$28,"..") -> 236.42854 | J37: =IFERROR(J15/J$28,"..") -> 231.6655 | ... AB37: =IFERROR(AB15/AB$28,"..") -> 168.77326 | AC37: =IFERROR(AB37/C37-1,"..") -> -0.35828673
B38: Forests, water retention services (es3) | C38: =IFERROR(C16/C$28,"..") -> 2241.9864 | D38: =IFERROR(D16/D$28,"..") -> 2202.1164 | E38: =IFERROR(E16/E$28,"..") -> 2164.2381 | F38: =IFERROR(F16/F$28,"..") -> 2127.8024 | G38: =IFERROR(G16/G$28,"..") -> 2092.0472 | H38: =IFERROR(H16/H$28,"..") -> 2057.218 | I38: =IFERROR(I16/I$28,"..") -> 2015.4417 | J38: =IFERROR(J16/J$28,"..") -> 1974.839 | ... AB38: =IFERROR(AB16/AB$28,"..") -> 1438.7124 | AC38: =IFERROR(AB38/C38-1,"..") -> -0.35828673
B39: Mangroves | C39: =IFERROR(C17/C$28,"..") -> 0 | D39: =IFERROR(D17/D$28,"..") -> 0 | E39: =IFERROR(E17/E$28,"..") -> 0 | F39: =IFERROR(F17/F$28,"..") -> 0 | G39: =IFERROR(G17/G$28,"..") -> 0 | H39: =IFERROR(H17/H$28,"..") -> 0 | I39: =IFERROR(I17/I$28,"..") -> 0 | J39: =IFERROR(J17/J$28,"..") -> 0 | ... AB39: =IFERROR(AB17/AB$28,"..") -> 0 | AC39: =IFERROR(AB39/C39-1,"..") -> ..
B40: Fisheries | C40: =IFERROR(C18/C$28,"..") -> 74.836873 | D40: =IFERROR(D18/D$28,"..") -> 71.746951 | E40: =IFERROR(E18/E$28,"..") -> 68.443805 | F40: =IFERROR(F18/F$28,"..") -> 65.467976 | G40: =IFERROR(G18/G$28,"..") -> 62.807147 | H40: =IFERROR(H18/H$28,"..") -> 60.580756 | I40: =IFERROR(I18/I$28,"..") -> 59.269147 | J40: =IFERROR(J18/J$28,"..") -> 58.447301 | ... AB40: =IFERROR(AB18/AB$28,"..") -> 54.000638 | AC40: =IFERROR(AB40/C40-1,"..") -> -0.27842204
B41: Agricultural land | C41: =IFERROR(C19/C$28,"..") -> 5953.3796 | D41: =IFERROR(D19/D$28,"..") -> 5883.2669 | E41: =IFERROR(E19/E$28,"..") -> 5817.4095 | F41: =IFERROR(F19/F$28,"..") -> 5754.6823 | G41: =IFERROR(G19/G$28,"..") -> 5692.4012 | H41: =IFERROR(H19/H$28,"..") -> 5632.55 | I41: =IFERROR(I19/I$28,"..") -> 5575.1393 | J41: =IFERROR(J19/J$28,"..") -> 5520.0685 | ... AB41: =IFERROR(AB19/AB$28,"..") -> 3880.8108 | AC41: =IFERROR(AB41/C41-1,"..") -> -0.34813314
B42: Hydropower energy | C42: =IFERROR(C20/C$28,"..") -> 346.37837 | D42: =IFERROR(D20/D$28,"..") -> 291.32843 | E42: =IFERROR(E20/E$28,"..") -> 352.93178 | F42: =IFERROR(F20/F$28,"..") -> 329.19669 | G42: =IFERROR(G20/G$28,"..") -> 265.17957 | H42: =IFERROR(H20/H$28,"..") -> 352.41256 | I42: =IFERROR(I20/I$28,"..") -> 449.06956 | J42: =IFERROR(J20/J$28,"..") -> 430.09337 | ... AB42: =IFERROR(AB20/AB$28,"..") -> 267.37422 | AC42: =IFERROR(AB42/C42-1,"..") -> -0.22808629
... B49: Foreign liabilities | C49: =IFERROR(C27/C$28,"..") -> 29297.558 | D49: =IFERROR(D27/D$28,"..") -> 32932.664 | E49: =IFERROR(E27/E$28,"..") -> 38198.571 | F49: =IFERROR(F27/F$28,"..") -> 41096.544 | G49: =IFERROR(G27/G$28,"..") -> 43532.217 | H49: =IFERROR(H27/H$28,"..") -> 44010.048 | I49: =IFERROR(I27/I$28,"..") -> 45860.425 | J49: =IFERROR(J27/J$28,"..") -> 29311.499 | ... AB49: =IFERROR(AB27/AB$28,"..") -> 4309.1405 | AC49: =IFERROR(AB49/C49-1,"..") -> -0.8529181
B55: Nominal Wealth, current USD, Millions | C55: 1995 | D55: 1996 | E55: 1997 | F55: 1998 | G55: 1999 | H55: 2000 | I55: 2001 | J55: 2002 | K55: 2003 | L55: 2004 | M55: 2005 | N55: 2006 | O55: 2007 | P55: 2008 | Q55: 2009 | R55: 2010 | S55: 2011 | T55: 2012 | U55: 2013 | V55: 2014 | W55: 2015 | X55: 2016 | Y55: 2017 | Z55: 2018 | AA55: 2019 | AB55: 2020 | AC55: Percent change (1995 to 2020)
A56: 38 | B56: Produced capital | C56: =IFERROR(VLOOKUP(CONCATENATE($C$4,".",C$8),country!$G:$CD,$A56,FALSE)/1000000,"..") -> 564923.39 | D56: =IFERROR(VLOOKUP(CONCATENATE($C$4,".",D$8),country!$G:$CD,$A56,FALSE)/1000000,"..") -> 536423.53 | E56: =IFERROR(VLOOKUP(CONCATENATE($C$4,".",E$8),country!$G:$CD,$A56,FALSE)/1000000,"..") -> 545420.09 | F56: =IFERROR(VLOOKUP(CONCATENATE($C$4,".",F$8),country!$G:$CD,$A56,FALSE)/1000000,"..") -> 568948.96 | G56: =IFERROR(VLOOKUP(CONCATENATE($C$4,".",G$8),country!$G:$CD,$A56,FALSE)/1000000,"..") -> 594111.46 | H56: =IFERROR(VLOOKUP(CONCATENATE($C$4,".",H$8),country!$G:$CD,$A56,FALSE)/1000000,"..") -> 608102.32 | I56: =IFERROR(VLOOKUP(CONCATENATE($C$4,".",I$8),country!$G:$CD,$A56,FALSE)/1000000,"..") -> 622997.8 | J56: =IFERROR(VLOOKUP(CONCATENATE($C$4,".",J$8),country!$G:$CD,$A56,FALSE)/1000000,"..") -> 299800.76 | ... AB56: =IFERROR(VLOOKUP(CONCATENATE($C$4,".",AB$8),country!$G:$CD,$A56,FALSE)/1000000,"..") -> 847346.99 | AC56: =IFERROR(AB56/C56-1,"..") -> 0.49993258
A57: 72 | B57: Human capital | C57: =IFERROR(VLOOKUP(CONCATENATE($C$4,".",C$8),country!$G:$CD,$A57,FALSE)/1000000,"..") -> 1009371.3 | D57: =IFERROR(VLOOKUP(CONCATENATE($C$4,".",D$8),country!$G:$CD,$A57,FALSE)/1000000,"..") -> 1023125.9 | E57: =IFERROR(VLOOKUP(CONCATENATE($C$4,".",E$8),country!$G:$CD,$A57,FALSE)/1000000,"..") -> 1120110.7 | F57: =IFERROR(VLOOKUP(CONCATENATE($C$4,".",F$8),country!$G:$CD,$A57,FALSE)/1000000,"..") -> 1237128.2 | G57: =IFERROR(VLOOKUP(CONCATENATE($C$4,".",G$8),country!$G:$CD,$A57,FALSE)/1000000,"..") -> 1243042.4 | H57: =IFERROR(VLOOKUP(CONCATENATE($C$4,".",H$8),country!$G:$CD,$A57,FALSE)/1000000,"..") -> 1298501.5 | I57: =IFERROR(VLOOKUP(CONCATENATE($C$4,".",I$8),country!$G:$CD,$A57,FALSE)/1000000,"..") -> 1267899.3 | J57: =IFERROR(VLOOKUP(CONCATENATE($C$4,".",J$8),country!$G:$CD,$A57,FALSE)/1000000,"..") -> 362791.22 | ... AB57: =IFERROR(VLOOKUP(CONCATENATE($C$4,".",AB$8),country!$G:$CD,$A57,FALSE)/1000000,"..") -> 2029767.7 | AC57: =IFERROR(AB57/C57-1,"..") -> 1.0109227
A58: 43 | B58: Renewable natural capital | C58: =IFERROR(VLOOKUP(CONCATENATE($C$4,".",C$8),country!$G:$CD,$A58,FALSE)/1000000,"..") -> 201992.04 | D58: =IFERROR(VLOOKUP(CONCATENATE($C$4,".",D$8),country!$G:$CD,$A58,FALSE)/1000000,"..") -> 193919.49 | E58: =IFERROR(VLOOKUP(CONCATENATE($C$4,".",E$8),country!$G:$CD,$A58,FALSE)/1000000,"..") -> 208521.59 | F58: =IFERROR(VLOOKUP(CONCATENATE($C$4,".",F$8),country!$G:$CD,$A58,FALSE)/1000000,"..") -> 201196.21 | G58: =IFERROR(VLOOKUP(CONCATENATE($C$4,".",G$8),country!$G:$CD,$A58,FALSE)/1000000,"..") -> 177817.31 | H58: =IFERROR(VLOOKUP(CONCATENATE($C$4,".",H$8),country!$G:$CD,$A58,FALSE)/1000000,"..") -> 192911.49 | I58: =IFERROR(VLOOKUP(CONCATENATE($C$4,".",I$8),country!$G:$CD,$A58,FALSE)/1000000,"..") -> 178083.11 | J58: =IFERROR(VLOOKUP(CONCATENATE($C$4,".",J$8),country!$G:$CD,$A58,FALSE)/1000000,"..") -> 99794.43 | ... AB58: =IFERROR(VLOOKUP(CONCATENATE($C$4,".",AB$8),country!$G:$CD,$A58,FALSE)/1000000,"..") -> 263120.63 | AC58: =IFERROR(AB58/C58-1,"..") -> 0.3026287
A59: 47 | B59: Forests, timber | C59: =IFERROR(VLOOKUP(CONCATENATE($C$4,".",C$8),country!$G:$CD,$A59,FALSE)/1000000,"..") -> 6116.99 | D59: =IFERROR(VLOOKUP(CONCATENATE($C$4,".",D$8),country!$G:$CD,$A59,FALSE)/1000000,"..") -> 5652.7735 | E59: =IFERROR(VLOOKUP(CONCATENATE($C$4,".",E$8),country!$G:$CD,$A59,FALSE)/1000000,"..") -> 4775.9178 | F59: =IFERROR(VLOOKUP(CONCATENATE($C$4,".",F$8),country!$G:$CD,$A59,FALSE)/1000000,"..") -> 4381.5843 | G59: =IFERROR(VLOOKUP(CONCATENATE($C$4,".",G$8),country!$G:$CD,$A59,FALSE)/1000000,"..") -> 3522.4437 | H59: =IFERROR(VLOOKUP(CONCATENATE($C$4,".",H$8),country!$G:$CD,$A59,FALSE)/1000000,"..") -> 2789.3785 | I59: =IFERROR(VLOOKUP(CONCATENATE($C$4,".",I$8),country!$G:$CD,$A59,FALSE)/1000000,"..") -> 2577.9761 | J59: =IFERROR(VLOOKUP(CONCATENATE($C$4,".",J$8),country!$G:$CD,$A59,FALSE)/1000000,"..") -> 4698.6826 | ... AB59: =IFERROR(VLOOKUP(CONCATENATE($C$4,".",AB$8),country!$G:$CD,$A59,FALSE)/1000000,"..") -> 16886.694 | AC59: =IFERROR(AB59/C59-1,"..") -> 1.7606214
A60: 49 | B60: Forests, recreation, hunting, and fishing services (es1) | C60: =IFERROR(VLOOKUP(CONCATENATE($C$4,".",C$8),country!$G:$CD,$A60,FALSE)/1000000,"..") -> 1874.6324 | D60: =IFERROR(VLOOKUP(CONCATENATE($C$4,".",D$8),country!$G:$CD,$A60,FALSE)/1000000,"..") -> 2187.0712 | E60: =IFERROR(VLOOKUP(CONCATENATE($C$4,".",E$8),country!$G:$CD,$A60,FALSE)/1000000,"..") -> 2317.9279 | F60: =IFERROR(VLOOKUP(CONCATENATE($C$4,".",F$8),country!$G:$CD,$A60,FALSE)/1000000,"..") -> 2464.9578 | G60: =IFERROR(VLOOKUP(CONCATENATE($C$4,".",G$8),country!$G:$CD,$A60,FALSE)/1000000,"..") -> 2334.1012 | H60: =IFERROR(VLOOKUP(CONCATENATE($C$4,".",H$8),country!$G:$CD,$A60,FALSE)/1000000,"..") -> 2348.8042 | I60: =IFERROR(VLOOKUP(CONCATENATE($C$4,".",I$8),country!$G:$CD,$A60,FALSE)/1000000,"..") -> 2026.0733 | J60: =IFERROR(VLOOKUP(CONCATENATE($C$4,".",J$8),country!$G:$CD,$A60,FALSE)/1000000,"..") -> 1261.5173 | ... AB60: =IFERROR(VLOOKUP(CONCATENATE($C$4,".",AB$8),country!$G:$CD,$A60,FALSE)/1000000,"..") -> 1251.2252 | AC60: =IFERROR(AB60/C60-1,"..") -> -0.33254902
A61: 50 | B61: Forests, non-wood forest products (es2) | C61: =IFERROR(VLOOKUP(CONCATENATE($C$4,".",C$8),country!$G:$CD,$A61,FALSE)/1000000,"..") -> 6599.2944 | D61: =IFERROR(VLOOKUP(CONCATENATE($C$4,".",D$8),country!$G:$CD,$A61,FALSE)/1000000,"..") -> 6682.949 | E61: =IFERROR(VLOOKUP(CONCATENATE($C$4,".",E$8),country!$G:$CD,$A61,FALSE)/1000000,"..") -> 6772.879 | F61: =IFERROR(VLOOKUP(CONCATENATE($C$4,".",F$8),country!$G:$CD,$A61,FALSE)/1000000,"..") -> 6820.5783 | G61: =IFERROR(VLOOKUP(CONCATENATE($C$4,".",G$8),country!$G:$CD,$A61,FALSE)/1000000,"..") -> 6902.3993 | H61: =IFERROR(VLOOKUP(CONCATENATE($C$4,".",H$8),country!$G:$CD,$A61,FALSE)/1000000,"..") -> 7049.4561 | I61: =IFERROR(VLOOKUP(CONCATENATE($C$4,".",I$8),country!$G:$CD,$A61,FALSE)/1000000,"..") -> 7006.0894 | J61: =IFERROR(VLOOKUP(CONCATENATE($C$4,".",J$8),country!$G:$CD,$A61,FALSE)/1000000,"..") -> 6850.691 | ... AB61: =IFERROR(VLOOKUP(CONCATENATE($C$4,".",AB$8),country!$G:$CD,$A61,FALSE)/1000000,"..") -> 7748.3836 | AC61: =IFERROR(AB61/C61-1,"..") -> 0.17412305
A62: 51 | B62: Forests, water retention services (es3) | C62: =IFERROR(VLOOKUP(CONCATENATE($C$4,".",C$8),country!$G:$CD,$A62,FALSE)/1000000,"..") -> 47462.423 | D62: =IFERROR(VLOOKUP(CONCATENATE($C$4,".",D$8),country!$G:$CD,$A62,FALSE)/1000000,"..") -> 48157.849 | E62: =IFERROR(VLOOKUP(CONCATENATE($C$4,".",E$8),country!$G:$CD,$A62,FALSE)/1000000,"..") -> 48777.591 | F62: =IFERROR(VLOOKUP(CONCATENATE($C$4,".",F$8),country!$G:$CD,$A62,FALSE)/1000000,"..") -> 49421.286 | G62: =IFERROR(VLOOKUP(CONCATENATE($C$4,".",G$8),country!$G:$CD,$A62,FALSE)/1000000,"..") -> 50177.945 | H62: =IFERROR(VLOOKUP(CONCATENATE($C$4,".",H$8),country!$G:$CD,$A62,FALSE)/1000000,"..") -> 51279.587 | I62: =IFERROR(VLOOKUP(CONCATENATE($C$4,".",I$8),country!$G:$CD,$A62,FALSE)/1000000,"..") -> 51479.319 | J62: =IFERROR(VLOOKUP(CONCATENATE($C$4,".",J$8),country!$G:$CD,$A62,FALSE)/1000000,"..") -> 23947.266 | ... AB62: =IFERROR(VLOOKUP(CONCATENATE($C$4,".",AB$8),country!$G:$CD,$A62,FALSE)/1000000,"..") -> 66021.066 | AC62: =IFERROR(AB62/C62-1,"..") -> 0.39101759
A63: 48 | B63: Mangroves | C63: =IFERROR(VLOOKUP(CONCATENATE($C$4,".",C$8),country!$G:$CD,$A63,FALSE)/1000000,"..") -> 0 | D63: =IFERROR(VLOOKUP(CONCATENATE($C$4,".",D$8),country!$G:$CD,$A63,FALSE)/1000000,"..") -> 0 | E63: =IFERROR(VLOOKUP(CONCATENATE($C$4,".",E$8),country!$G:$CD,$A63,FALSE)/1000000,"..") -> 0 | F63: =IFERROR(VLOOKUP(CONCATENATE($C$4,".",F$8),country!$G:$CD,$A63,FALSE)/1000000,"..") -> 0 | G63: =IFERROR(VLOOKUP(CONCATENATE($C$4,".",G$8),country!$G:$CD,$A63,FALSE)/1000000,"..") -> 0 | H63: =IFERROR(VLOOKUP(CONCATENATE($C$4,".",H$8),country!$G:$CD,$A63,FALSE)/1000000,"..") -> 0 | I63: =IFERROR(VLOOKUP(CONCATENATE($C$4,".",I$8),country!$G:$CD,$A63,FALSE)/1000000,"..") -> 0 | J63: =IFERROR(VLOOKUP(CONCATENATE($C$4,".",J$8),country!$G:$CD,$A63,FALSE)/1000000,"..") -> 0 | ... AB63: =IFERROR(VLOOKUP(CONCATENATE($C$4,".",AB$8),country!$G:$CD,$A63,FALSE)/1000000,"..") -> 0 | AC63: =IFERROR(AB63/C63-1,"..") -> ..
A64: 52 | B64: Fisheries | C64: =IFERROR(VLOOKUP(CONCATENATE($C$4,".",C$8),country!$G:$CD,$A64,FALSE)/1000000,"..") -> 14469.124 | D64: =IFERROR(VLOOKUP(CONCATENATE($C$4,".",D$8),country!$G:$CD,$A64,FALSE)/1000000,"..") -> 15910.575 | E64: =IFERROR(VLOOKUP(CONCATENATE($C$4,".",E$8),country!$G:$CD,$A64,FALSE)/1000000,"..") -> 15460.123 | F64: =IFERROR(VLOOKUP(CONCATENATE($C$4,".",F$8),country!$G:$CD,$A64,FALSE)/1000000,"..") -> 13346.241 | G64: =IFERROR(VLOOKUP(CONCATENATE($C$4,".",G$8),country!$G:$CD,$A64,FALSE)/1000000,"..") -> 12981.449 | H64: =IFERROR(VLOOKUP(CONCATENATE($C$4,".",H$8),country!$G:$CD,$A64,FALSE)/1000000,"..") -> 9952.1084 | I64: =IFERROR(VLOOKUP(CONCATENATE($C$4,".",I$8),country!$G:$CD,$A64,FALSE)/1000000,"..") -> 11407.161 | J64: =IFERROR(VLOOKUP(CONCATENATE($C$4,".",J$8),country!$G:$CD,$A64,FALSE)/1000000,"..") -> 4840.66 | ... AB64: =IFERROR(VLOOKUP(CONCATENATE($C$4,".",AB$8),country!$G:$CD,$A64,FALSE)/1000000,"..") -> 2932.7275 | AC64: =IFERROR(AB64/C64-1,"..") -> -0.79731133
A65: 44 | B65: Agricultural land | C65: =IFERROR(VLOOKUP(CONCATENATE($C$4,".",C$8),country!$G:$CD,$A65,FALSE)/1000000,"..") -> 94638.927 | D65: =IFERROR(VLOOKUP(CONCATENATE($C$4,".",D$8),country!$G:$CD,$A65,FALSE)/1000000,"..") -> 93778.027 | E65: =IFERROR(VLOOKUP(CONCATENATE($C$4,".",E$8),country!$G:$CD,$A65,FALSE)/1000000,"..") -> 100142.25 | F65: =IFERROR(VLOOKUP(CONCATENATE($C$4,".",F$8),country!$G:$CD,$A65,FALSE)/1000000,"..") -> 97402.013 | G65: =IFERROR(VLOOKUP(CONCATENATE($C$4,".",G$8),country!$G:$CD,$A65,FALSE)/1000000,"..") -> 85161.07 | H65: =IFERROR(VLOOKUP(CONCATENATE($C$4,".",H$8),country!$G:$CD,$A65,FALSE)/1000000,"..") -> 88911.186 | I65: =IFERROR(VLOOKUP(CONCATENATE($C$4,".",I$8),country!$G:$CD,$A65,FALSE)/1000000,"..") -> 57932.381 | J65: =IFERROR(VLOOKUP(CONCATENATE($C$4,".",J$8),country!$G:$CD,$A65,FALSE)/1000000,"..") -> 54687.073 | ... AB65: =IFERROR(VLOOKUP(CONCATENATE($C$4,".",AB$8),country!$G:$CD,$A65,FALSE)/1000000,"..") -> 168280.53 | AC65: =IFERROR(AB65/C65-1,"..") -> 0.77813231
A66: 53 | B66: Hydropower energy | C66: =IFERROR(VLOOKUP(CONCATENATE($C$4,".",C$8),country!$G:$CD,$A66,FALSE)/1000000,"..") -> 30830.649 | D66: =IFERROR(VLOOKUP(CONCATENATE($C$4,".",D$8),country!$G:$CD,$A66,FALSE)/1000000,"..") -> 21550.242 | E66: =IFERROR(VLOOKUP(CONCATENATE($C$4,".",E$8),country!$G:$CD,$A66,FALSE)/1000000,"..") -> 30274.901 | F66: =IFERROR(VLOOKUP(CONCATENATE($C$4,".",F$8),country!$G:$CD,$A66,FALSE)/1000000,"..") -> 27359.553 | G66: =IFERROR(VLOOKUP(CONCATENATE($C$4,".",G$8),country!$G:$CD,$A66,FALSE)/1000000,"..") -> 16737.906 | H66: =IFERROR(VLOOKUP(CONCATENATE($C$4,".",H$8),country!$G:$CD,$A66,FALSE)/1000000,"..") -> 30580.964 | I66: =IFERROR(VLOOKUP(CONCATENATE($C$4,".",I$8),country!$G:$CD,$A66,FALSE)/1000000,"..") -> 45654.105 | J66: =IFERROR(VLOOKUP(CONCATENATE($C$4,".",J$8),country!$G:$CD,$A66,FALSE)/1000000,"..") -> 3508.539 | ... AB66: =IFERROR(VLOOKUP(CONCATENATE($C$4,".",AB$8),country!$G:$CD,$A66,FALSE)/1000000,"..") -> 0 | AC66: =IFERROR(AB66/C66-1,"..") -> -1
A67: 54 | B67: Nonrenewable natural capital | C67: =IFERROR(VLOOKUP(CONCATENATE($C$4,".",C$8),country!$G:$CD,$A67,FALSE)/1000000,"..") -> 26815.946 | D67: =IFERROR(VLOOKUP(CONCATENATE($C$4,".",D$8),country!$G:$CD,$A67,FALSE)/1000000,"..") -> 33738.996 | E67: =IFERROR(VLOOKUP(CONCATENATE($C$4,".",E$8),country!$G:$CD,$A67,FALSE)/1000000,"..") -> 31803.969 | F67: =IFERROR(VLOOKUP(CONCATENATE($C$4,".",F$8),country!$G:$CD,$A67,FALSE)/1000000,"..") -> 25545.965 | G67: =IFERROR(VLOOKUP(CONCATENATE($C$4,".",G$8),country!$G:$CD,$A67,FALSE)/1000000,"..") -> 36061.158 | H67: =IFERROR(VLOOKUP(CONCATENATE($C$4,".",H$8),country!$G:$CD,$A67,FALSE)/1000000,"..") -> 73855.333 | I67: =IFERROR(VLOOKUP(CONCATENATE($C$4,".",I$8),country!$G:$CD,$A67,FALSE)/1000000,"..") -> 47896.186 | J67: =IFERROR(VLOOKUP(CONCATENATE($C$4,".",J$8),country!$G:$CD,$A67,FALSE)/1000000,"..") -> 53922.518 | ... AB67: =IFERROR(VLOOKUP(CONCATENATE($C$4,".",AB$8),country!$G:$CD,$A67,FALSE)/1000000,"..") -> 35044.672 | AC67: =IFERROR(AB67/C67-1,"..") -> 0.30685946
... A71: 58 | B71: Metals and minerals | C71: =IFERROR(VLOOKUP(CONCATENATE($C$4,".",C$8),country!$G:$CD,$A71,FALSE)/1000000,"..") -> 522.19261 | D71: =IFERROR(VLOOKUP(CONCATENATE($C$4,".",D$8),country!$G:$CD,$A71,FALSE)/1000000,"..") -> 515.51385 | E71: =IFERROR(VLOOKUP(CONCATENATE($C$4,".",E$8),country!$G:$CD,$A71,FALSE)/1000000,"..") -> 481.56146 | F71: =IFERROR(VLOOKUP(CONCATENATE($C$4,".",F$8),country!$G:$CD,$A71,FALSE)/1000000,"..") -> 348.59611 | G71: =IFERROR(VLOOKUP(CONCATENATE($C$4,".",G$8),country!$G:$CD,$A71,FALSE)/1000000,"..") -> 485.32804 | H71: =IFERROR(VLOOKUP(CONCATENATE($C$4,".",H$8),country!$G:$CD,$A71,FALSE)/1000000,"..") -> 297.47728 | I71: =IFERROR(VLOOKUP(CONCATENATE($C$4,".",I$8),country!$G:$CD,$A71,FALSE)/1000000,"..") -> 232.40077 | J71: =IFERROR(VLOOKUP(CONCATENATE($C$4,".",J$8),country!$G:$CD,$A71,FALSE)/1000000,"..") -> 3105.8065 | ... AB71: =IFERROR(VLOOKUP(CONCATENATE($C$4,".",AB$8),country!$G:$CD,$A71,FALSE)/1000000,"..") -> 35044.672 | AC71: =IFERROR(AB71/C71-1,"..") -> 66.110624
B73: Shares of wealth (based on nominal wealth) | C73: 1995 | D73: 1996 | E73: 1997 | F73: 1998 | G73: 1999 | H73: 2000 | I73: 2001 | J73: 2002 | K73: 2003 | L73: 2004 | M73: 2005 | N73: 2006 | O73: 2007 | P73: 2008 | Q73: 2009 | R73: 2010 | S73: 2011 | T73: 2012 | U73: 2013 | V73: 2014 | W73: 2015 | X73: 2016 | Y73: 2017 | Z73: 2018 | AA73: 2019 | AB73: 2020
B74: Produced capital | C74: =IFERROR(C56/SUM(C56,C57,C58,C67), "..") -> 0.31330627 | D74: =IFERROR(D56/SUM(D56,D57,D58,D67), "..") -> 0.30014613 | E74: =IFERROR(E56/SUM(E56,E57,E58,E67), "..") -> 0.28618112 | F74: =IFERROR(F56/SUM(F56,F57,F58,F67), "..") -> 0.27988172 | G74: =IFERROR(G56/SUM(G56,G57,G58,G67), "..") -> 0.2896646 | H74: =IFERROR(H56/SUM(H56,H57,H58,H67), "..") -> 0.27979687 | I74: =IFERROR(I56/SUM(I56,I57,I58,I67), "..") -> 0.2943005 | J74: =IFERROR(J56/SUM(J56,J57,J58,J67), "..") -> 0.36726385 | ... AB74: =IFERROR(AB56/SUM(AB56,AB57,AB58,AB67), "..") -> 0.26685741
B75: Human capital | C75: =IFERROR(C57/SUM(C56,C57,C58,C67), "..") -> 0.55979691 | D75: =IFERROR(D57/SUM(D56,D57,D58,D67), "..") -> 0.57247167 | E75: =IFERROR(E57/SUM(E56,E57,E58,E67), "..") -> 0.58772041 | F75: =IFERROR(F57/SUM(F56,F57,F58,F67), "..") -> 0.60857754 | G75: =IFERROR(G57/SUM(G56,G57,G58,G67), "..") -> 0.60605695 | H75: =IFERROR(H57/SUM(H56,H57,H58,H67), "..") -> 0.59745977 | I75: =IFERROR(I57/SUM(I56,I57,I58,I67), "..") -> 0.59894821 | J75: =IFERROR(J57/SUM(J56,J57,J58,J67), "..") -> 0.44442883 | ... AB75: =IFERROR(AB57/SUM(AB56,AB57,AB58,AB67), "..") -> 0.63924054
B76: Renewable Natural Capital | C76: =IFERROR(C58/SUM(C56,C57,C58,C67), "..") -> 0.1120247 | D76: =IFERROR(D58/SUM(D56,D57,D58,D67), "..") -> 0.10850416 | E76: =IFERROR(E58/SUM(E56,E57,E58,E67), "..") -> 0.10941097 | F76: =IFERROR(F58/SUM(F56,F57,F58,F67), "..") -> 0.098973977 | G76: =IFERROR(G58/SUM(G56,G57,G58,G67), "..") -> 0.086696495 | H76: =IFERROR(H58/SUM(H56,H57,H58,H67), "..") -> 0.088761428 | I76: =IFERROR(I58/SUM(I56,I57,I58,I67), "..") -> 0.084125413 | J76: =IFERROR(J58/SUM(J56,J57,J58,J67), "..") -> 0.12225081 | ... AB76: =IFERROR(AB58/SUM(AB56,AB57,AB58,AB67), "..") -> 0.082865331
B77: Nonrenewable Natural capital | C77: =IFERROR(C67/SUM(C56,C57,C58,C67), "..") -> 0.014872112 | D77: =IFERROR(D67/SUM(D56,D57,D58,D67), "..") -> 0.018878048 | E77: =IFERROR(E67/SUM(E56,E57,E58,E67), "..") -> 0.016687496 | F77: =IFERROR(F67/SUM(F56,F57,F58,F67), "..") -> 0.012566766 | G77: =IFERROR(G67/SUM(G56,G57,G58,G67), "..") -> 0.017581955 | H77: =IFERROR(H67/SUM(H56,H57,H58,H67), "..") -> 0.033981931 | I77: =IFERROR(I67/SUM(I56,I57,I58,I67), "..") -> 0.022625877 | J77: =IFERROR(J67/SUM(J56,J57,J58,J67), "..") -> 0.066056509 | ... AB77: =IFERROR(AB67/SUM(AB56,AB57,AB58,AB67), "..") -> 0.011036719
B79: Share of renewable natural capital (based on nominal wealth) | C79: 1995 | D79: 1996 | E79: 1997 | F79: 1998 | G79: 1999 | H79: 2000 | I79: 2001 | J79: 2002 | K79: 2003 | L79: 2004 | M79: 2005 | N79: 2006 | O79: 2007 | P79: 2008 | Q79: 2009 | R79: 2010 | S79: 2011 | T79: 2012 | U79: 2013 | V79: 2014 | W79: 2015 | X79: 2016 | Y79: 2017 | Z79: 2018 | AA79: 2019 | AB79: 2020
B80: Renewable Natural capital | C80: =IFERROR(C58/C$58,"..") -> 1 | D80: =IFERROR(D58/D$58,"..") -> 1 | E80: =IFERROR(E58/E$58,"..") -> 1 | F80: =IFERROR(F58/F$58,"..") -> 1 | G80: =IFERROR(G58/G$58,"..") -> 1 | H80: =IFERROR(H58/H$58,"..") -> 1 | I80: =IFERROR(I58/I$58,"..") -> 1 | J80: =IFERROR(J58/J$58,"..") -> 1 | ... AB80: =IFERROR(AB58/AB$58,"..") -> 1
B81: Forests, timber | C81: =IFERROR(C59/C$58,"..") -> 0.030283322 | D81: =IFERROR(D59/D$58,"..") -> 0.029150105 | E81: =IFERROR(E59/E$58,"..") -> 0.022903709 | F81: =IFERROR(F59/F$58,"..") -> 0.021777668 | G81: =IFERROR(G59/G$58,"..") -> 0.01980934 | H81: =IFERROR(H59/H$58,"..") -> 0.01445937 | I81: =IFERROR(I59/I$58,"..") -> 0.014476253 | J81: =IFERROR(J59/J$58,"..") -> 0.047083616 | ... AB81: =IFERROR(AB59/AB$58,"..") -> 0.064178524
B82: Forests, recreation, hunting, and fishing services | C82: =IFERROR(C60/C$58,"..") -> 0.0092807242 | D82: =IFERROR(D60/D$58,"..") -> 0.011278243 | E82: =IFERROR(E60/E$58,"..") -> 0.011116009 | F82: =IFERROR(F60/F$58,"..") -> 0.012251512 | G82: =IFERROR(G60/G$58,"..") -> 0.0131264 | H82: =IFERROR(H60/H$58,"..") -> 0.012175554 | I82: =IFERROR(I60/I$58,"..") -> 0.011377123 | J82: =IFERROR(J60/J$58,"..") -> 0.01264116 | ... AB82: =IFERROR(AB60/AB$58,"..") -> 0.0047553293
B83: Forests, non-wood forest products | C83: =IFERROR(C61/C$58,"..") -> 0.032671061 | D83: =IFERROR(D61/D$58,"..") -> 0.034462493 | E83: =IFERROR(E61/E$58,"..") -> 0.032480469 | F83: =IFERROR(F61/F$58,"..") -> 0.033900132 | G83: =IFERROR(G61/G$58,"..") -> 0.038817364 | H83: =IFERROR(H61/H$58,"..") -> 0.036542439 | I83: =IFERROR(I61/I$58,"..") -> 0.039341685 | J83: =IFERROR(J61/J$58,"..") -> 0.06864803 | ... AB83: =IFERROR(AB61/AB$58,"..") -> 0.029448028
B84: Forests, water retention services | C84: =IFERROR(C62/C$58,"..") -> 0.23497175 | D84: =IFERROR(D62/D$58,"..") -> 0.2483394 | E84: =IFERROR(E62/E$58,"..") -> 0.23392106 | F84: =IFERROR(F62/F$58,"..") -> 0.24563726 | G84: =IFERROR(G62/G$58,"..") -> 0.28218818 | H84: =IFERROR(H62/H$58,"..") -> 0.26581926 | I84: =IFERROR(I62/I$58,"..") -> 0.28907469 | J84: =IFERROR(J62/J$58,"..") -> 0.23996596 | ... AB84: =IFERROR(AB62/AB$58,"..") -> 0.25091558
B85: Mangroves | C85: =IFERROR(C63/C$58,"..") -> 0 | D85: =IFERROR(D63/D$58,"..") -> 0 | E85: =IFERROR(E63/E$58,"..") -> 0 | F85: =IFERROR(F63/F$58,"..") -> 0 | G85: =IFERROR(G63/G$58,"..") -> 0 | H85: =IFERROR(H63/H$58,"..") -> 0 | I85: =IFERROR(I63/I$58,"..") -> 0 | J85: =IFERROR(J63/J$58,"..") -> 0 | ... AB85: =IFERROR(AB63/AB$58,"..") -> 0
B86: Fisheries | C86: =IFERROR(C64/C$58,"..") -> 0.071632149 | D86: =IFERROR(D64/D$58,"..") -> 0.082047325 | E86: =IFERROR(E64/E$58,"..") -> 0.074141596 | F86: =IFERROR(F64/F$58,"..") -> 0.066334456 | G86: =IFERROR(G64/G$58,"..") -> 0.073004416 | H86: =IFERROR(H64/H$58,"..") -> 0.051588988 | I86: =IFERROR(I64/I$58,"..") -> 0.064055268 | J86: =IFERROR(J64/J$58,"..") -> 0.048506314 | ... AB86: =IFERROR(AB64/AB$58,"..") -> 0.011145943
B87: Agricultural Land | C87: =IFERROR(C65/C$58,"..") -> 0.468528 | D87: =IFERROR(D65/D$58,"..") -> 0.48359259 | E87: =IFERROR(E65/E$58,"..") -> 0.48024883 | F87: =IFERROR(F65/F$58,"..") -> 0.48411454 | G87: =IFERROR(G65/G$58,"..") -> 0.47892451 | H87: =IFERROR(H65/H$58,"..") -> 0.4608911 | I87: =IFERROR(I65/I$58,"..") -> 0.32531093 | J87: =IFERROR(J65/J$58,"..") -> 0.54799725 | ... AB87: =IFERROR(AB65/AB$58,"..") -> 0.63955659
B88: Hydropower energy | C88: =IFERROR(C66/C$58,"..") -> 0.15263299 | D88: =IFERROR(D66/D$58,"..") -> 0.11112984 | E88: =IFERROR(E66/E$58,"..") -> 0.14518833 | F88: =IFERROR(F66/F$58,"..") -> 0.13598443 | G88: =IFERROR(G66/G$58,"..") -> 0.094129786 | H88: =IFERROR(H66/H$58,"..") -> 0.15852329 | I88: =IFERROR(I66/I$58,"..") -> 0.25636405 | J88: =IFERROR(J66/J$58,"..") -> 0.035157664 | ... AB88: =IFERROR(AB66/AB$58,"..") -> 0
B90: Share of nonrenewable natural capital (based on nominal wealth) | C90: 1995 | D90: 1996 | E90: 1997 | F90: 1998 | G90: 1999 | H90: 2000 | I90: 2001 | J90: 2002 | K90: 2003 | L90: 2004 | M90: 2005 | N90: 2006 | O90: 2007 | P90: 2008 | Q90: 2009 | R90: 2010 | S90: 2011 | T90: 2012 | U90: 2013 | V90: 2014 | W90: 2015 | X90: 2016 | Y90: 2017 | Z90: 2018 | AA90: 2019 | AB90: 2020
B91: Nonrenewable Natural capital | C91: =IFERROR(C67/C$67,"..") -> 1 | D91: =IFERROR(D67/D$67,"..") -> 1 | E91: =IFERROR(E67/E$67,"..") -> 1 | F91: =IFERROR(F67/F$67,"..") -> 1 | G91: =IFERROR(G67/G$67,"..") -> 1 | H91: =IFERROR(H67/H$67,"..") -> 1 | I91: =IFERROR(I67/I$67,"..") -> 1 | J91: =IFERROR(J67/J$67,"..") -> 1 | ... AB91: =IFERROR(AB67/AB$67,"..") -> 1
B92: Oil | C92: =IFERROR(C68/C$67,"..") -> 0.73759959 | D92: =IFERROR(D68/D$67,"..") -> 0.75608402 | E92: =IFERROR(E68/E$67,"..") -> 0.71898695 | F92: =IFERROR(F68/F$67,"..") -> 0.59457254 | G92: =IFERROR(G68/G$67,"..") -> 0.62161264 | H92: =IFERROR(H68/H$67,"..") -> 0.71054626 | I92: =IFERROR(I68/I$67,"..") -> 0.62548756 | J92: =IFERROR(J68/J$67,"..") -> 0.63214847 | ... AB92: =IFERROR(AB68/AB$67,"..") -> 0
B93: Natural Gas | C93: =IFERROR(C69/C$67,"..") -> 0.2429272 | D93: =IFERROR(D69/D$67,"..") -> 0.22863651 | E93: =IFERROR(E69/E$67,"..") -> 0.2658715 | F93: =IFERROR(F69/F$67,"..") -> 0.39178162 | G93: =IFERROR(G69/G$67,"..") -> 0.36492889 | H93: =IFERROR(H69/H$67,"..") -> 0.2854259 | I93: =IFERROR(I69/I$67,"..") -> 0.36966027 | J93: =IFERROR(J69/J$67,"..") -> 0.31025396 | ... AB93: =IFERROR(AB69/AB$67,"..") -> 0
B94: Coal | C94: =IFERROR(C70/C$67,"..") -> 0 | D94: =IFERROR(D70/D$67,"..") -> 0 | E94: =IFERROR(E70/E$67,"..") -> 0 | F94: =IFERROR(F70/F$67,"..") -> 0 | G94: =IFERROR(G70/G$67,"..") -> 0 | H94: =IFERROR(H70/H$67,"..") -> 0 | I94: =IFERROR(I70/I$67,"..") -> 0 | J94: =IFERROR(J70/J$67,"..") -> 0 | ... AB94: =IFERROR(AB70/AB$67,"..") -> 0
B95: Metals and Minerals | C95: =IFERROR(C71/C$67,"..") -> 0.019473213 | D95: =IFERROR(D71/D$67,"..") -> 0.015279466 | E95: =IFERROR(E71/E$67,"..") -> 0.015141552 | F95: =IFERROR(F71/F$67,"..") -> 0.013645838 | G95: =IFERROR(G71/G$67,"..") -> 0.01345847 | H95: =IFERROR(H71/H$67,"..") -> 0.0040278375 | I95: =IFERROR(I71/I$67,"..") -> 0.0048521768 | J95: =IFERROR(J71/J$67,"..") -> 0.057597579 | ... AB95: =IFERROR(AB71/AB$67,"..") -> 1
B97: Share of total natural capital (based on nominal wealth) | C97: 1995 | D97: 1996 | E97: 1997 | F97: 1998 | G97: 1999 | H97: 2000 | I97: 2001 | J97: 2002 | K97: 2003 | L97: 2004 | M97: 2005 | N97: 2006 | O97: 2007 | P97: 2008 | Q97: 2009 | R97: 2010 | S97: 2011 | T97: 2012 | U97: 2013 | V97: 2014 | W97: 2015 | X97: 2016 | Y97: 2017 | Z97: 2018 | AA97: 2019 | AB97: 2020
B98: Forests, timber | C98: =IFERROR(C59/SUM(C58, C67),"") -> 0.026734163 | D98: =IFERROR(D59/SUM(D58, D67),"") -> 0.024830059 | E98: =IFERROR(E59/SUM(E58, E67),"") -> 0.0198727 | F98: =IFERROR(F59/SUM(F58, F67),"") -> 0.019324081 | G98: =IFERROR(G59/SUM(G58, G67),"") -> 0.01646937 | H98: =IFERROR(H59/SUM(H58, H67),"") -> 0.010456242 | I98: =IFERROR(I59/SUM(I58, I67),"") -> 0.011408019 | J98: =IFERROR(J59/SUM(J58, J67),"") -> 0.030567108 | ... AB98: =IFERROR(AB59/SUM(AB58, AB67),"") -> 0.056635341
B99: Forests, recreation, hunting, and fishing services | C99: =IFERROR(C60/SUM(C58, C67),"") -> 0.0081930376 | D99: =IFERROR(D60/SUM(D58, D67),"") -> 0.0096068072 | E99: =IFERROR(E60/SUM(E58, E67),"") -> 0.0096449495 | F99: =IFERROR(F60/SUM(F58, F67),"") -> 0.010871192 | G99: =IFERROR(G60/SUM(G58, G67),"") -> 0.010913212 | H99: =IFERROR(H60/SUM(H58, H67),"") -> 0.0088047088 | I99: =IFERROR(I60/SUM(I58, I67),"") -> 0.0089657477 | J99: =IFERROR(J60/SUM(J58, J67),"") -> 0.0082067551 | ... AB99: =IFERROR(AB60/SUM(AB58, AB67),"") -> 0.0041964147
B100: Forests, non-wood forest products | C100: =IFERROR(C61/SUM(C58, C67),"") -> 0.028842063 | D100: =IFERROR(D61/SUM(D58, D67),"") -> 0.02935515 | E100: =IFERROR(E61/SUM(E58, E67),"") -> 0.0281821 | F100: =IFERROR(F61/SUM(F58, F67),"") -> 0.030080765 | G100: =IFERROR(G61/SUM(G58, G67),"") -> 0.03227253 | H100: =IFERROR(H61/SUM(H58, H67),"") -> 0.026425536 | I100: =IFERROR(I61/SUM(I58, I67),"") -> 0.031003236 | J100: =IFERROR(J61/SUM(J58, J67),"") -> 0.044566921 | ... AB100: =IFERROR(AB61/SUM(AB58, AB67),"") -> 0.025986872
B101: Forests, water retention services | C101: =IFERROR(C62/SUM(C58, C67),"") -> 0.20743342 | D101: =IFERROR(D62/SUM(D58, D67),"") -> 0.21153549 | E101: =IFERROR(E62/SUM(E58, E67),"") -> 0.20296464 | F101: =IFERROR(F62/SUM(F58, F67),"") -> 0.21796247 | G101: =IFERROR(G62/SUM(G58, G67),"") -> 0.23460961 | H101: =IFERROR(H62/SUM(H58, H67),"") -> 0.19222626 | I101: =IFERROR(I62/SUM(I58, I67),"") -> 0.22780547 | J101: =IFERROR(J62/SUM(J58, J67),"") -> 0.15578807 | ... AB101: =IFERROR(AB62/SUM(AB58, AB67),"") -> 0.22142438
B102: Mangroves | C102: =IFERROR(C63/SUM(C58, C67),"") -> 0 | D102: =IFERROR(D63/SUM(D58, D67),"") -> 0 | E102: =IFERROR(E63/SUM(E58, E67),"") -> 0 | F102: =IFERROR(F63/SUM(F58, F67),"") -> 0 | G102: =IFERROR(G63/SUM(G58, G67),"") -> 0 | H102: =IFERROR(H63/SUM(H58, H67),"") -> 0 | I102: =IFERROR(I63/SUM(I58, I67),"") -> 0 | J102: =IFERROR(J63/SUM(J58, J67),"") -> 0 | ... AB102: =IFERROR(AB63/SUM(AB58, AB67),"") -> 0
B103: Fisheries | C103: =IFERROR(C64/SUM(C58, C67),"") -> 0.063236971 | D103: =IFERROR(D64/SUM(D58, D67),"") -> 0.069887908 | E103: =IFERROR(E64/SUM(E58, E67),"") -> 0.064329918 | F103: =IFERROR(F64/SUM(F58, F67),"") -> 0.058860868 | G103: =IFERROR(G64/SUM(G58, G67),"") -> 0.060695446 | H103: =IFERROR(H64/SUM(H58, H67),"") -> 0.037306395 | I103: =IFERROR(I64/SUM(I58, I67),"") -> 0.05047879 | J103: =IFERROR(J64/SUM(J58, J67),"") -> 0.031490737 | ... AB103: =IFERROR(AB64/SUM(AB58, AB67),"") -> 0.0098359116
B104: Agricultural Land | C104: =IFERROR(C65/SUM(C58, C67),"") -> 0.41361724 | D104: =IFERROR(D65/SUM(D58, D67),"") -> 0.41192415 | E104: =IFERROR(E65/SUM(E58, E67),"") -> 0.41669413 | F104: =IFERROR(F65/SUM(F58, F67),"") -> 0.42957166 | G104: =IFERROR(G65/SUM(G58, G67),"") -> 0.39817504 | H104: =IFERROR(H65/SUM(H58, H67),"") -> 0.33329178 | I104: =IFERROR(I65/SUM(I58, I67),"") -> 0.25636146 | J104: =IFERROR(J65/SUM(J58, J67),"") -> 0.35576476 | ... AB104: =IFERROR(AB65/SUM(AB58, AB67),"") -> 0.56438671
B105: Hydropower energy | C105: =IFERROR(C66/SUM(C58, C67),"") -> 0.13474464 | D105: =IFERROR(D66/SUM(D58, D67),"") -> 0.094660396 | E105: =IFERROR(E66/SUM(E58, E67),"") -> 0.12597454 | F105: =IFERROR(F66/SUM(F58, F67),"") -> 0.12066371 | G105: =IFERROR(G66/SUM(G58, G67),"") -> 0.078258955 | H105: =IFERROR(H66/SUM(H58, H67),"") -> 0.11463556 | I105: =IFERROR(I66/SUM(I58, I67),"") -> 0.20202783 | J105: =IFERROR(J66/SUM(J58, J67),"") -> 0.022824673 | ... AB105: =IFERROR(AB66/SUM(AB58, AB67),"") -> 0
B106: Oil | C106: =IFERROR(C68/SUM(C58, C67),"") -> 0.086445542 | D106: =IFERROR(D68/SUM(D58, D67),"") -> 0.11205168 | E106: =IFERROR(E68/SUM(E58, E67),"") -> 0.095148593 | F106: =IFERROR(F68/SUM(F58, F67),"") -> 0.066987667 | G106: =IFERROR(G68/SUM(G58, G67),"") -> 0.10480752 | H106: =IFERROR(H68/SUM(H58, H67),"") -> 0.19671723 | I106: =IFERROR(I68/SUM(I58, I67),"") -> 0.13257174 | J106: =IFERROR(J68/SUM(J58, J67),"") -> 0.22175198 | ... AB106: =IFERROR(AB68/SUM(AB58, AB67),"") -> 0
B107: Natural Gas | C107: =IFERROR(C69/SUM(C58, C67),"") -> 0.028470696 | D107: =IFERROR(D69/SUM(D58, D67),"") -> 0.03388394 | E107: =IFERROR(E69/SUM(E58, E67),"") -> 0.035184643 | F107: =IFERROR(F69/SUM(F58, F67),"") -> 0.044140176 | G107: =IFERROR(G69/SUM(G58, G67),"") -> 0.06152914 | H107: =IFERROR(H69/SUM(H58, H67),"") -> 0.079021166 | I107: =IFERROR(I69/SUM(I58, I67),"") -> 0.078349289 | J107: =IFERROR(J69/SUM(J58, J67),"") -> 0.10883429 | ... AB107: =IFERROR(AB69/SUM(AB58, AB67),"") -> 0
B108: Coal | C108: =IFERROR(C70/SUM(C58, C67),"") -> 0 | D108: =IFERROR(D70/SUM(D58, D67),"") -> 0 | E108: =IFERROR(E70/SUM(E58, E67),"") -> 0 | F108: =IFERROR(F70/SUM(F58, F67),"") -> 0 | G108: =IFERROR(G70/SUM(G58, G67),"") -> 0 | H108: =IFERROR(H70/SUM(H58, H67),"") -> 0 | I108: =IFERROR(I70/SUM(I58, I67),"") -> 0 | J108: =IFERROR(J70/SUM(J58, J67),"") -> 0 | ... AB108: =IFERROR(AB70/SUM(AB58, AB67),"") -> 0
B109: Metals and Minerals | C109: =IFERROR(C71/SUM(C58, C67),"") -> 0.0022822307 | D109: =IFERROR(D71/SUM(D58, D67),"") -> 0.0022644175 | E109: =IFERROR(E71/SUM(E58, E67),"") -> 0.002003788 | F109: =IFERROR(F71/SUM(F58, F67),"") -> 0.0015374118 | G109: =IFERROR(G71/SUM(G58, G67),"") -> 0.0022691767 | H109: =IFERROR(H71/SUM(H58, H67),"") -> 0.001115121 | I109: =IFERROR(I71/SUM(I58, I67),"") -> 0.0010284162 | J109: =IFERROR(J71/SUM(J58, J67),"") -> 0.020204711 | ... AB109: =IFERROR(AB71/SUM(AB58, AB67),"") -> 0.11753437

Sheet Wealth_graphs
A1: IMPORTANT NOTE: | B1: The trends in total wealth and asset categories (produced, human, renewable, and nonrenewable natural capital) are based on the Törnqvist index, where the change in physical volumes of individual assets is weighted by their value shares. “Volume” here refers to the physical quantity of each asset, or a proxy for that quantity. For example, the volume of timber assets is measured in hectares, while the volume of oil assets is measured in barrels. Because these assets are measured in different units, the Törnqvist index allows us to combine them by weighting the change in each asset by its value share, making the changes unitless and allowing the aggregation of different asset types to obtain an overall measure of how the total volume has changed. The Törnqvist volume index it is 'chained' together to make a time series by selecting a base year (2019) and then expressing other years in terms relative to the base year. For the base year, the chained Törnqvist volume index is normalized to 100. To make the index easier to interpret, the chained volume index is converted into monetary terms using 2019 US dollars, referred to as real asset values and expressed in “chained 2019 dollars”. This adjustment captures the "real" value of assets while removing the effect of inflation and other price changes. For each individual asset (sub-components of the aggregate categories), the change between 1995 and 2020 follows the trend in physical volumes, but unlike the aggregate asset categories, the changes over time in individual assets are not weighted by their shares in total wealth.
A3: ='Select a Country'!B4 -> Argentina
A5: Millions, chained 2019 USD | B5: 1995 | C5: 1996 | D5: 1997 | E5: 1998 | F5: 1999 | G5: 2000 | H5: 2001 | I5: 2002 | J5: 2003 | K5: 2004 | L5: 2005 | M5: 2006 | N5: 2007 | O5: 2008 | P5: 2009 | Q5: 2010 | R5: 2011 | S5: 2012 | T5: 2013 | U5: 2014 | V5: 2015 | W5: 2016 | X5: 2017 | Y5: 2018 | Z5: 2019 | AA5: 2020
A6: National Comprehensive Wealth Index | B6: ='Select a Country'!C9 -> 1775865.6 | C6: ='Select a Country'!D9 -> 1755387.1 | D6: ='Select a Country'!E9 -> 1718201.8 | E6: ='Select a Country'!F9 -> 1728758.8 | F6: ='Select a Country'!G9 -> 1653061 | G6: ='Select a Country'!H9 -> 1654586.9 | H6: ='Select a Country'!I9 -> 1537978.1 | I6: ='Select a Country'!J9 -> 2003756.1 | ... AA6: ='Select a Country'!AB9 -> 3766127.3
A7: Produced Capital | B7: ='Select a Country'!C10 -> 391198.06 | C7: ='Select a Country'!D10 -> 405064.18 | D7: ='Select a Country'!E10 -> 423211.87 | E7: ='Select a Country'!F10 -> 442622.75 | F7: ='Select a Country'!G10 -> 456678.56 | G7: ='Select a Country'!H10 -> 468128.76 | H7: ='Select a Country'!I10 -> 474772.76 | I7: ='Select a Country'!J10 -> 471844.11 | ... AA7: ='Select a Country'!AB10 -> 827744.06
A8: Human Capital | B8: ='Select a Country'!C11 -> 1455187.3 | C8: ='Select a Country'!D11 -> 1526475.9 | D8: ='Select a Country'!E11 -> 1617412.2 | E8: ='Select a Country'!F11 -> 1697522.9 | F8: ='Select a Country'!G11 -> 1684917.5 | G8: ='Select a Country'!H11 -> 1688360.8 | H8: ='Select a Country'!I11 -> 1664920.6 | I8: ='Select a Country'!J11 -> 1616374.1 | ... AA8: ='Select a Country'!AB11 -> 2567714.5
A9: Renewable Natural Capital | B9: =SUM('Select a Country'!C12) -> 327340.87 | C9: =SUM('Select a Country'!D12) -> 319336.11 | D9: =SUM('Select a Country'!E12) -> 326455.81 | E9: =SUM('Select a Country'!F12) -> 322636.67 | F9: =SUM('Select a Country'!G12) -> 313995.9 | G9: =SUM('Select a Country'!H12) -> 324956.51 | H9: =SUM('Select a Country'!I12) -> 341265.34 | I9: =SUM('Select a Country'!J12) -> 338535.43 | ... AA9: =SUM('Select a Country'!AB12) -> 286052
A10: Nonrenewable Natural Capital | B10: ='Select a Country'!C21 -> 78911.938 | C10: ='Select a Country'!D21 -> 84836.893 | D10: ='Select a Country'!E21 -> 86648.798 | E10: ='Select a Country'!F21 -> 89583.474 | F10: ='Select a Country'!G21 -> 97870.369 | G10: ='Select a Country'!H21 -> 97810.516 | H10: ='Select a Country'!I21 -> 95128.032 | I10: ='Select a Country'!J21 -> 89471.797 | ... AA10: ='Select a Country'!AB21 -> 32635.538
A11: Foreign Assets | B11: ='Select a Country'!C26 -> 773697.88 | C11: ='Select a Country'!D26 -> 888926.35 | D11: ='Select a Country'!E26 -> 1020923.4 | E11: ='Select a Country'!F26 -> 1076835 | F11: ='Select a Country'!G26 -> 1181432.8 | G11: ='Select a Country'!H26 -> 1197848.5 | H11: ='Select a Country'!I26 -> 1060027.5 | I11: ='Select a Country'!J26 -> 827758.74 | ... AA11: ='Select a Country'!AB26 -> 278419.7
A12: Foreign Liabilities | B12: ='Select a Country'!C27 -> 1023835.7 | C12: ='Select a Country'!D27 -> 1165466 | D12: ='Select a Country'!E27 -> 1368118.9 | E12: ='Select a Country'!F27 -> 1489059.1 | F12: ='Select a Country'!G27 -> 1595587.7 | G12: ='Select a Country'!H27 -> 1631486.5 | H12: ='Select a Country'!I27 -> 1718871.3 | I12: ='Select a Country'!J27 -> 1110467 | ... AA12: ='Select a Country'!AB27 -> 195534.85
A13: Population (millions) | B13: ='Select a Country'!C28 -> 34.94611 | C13: ='Select a Country'!D28 -> 35.389362 | D13: ='Select a Country'!E28 -> 35.815971 | E13: ='Select a Country'!F28 -> 36.233195 | F13: ='Select a Country'!G28 -> 36.653031 | G13: ='Select a Country'!H28 -> 37.070774 | H13: ='Select a Country'!I28 -> 37.480493 | I13: ='Select a Country'!J28 -> 37.885028 | ... AA13: ='Select a Country'!AB28 -> 45.376763
A15: =CONCATENATE("Real Wealth Per Capita, 1995 - 2020, ",$A$3) -> Real Wealth Per Capita, 1995 - 2020, Argentina
A16: Per Capita, chained 2019 USD | B16: 1995 | C16: 1996 | D16: 1997 | E16: 1998 | F16: 1999 | G16: 2000 | H16: 2001 | I16: 2002 | J16: 2003 | K16: 2004 | L16: 2005 | M16: 2006 | N16: 2007 | O16: 2008 | P16: 2009 | Q16: 2010 | R16: 2011 | S16: 2012 | T16: 2013 | U16: 2014 | V16: 2015 | W16: 2016 | X16: 2017 | Y16: 2018 | Z16: 2019 | AA16: 2020
A17: National Comprehensive Wealth Index | B17: =IF(IFERROR(B6/B$13, "..")=0, NA(), IFERROR(B6/B$13, "..")) -> 50817.262 | C17: =IF(IFERROR(C6/C$13, "..")=0, NA(), IFERROR(C6/C$13, "..")) -> 49602.113 | D17: =IF(IFERROR(D6/D$13, "..")=0, NA(), IFERROR(D6/D$13, "..")) -> 47973.063 | E17: =IF(IFERROR(E6/E$13, "..")=0, NA(), IFERROR(E6/E$13, "..")) -> 47712.016 | F17: =IF(IFERROR(F6/F$13, "..")=0, NA(), IFERROR(F6/F$13, "..")) -> 45100.255 | G17: =IF(IFERROR(G6/G$13, "..")=0, NA(), IFERROR(G6/G$13, "..")) -> 44633.189 | H17: =IF(IFERROR(H6/H$13, "..")=0, NA(), IFERROR(H6/H$13, "..")) -> 41034.095 | I17: =IF(IFERROR(I6/I$13, "..")=0, NA(), IFERROR(I6/I$13, "..")) -> 52890.447 | ... AA17: =IF(IFERROR(AA6/AA$13, "..")=0, NA(), IFERROR(AA6/AA$13, "..")) -> 82996.827
A18: Produced Capital | B18: =IF(IFERROR(B7/B$13, "..")=0, NA(), IFERROR(B7/B$13, "..")) -> 11194.323 | C18: =IF(IFERROR(C7/C$13, "..")=0, NA(), IFERROR(C7/C$13, "..")) -> 11445.93 | D18: =IF(IFERROR(D7/D$13, "..")=0, NA(), IFERROR(D7/D$13, "..")) -> 11816.289 | E18: =IF(IFERROR(E7/E$13, "..")=0, NA(), IFERROR(E7/E$13, "..")) -> 12215.946 | F18: =IF(IFERROR(F7/F$13, "..")=0, NA(), IFERROR(F7/F$13, "..")) -> 12459.503 | G18: =IF(IFERROR(G7/G$13, "..")=0, NA(), IFERROR(G7/G$13, "..")) -> 12627.974 | H18: =IF(IFERROR(H7/H$13, "..")=0, NA(), IFERROR(H7/H$13, "..")) -> 12667.196 | I18: =IF(IFERROR(I7/I$13, "..")=0, NA(), IFERROR(I7/I$13, "..")) -> 12454.633 | ... AA18: =IF(IFERROR(AA7/AA$13, "..")=0, NA(), IFERROR(AA7/AA$13, "..")) -> 18241.585
A19: Human Capital | B19: =IF(IFERROR(B8/B$13, "..")=0, NA(), IFERROR(B8/B$13, "..")) -> 41640.895 | C19: =IF(IFERROR(C8/C$13, "..")=0, NA(), IFERROR(C8/C$13, "..")) -> 43133.749 | D19: =IF(IFERROR(D8/D$13, "..")=0, NA(), IFERROR(D8/D$13, "..")) -> 45158.964 | E19: =IF(IFERROR(E8/E$13, "..")=0, NA(), IFERROR(E8/E$13, "..")) -> 46849.938 | F19: =IF(IFERROR(F8/F$13, "..")=0, NA(), IFERROR(F8/F$13, "..")) -> 45969.39 | G19: =IF(IFERROR(G8/G$13, "..")=0, NA(), IFERROR(G8/G$13, "..")) -> 45544.256 | H19: =IF(IFERROR(H8/H$13, "..")=0, NA(), IFERROR(H8/H$13, "..")) -> 44420.989 | I19: =IF(IFERROR(I8/I$13, "..")=0, NA(), IFERROR(I8/I$13, "..")) -> 42665.249 | ... AA19: =IF(IFERROR(AA8/AA$13, "..")=0, NA(), IFERROR(AA8/AA$13, "..")) -> 56586.551
A20: Renewable Natural Capital | B20: =IF(IFERROR(B9/B$13, "..")=0, NA(), IFERROR(B9/B$13, "..")) -> 9367.0189 | C20: =IF(IFERROR(C9/C$13, "..")=0, NA(), IFERROR(C9/C$13, "..")) -> 9023.5058 | D20: =IF(IFERROR(D9/D$13, "..")=0, NA(), IFERROR(D9/D$13, "..")) -> 9114.8111 | E20: =IF(IFERROR(E9/E$13, "..")=0, NA(), IFERROR(E9/E$13, "..")) -> 8904.45 | F20: =IF(IFERROR(F9/F$13, "..")=0, NA(), IFERROR(F9/F$13, "..")) -> 8566.7103 | G20: =IF(IFERROR(G9/G$13, "..")=0, NA(), IFERROR(G9/G$13, "..")) -> 8765.8409 | H20: =IF(IFERROR(H9/H$13, "..")=0, NA(), IFERROR(H9/H$13, "..")) -> 9105.1455 | I20: =IF(IFERROR(I9/I$13, "..")=0, NA(), IFERROR(I9/I$13, "..")) -> 8935.8633 | ... AA20: =IF(IFERROR(AA9/AA$13, "..")=0, NA(), IFERROR(AA9/AA$13, "..")) -> 6303.9313 | AB20: Note: Renewable includes forests, mangroves, fisheries, agricultural land and hydropower energy.
A21: Nonrenewable Natural Capital | B21: =IF(IFERROR(B10/B$13, "..")=0, NA(), IFERROR(B10/B$13, "..")) -> 2258.1036 | C21: =IF(IFERROR(C10/C$13, "..")=0, NA(), IFERROR(C10/C$13, "..")) -> 2397.2428 | D21: =IF(IFERROR(D10/D$13, "..")=0, NA(), IFERROR(D10/D$13, "..")) -> 2419.2782 | E21: =IF(IFERROR(E10/E$13, "..")=0, NA(), IFERROR(E10/E$13, "..")) -> 2472.4144 | F21: =IF(IFERROR(F10/F$13, "..")=0, NA(), IFERROR(F10/F$13, "..")) -> 2670.1849 | G21: =IF(IFERROR(G10/G$13, "..")=0, NA(), IFERROR(G10/G$13, "..")) -> 2638.4805 | H21: =IF(IFERROR(H10/H$13, "..")=0, NA(), IFERROR(H10/H$13, "..")) -> 2538.0678 | I21: =IF(IFERROR(I10/I$13, "..")=0, NA(), IFERROR(I10/I$13, "..")) -> 2361.6664 | ... AA21: =IF(IFERROR(AA10/AA$13, "..")=0, NA(), IFERROR(AA10/AA$13, "..")) -> 719.21256 | AB21: Note: Nonrenewable refers to subsoil assets (oil, gas, coal, metals and minerals).
A22: Foreign Assets | B22: =IF(IFERROR(B11/B$13, "..")=0, NA(), IFERROR(B11/B$13, "..")) -> 22139.742 | C22: =IF(IFERROR(C11/C$13, "..")=0, NA(), IFERROR(C11/C$13, "..")) -> 25118.462 | D22: =IF(IFERROR(D11/D$13, "..")=0, NA(), IFERROR(D11/D$13, "..")) -> 28504.698 | E22: =IF(IFERROR(E11/E$13, "..")=0, NA(), IFERROR(E11/E$13, "..")) -> 29719.57 | F22: =IF(IFERROR(F11/F$13, "..")=0, NA(), IFERROR(F11/F$13, "..")) -> 32232.883 | G22: =IF(IFERROR(G11/G$13, "..")=0, NA(), IFERROR(G11/G$13, "..")) -> 32312.475 | H22: =IF(IFERROR(H11/H$13, "..")=0, NA(), IFERROR(H11/H$13, "..")) -> 28282.112 | I22: =IF(IFERROR(I11/I$13, "..")=0, NA(), IFERROR(I11/I$13, "..")) -> 21849.231 | ... AA22: =IF(IFERROR(AA11/AA$13, "..")=0, NA(), IFERROR(AA11/AA$13, "..")) -> 6135.7329
A23: Foreign Liablities | B23: =IF(IFERROR(B12/B$13, "..")=0, NA(), IFERROR(B12/B$13, "..")) -> 29297.558 | C23: =IF(IFERROR(C12/C$13, "..")=0, NA(), IFERROR(C12/C$13, "..")) -> 32932.664 | D23: =IF(IFERROR(D12/D$13, "..")=0, NA(), IFERROR(D12/D$13, "..")) -> 38198.571 | E23: =IF(IFERROR(E12/E$13, "..")=0, NA(), IFERROR(E12/E$13, "..")) -> 41096.544 | F23: =IF(IFERROR(F12/F$13, "..")=0, NA(), IFERROR(F12/F$13, "..")) -> 43532.217 | G23: =IF(IFERROR(G12/G$13, "..")=0, NA(), IFERROR(G12/G$13, "..")) -> 44010.048 | H23: =IF(IFERROR(H12/H$13, "..")=0, NA(), IFERROR(H12/H$13, "..")) -> 45860.425 | I23: =IF(IFERROR(I12/I$13, "..")=0, NA(), IFERROR(I12/I$13, "..")) -> 29311.499 | ... AA23: =IF(IFERROR(AA12/AA$13, "..")=0, NA(), IFERROR(AA12/AA$13, "..")) -> 4309.1405
A25: =CONCATENATE("Trends in real Wealth Per Capita, 1995 - 2020, ",$A$3) -> Trends in real Wealth Per Capita, 1995 - 2020, Argentina
A26: Per Capita, chained 2019 USD, Indexed | B26: 1995 | C26: 1996 | D26: 1997 | E26: 1998 | F26: 1999 | G26: 2000 | H26: 2001 | I26: 2002 | J26: 2003 | K26: 2004 | L26: 2005 | M26: 2006 | N26: 2007 | O26: 2008 | P26: 2009 | Q26: 2010 | R26: 2011 | S26: 2012 | T26: 2013 | U26: 2014 | V26: 2015 | W26: 2016 | X26: 2017 | Y26: 2018 | Z26: 2019 | AA26: 2020
A27: National Comprehensive Wealth Index | B27: =IF(B17=0, NA(), 100) -> 100 | C27: {=IF(AND(C17=0, ISNA(B27)), NA(), IF(AND(C17<>0, ISNA(B27)), 100, C17/INDEX($B17:$AA17, MATCH(TRUE, $B17:$AA17 <> 0, 0))*100))} -> 97.608786 | D27: {=IF(AND(D17=0, ISNA(C27)), NA(), IF(AND(D17<>0, ISNA(C27)), 100, D17/INDEX($B17:$AA17, MATCH(TRUE, $B17:$AA17 <> 0, 0))*100))} -> 94.403083 | E27: {=IF(AND(E17=0, ISNA(D27)), NA(), IF(AND(E17<>0, ISNA(D27)), 100, E17/INDEX($B17:$AA17, MATCH(TRUE, $B17:$AA17 <> 0, 0))*100))} -> 93.889386 | F27: {=IF(AND(F17=0, ISNA(E27)), NA(), IF(AND(F17<>0, ISNA(E27)), 100, F17/INDEX($B17:$AA17, MATCH(TRUE, $B17:$AA17 <> 0, 0))*100))} -> 88.749872 | G27: {=IF(AND(G17=0, ISNA(F27)), NA(), IF(AND(G17<>0, ISNA(F27)), 100, G17/INDEX($B17:$AA17, MATCH(TRUE, $B17:$AA17 <> 0, 0))*100))} -> 87.830763 | H27: {=IF(AND(H17=0, ISNA(G27)), NA(), IF(AND(H17<>0, ISNA(G27)), 100, H17/INDEX($B17:$AA17, MATCH(TRUE, $B17:$AA17 <> 0, 0))*100))} -> 80.748338 | I27: {=IF(AND(I17=0, ISNA(H27)), NA(), IF(AND(I17<>0, ISNA(H27)), 100, I17/INDEX($B17:$AA17, MATCH(TRUE, $B17:$AA17 <> 0, 0))*100))} -> 104.07969 | J27: {=IF(AND(J17=0, ISNA(I27)), NA(), IF(AND(J17<>0, ISNA(I27)), 100, J17/INDEX($B17:$AA17, MATCH(TRUE, $B17:$AA17 <> 0, 0))*100))} -> 110.78931 | ... AA27: {=IF(AND(AA17=0, ISNA(Z27)), NA(), IF(AND(AA17<>0, ISNA(Z27)), 100, AA17/INDEX($B17:$AA17, MATCH(TRUE, $B17:$AA17 <> 0, 0))*100))} -> 163.32408
A28: Produced Capital | B28: =IF(B18=0, NA(), 100) -> 100 | C28: {=IF(AND(C18=0, ISNA(B28)), NA(), IF(AND(C18<>0, ISNA(B28)), 100, C18/INDEX($B18:$AA18, MATCH(TRUE, $B18:$AA18 <> 0, 0))*100))} -> 102.24763 | D28: {=IF(AND(D18=0, ISNA(C28)), NA(), IF(AND(D18<>0, ISNA(C28)), 100, D18/INDEX($B18:$AA18, MATCH(TRUE, $B18:$AA18 <> 0, 0))*100))} -> 105.55608 | E28: {=IF(AND(E18=0, ISNA(D28)), NA(), IF(AND(E18<>0, ISNA(D28)), 100, E18/INDEX($B18:$AA18, MATCH(TRUE, $B18:$AA18 <> 0, 0))*100))} -> 109.12625 | F28: {=IF(AND(F18=0, ISNA(E28)), NA(), IF(AND(F18<>0, ISNA(E28)), 100, F18/INDEX($B18:$AA18, MATCH(TRUE, $B18:$AA18 <> 0, 0))*100))} -> 111.30198 | G28: {=IF(AND(G18=0, ISNA(F28)), NA(), IF(AND(G18<>0, ISNA(F28)), 100, G18/INDEX($B18:$AA18, MATCH(TRUE, $B18:$AA18 <> 0, 0))*100))} -> 112.80694 | H28: {=IF(AND(H18=0, ISNA(G28)), NA(), IF(AND(H18<>0, ISNA(G28)), 100, H18/INDEX($B18:$AA18, MATCH(TRUE, $B18:$AA18 <> 0, 0))*100))} -> 113.15732 | I28: {=IF(AND(I18=0, ISNA(H28)), NA(), IF(AND(I18<>0, ISNA(H28)), 100, I18/INDEX($B18:$AA18, MATCH(TRUE, $B18:$AA18 <> 0, 0))*100))} -> 111.25847 | J28: {=IF(AND(J18=0, ISNA(I28)), NA(), IF(AND(J18<>0, ISNA(I28)), 100, J18/INDEX($B18:$AA18, MATCH(TRUE, $B18:$AA18 <> 0, 0))*100))} -> 110.93852 | ... AA28: {=IF(AND(AA18=0, ISNA(Z28)), NA(), IF(AND(AA18<>0, ISNA(Z28)), 100, AA18/INDEX($B18:$AA18, MATCH(TRUE, $B18:$AA18 <> 0, 0))*100))} -> 162.95388
A29: Human Capital | B29: =IF(B19=0, NA(), 100) -> 100 | C29: {=IF(AND(C19=0, ISNA(B29)), NA(), IF(AND(C19<>0, ISNA(B29)), 100, C19/INDEX($B19:$AA19, MATCH(TRUE, $B19:$AA19 <> 0, 0))*100))} -> 103.58507 | D29: {=IF(AND(D19=0, ISNA(C29)), NA(), IF(AND(D19<>0, ISNA(C29)), 100, D19/INDEX($B19:$AA19, MATCH(TRUE, $B19:$AA19 <> 0, 0))*100))} -> 108.44859 | E29: {=IF(AND(E19=0, ISNA(D29)), NA(), IF(AND(E19<>0, ISNA(D29)), 100, E19/INDEX($B19:$AA19, MATCH(TRUE, $B19:$AA19 <> 0, 0))*100))} -> 112.50944 | F29: {=IF(AND(F19=0, ISNA(E29)), NA(), IF(AND(F19<>0, ISNA(E29)), 100, F19/INDEX($B19:$AA19, MATCH(TRUE, $B19:$AA19 <> 0, 0))*100))} -> 110.39482 | G29: {=IF(AND(G19=0, ISNA(F29)), NA(), IF(AND(G19<>0, ISNA(F29)), 100, G19/INDEX($B19:$AA19, MATCH(TRUE, $B19:$AA19 <> 0, 0))*100))} -> 109.37386 | H29: {=IF(AND(H19=0, ISNA(G29)), NA(), IF(AND(H19<>0, ISNA(G29)), 100, H19/INDEX($B19:$AA19, MATCH(TRUE, $B19:$AA19 <> 0, 0))*100))} -> 106.67635 | I29: {=IF(AND(I19=0, ISNA(H29)), NA(), IF(AND(I19<>0, ISNA(H29)), 100, I19/INDEX($B19:$AA19, MATCH(TRUE, $B19:$AA19 <> 0, 0))*100))} -> 102.45997 | J29: {=IF(AND(J19=0, ISNA(I29)), NA(), IF(AND(J19<>0, ISNA(I29)), 100, J19/INDEX($B19:$AA19, MATCH(TRUE, $B19:$AA19 <> 0, 0))*100))} -> 110.68551 | ... AA29: {=IF(AND(AA19=0, ISNA(Z29)), NA(), IF(AND(AA19<>0, ISNA(Z29)), 100, AA19/INDEX($B19:$AA19, MATCH(TRUE, $B19:$AA19 <> 0, 0))*100))} -> 135.89177
A30: Renewable Natural Capital | B30: =IF(B20=0, NA(), 100) -> 100 | C30: {=IF(AND(C20=0, ISNA(B30)), NA(), IF(AND(C20<>0, ISNA(B30)), 100, C20/INDEX($B20:$AA20, MATCH(TRUE, $B20:$AA20 <> 0, 0))*100))} -> 96.332738 | D30: {=IF(AND(D20=0, ISNA(C30)), NA(), IF(AND(D20<>0, ISNA(C30)), 100, D20/INDEX($B20:$AA20, MATCH(TRUE, $B20:$AA20 <> 0, 0))*100))} -> 97.307491 | E30: {=IF(AND(E20=0, ISNA(D30)), NA(), IF(AND(E20<>0, ISNA(D30)), 100, E20/INDEX($B20:$AA20, MATCH(TRUE, $B20:$AA20 <> 0, 0))*100))} -> 95.061728 | F30: {=IF(AND(F20=0, ISNA(E30)), NA(), IF(AND(F20<>0, ISNA(E30)), 100, F20/INDEX($B20:$AA20, MATCH(TRUE, $B20:$AA20 <> 0, 0))*100))} -> 91.456101 | G30: {=IF(AND(G20=0, ISNA(F30)), NA(), IF(AND(G20<>0, ISNA(F30)), 100, G20/INDEX($B20:$AA20, MATCH(TRUE, $B20:$AA20 <> 0, 0))*100))} -> 93.58197 | H30: {=IF(AND(H20=0, ISNA(G30)), NA(), IF(AND(H20<>0, ISNA(G30)), 100, H20/INDEX($B20:$AA20, MATCH(TRUE, $B20:$AA20 <> 0, 0))*100))} -> 97.204303 | I30: {=IF(AND(I20=0, ISNA(H30)), NA(), IF(AND(I20<>0, ISNA(H30)), 100, I20/INDEX($B20:$AA20, MATCH(TRUE, $B20:$AA20 <> 0, 0))*100))} -> 95.397088 | J30: {=IF(AND(J20=0, ISNA(I30)), NA(), IF(AND(J20<>0, ISNA(I30)), 100, J20/INDEX($B20:$AA20, MATCH(TRUE, $B20:$AA20 <> 0, 0))*100))} -> 93.976115 | ... AA30: {=IF(AND(AA20=0, ISNA(Z30)), NA(), IF(AND(AA20<>0, ISNA(Z30)), 100, AA20/INDEX($B20:$AA20, MATCH(TRUE, $B20:$AA20 <> 0, 0))*100))} -> 67.299227
A31: Nonrenewable Natural Capital | B31: =IF(B21=0, NA(), 100) -> 100 | C31: {=IF(AND(C21=0, ISNA(B31)), NA(), IF(AND(C21<>0, ISNA(B31)), 100, C21/INDEX($B21:$AA21, MATCH(TRUE, $B21:$AA21 <> 0, 0))*100))} -> 106.16177 | D31: {=IF(AND(D21=0, ISNA(C31)), NA(), IF(AND(D21<>0, ISNA(C31)), 100, D21/INDEX($B21:$AA21, MATCH(TRUE, $B21:$AA21 <> 0, 0))*100))} -> 107.13761 | E31: {=IF(AND(E21=0, ISNA(D31)), NA(), IF(AND(E21<>0, ISNA(D31)), 100, E21/INDEX($B21:$AA21, MATCH(TRUE, $B21:$AA21 <> 0, 0))*100))} -> 109.49074 | F31: {=IF(AND(F21=0, ISNA(E31)), NA(), IF(AND(F21<>0, ISNA(E31)), 100, F21/INDEX($B21:$AA21, MATCH(TRUE, $B21:$AA21 <> 0, 0))*100))} -> 118.249 | G31: {=IF(AND(G21=0, ISNA(F31)), NA(), IF(AND(G21<>0, ISNA(F31)), 100, G21/INDEX($B21:$AA21, MATCH(TRUE, $B21:$AA21 <> 0, 0))*100))} -> 116.84497 | H31: {=IF(AND(H21=0, ISNA(G31)), NA(), IF(AND(H21<>0, ISNA(G31)), 100, H21/INDEX($B21:$AA21, MATCH(TRUE, $B21:$AA21 <> 0, 0))*100))} -> 112.3982 | I31: {=IF(AND(I21=0, ISNA(H31)), NA(), IF(AND(I21<>0, ISNA(H31)), 100, I21/INDEX($B21:$AA21, MATCH(TRUE, $B21:$AA21 <> 0, 0))*100))} -> 104.58627 | J31: {=IF(AND(J21=0, ISNA(I31)), NA(), IF(AND(J21<>0, ISNA(I31)), 100, J21/INDEX($B21:$AA21, MATCH(TRUE, $B21:$AA21 <> 0, 0))*100))} -> 97.556338 | ... AA31: {=IF(AND(AA21=0, ISNA(Z31)), NA(), IF(AND(AA21<>0, ISNA(Z31)), 100, AA21/INDEX($B21:$AA21, MATCH(TRUE, $B21:$AA21 <> 0, 0))*100))} -> 31.85029
A32: Foreign Assets | B32: =IF(B22=0, NA(), 100) -> 100 | C32: {=IF(AND(C22=0, ISNA(B32)), NA(), IF(AND(C22<>0, ISNA(B32)), 100, C22/INDEX($B22:$AA22, MATCH(TRUE, $B22:$AA22 <> 0, 0))*100))} -> 113.45417 | D32: {=IF(AND(D22=0, ISNA(C32)), NA(), IF(AND(D22<>0, ISNA(C32)), 100, D22/INDEX($B22:$AA22, MATCH(TRUE, $B22:$AA22 <> 0, 0))*100))} -> 128.749 | E32: {=IF(AND(E22=0, ISNA(D32)), NA(), IF(AND(E22<>0, ISNA(D32)), 100, E22/INDEX($B22:$AA22, MATCH(TRUE, $B22:$AA22 <> 0, 0))*100))} -> 134.23629 | F32: {=IF(AND(F22=0, ISNA(E32)), NA(), IF(AND(F22<>0, ISNA(E32)), 100, F22/INDEX($B22:$AA22, MATCH(TRUE, $B22:$AA22 <> 0, 0))*100))} -> 145.58834 | G32: {=IF(AND(G22=0, ISNA(F32)), NA(), IF(AND(G22<>0, ISNA(F32)), 100, G22/INDEX($B22:$AA22, MATCH(TRUE, $B22:$AA22 <> 0, 0))*100))} -> 145.94784 | H32: {=IF(AND(H22=0, ISNA(G32)), NA(), IF(AND(H22<>0, ISNA(G32)), 100, H22/INDEX($B22:$AA22, MATCH(TRUE, $B22:$AA22 <> 0, 0))*100))} -> 127.74364 | I32: {=IF(AND(I22=0, ISNA(H32)), NA(), IF(AND(I22<>0, ISNA(H32)), 100, I22/INDEX($B22:$AA22, MATCH(TRUE, $B22:$AA22 <> 0, 0))*100))} -> 98.687829 | J32: {=IF(AND(J22=0, ISNA(I32)), NA(), IF(AND(J22<>0, ISNA(I32)), 100, J22/INDEX($B22:$AA22, MATCH(TRUE, $B22:$AA22 <> 0, 0))*100))} -> 95.540748 | ... AA32: {=IF(AND(AA22=0, ISNA(Z32)), NA(), IF(AND(AA22<>0, ISNA(Z32)), 100, AA22/INDEX($B22:$AA22, MATCH(TRUE, $B22:$AA22 <> 0, 0))*100))} -> 27.71366
A33: Foreign Liabilities | B33: =IF(B23=0, NA(), 100) -> 100 | C33: {=IF(AND(C23=0, ISNA(B33)), NA(), IF(AND(C23<>0, ISNA(B33)), 100, C23/INDEX($B23:$AA23, MATCH(TRUE, $B23:$AA23 <> 0, 0))*100))} -> 112.40754 | D33: {=IF(AND(D23=0, ISNA(C33)), NA(), IF(AND(D23<>0, ISNA(C33)), 100, D23/INDEX($B23:$AA23, MATCH(TRUE, $B23:$AA23 <> 0, 0))*100))} -> 130.38142 | E33: {=IF(AND(E23=0, ISNA(D33)), NA(), IF(AND(E23<>0, ISNA(D33)), 100, E23/INDEX($B23:$AA23, MATCH(TRUE, $B23:$AA23 <> 0, 0))*100))} -> 140.27293 | F33: {=IF(AND(F23=0, ISNA(E33)), NA(), IF(AND(F23<>0, ISNA(E33)), 100, F23/INDEX($B23:$AA23, MATCH(TRUE, $B23:$AA23 <> 0, 0))*100))} -> 148.5865 | G33: {=IF(AND(G23=0, ISNA(F33)), NA(), IF(AND(G23<>0, ISNA(F33)), 100, G23/INDEX($B23:$AA23, MATCH(TRUE, $B23:$AA23 <> 0, 0))*100))} -> 150.21746 | H33: {=IF(AND(H23=0, ISNA(G33)), NA(), IF(AND(H23<>0, ISNA(G33)), 100, H23/INDEX($B23:$AA23, MATCH(TRUE, $B23:$AA23 <> 0, 0))*100))} -> 156.53327 | I33: {=IF(AND(I23=0, ISNA(H33)), NA(), IF(AND(I23<>0, ISNA(H33)), 100, I23/INDEX($B23:$AA23, MATCH(TRUE, $B23:$AA23 <> 0, 0))*100))} -> 100.04759 | J33: {=IF(AND(J23=0, ISNA(I33)), NA(), IF(AND(J23<>0, ISNA(I33)), 100, J23/INDEX($B23:$AA23, MATCH(TRUE, $B23:$AA23 <> 0, 0))*100))} -> 93.278245 | ... AA33: {=IF(AND(AA23=0, ISNA(Z33)), NA(), IF(AND(AA23<>0, ISNA(Z33)), 100, AA23/INDEX($B23:$AA23, MATCH(TRUE, $B23:$AA23 <> 0, 0))*100))} -> 14.70819
A84: =CONCATENATE("Nominal Wealth Shares (current US$) - ",$A$3) -> Nominal Wealth Shares (current US$) - Argentina
A85: =CONCATENATE("Nominal Wealth Shares - ",$A$3) -> Nominal Wealth Shares - Argentina | B85: 1995 | C85: 1996 | D85: 1997 | E85: 1998 | F85: 1999 | G85: 2000 | H85: 2001 | I85: 2002 | J85: 2003 | K85: 2004 | L85: 2005 | M85: 2006 | N85: 2007 | O85: 2008 | P85: 2009 | Q85: 2010 | R85: 2011 | S85: 2012 | T85: 2013 | U85: 2014 | V85: 2015 | W85: 2016 | X85: 2017 | Y85: 2018 | Z85: 2019 | AA85: 2020
A86: Produced capital | B86: ='Select a Country'!C74 -> 0.31330627 | C86: ='Select a Country'!D74 -> 0.30014613 | D86: ='Select a Country'!E74 -> 0.28618112 | E86: ='Select a Country'!F74 -> 0.27988172 | F86: ='Select a Country'!G74 -> 0.2896646 | G86: ='Select a Country'!H74 -> 0.27979687 | H86: ='Select a Country'!I74 -> 0.2943005 | I86: ='Select a Country'!J74 -> 0.36726385 | ... AA86: ='Select a Country'!AB74 -> 0.26685741
A87: Human capital | B87: ='Select a Country'!C75 -> 0.55979691 | C87: ='Select a Country'!D75 -> 0.57247167 | D87: ='Select a Country'!E75 -> 0.58772041 | E87: ='Select a Country'!F75 -> 0.60857754 | F87: ='Select a Country'!G75 -> 0.60605695 | G87: ='Select a Country'!H75 -> 0.59745977 | H87: ='Select a Country'!I75 -> 0.59894821 | I87: ='Select a Country'!J75 -> 0.44442883 | ... AA87: ='Select a Country'!AB75 -> 0.63924054
A88: Renewable Natural Capital | B88: ='Select a Country'!C76 -> 0.1120247 | C88: ='Select a Country'!D76 -> 0.10850416 | D88: ='Select a Country'!E76 -> 0.10941097 | E88: ='Select a Country'!F76 -> 0.098973977 | F88: ='Select a Country'!G76 -> 0.086696495 | G88: ='Select a Country'!H76 -> 0.088761428 | H88: ='Select a Country'!I76 -> 0.084125413 | I88: ='Select a Country'!J76 -> 0.12225081 | ... AA88: ='Select a Country'!AB76 -> 0.082865331
A89: Nonrenewable Natural capital | B89: ='Select a Country'!C77 -> 0.014872112 | C89: ='Select a Country'!D77 -> 0.018878048 | D89: ='Select a Country'!E77 -> 0.016687496 | E89: ='Select a Country'!F77 -> 0.012566766 | F89: ='Select a Country'!G77 -> 0.017581955 | G89: ='Select a Country'!H77 -> 0.033981931 | H89: ='Select a Country'!I77 -> 0.022625877 | I89: ='Select a Country'!J77 -> 0.066056509 | ... AA89: ='Select a Country'!AB77 -> 0.011036719

Sheet Region
B1: East Asia and Pacific | C1: =CONCATENATE(B1,C2) -> East Asia and Pacific1995 | D1: =CONCATENATE(B1,D2) -> East Asia and Pacific2000 | E1: =CONCATENATE(B1,E2) -> East Asia and Pacific2005 | F1: =CONCATENATE(B1,F2) -> East Asia and Pacific2010 | G1: =CONCATENATE(B1,G2) -> East Asia and Pacific2015 | H1: =CONCATENATE(B1,H2) -> East Asia and Pacific2020 | J1: Europe and Central Asia | K1: =CONCATENATE(J1,K2) -> Europe and Central Asia1995 | L1: =CONCATENATE(J1,L2) -> Europe and Central Asia2000 | M1: =CONCATENATE(J1,M2) -> Europe and Central Asia2005 | N1: =CONCATENATE(J1,N2) -> Europe and Central Asia2010 | O1: =CONCATENATE(J1,O2) -> Europe and Central Asia2015 | P1: =CONCATENATE(J1,P2) -> Europe and Central Asia2020 | R1: Latin America and Caribbean | S1: =CONCATENATE(R1,S2) -> Latin America and Caribbean1995 | T1: =CONCATENATE(R1,T2) -> Latin America and Caribbean2000 | U1: =CONCATENATE(R1,U2) -> Latin America and Caribbean2005 | V1: =CONCATENATE(R1,V2) -> Latin America and Caribbean2010 | W1: =CONCATENATE(R1,W2) -> Latin America and Caribbean2015 | X1: =CONCATENATE(R1,X2) -> Latin America and Caribbean2020 | Z1: Middle East and North Africa | AA1: =CONCATENATE(Z1,AA2) -> Middle East and North Africa1995 | AB1: =CONCATENATE(Z1,AB2) -> Middle East and North Africa2000 | AC1: =CONCATENATE(Z1,AC2) -> Middle East and North Africa2005 | AD1: =CONCATENATE(Z1,AD2) -> Middle East and North Africa2010 | AE1: =CONCATENATE(Z1,AE2) -> Middle East and North Africa2015 | AF1: =CONCATENATE(Z1,AF2) -> Middle East and North Africa2020 | AH1: North America | AI1: =CONCATENATE(AH1,AI2) -> North America1995 | AJ1: =CONCATENATE(AH1,AJ2) -> North America2000 | AK1: =CONCATENATE(AH1,AK2) -> North America2005 | AL1: =CONCATENATE(AH1,AL2) -> North America2010 | AM1: =CONCATENATE(AH1,AM2) -> North America2015 | AN1: =CONCATENATE(AH1,AN2) -> North America2020 | AP1: South Asia | AQ1: =CONCATENATE(AP1,AQ2) -> South Asia1995 | AR1: =CONCATENATE(AP1,AR2) -> South Asia2000 | AS1: =CONCATENATE(AP1,AS2) -> South Asia2005 | AT1: =CONCATENATE(AP1,AT2) -> South Asia2010 | AU1: =CONCATENATE(AP1,AU2) -> South Asia2015 | AV1: =CONCATENATE(AP1,AV2) -> South Asia2020 | AX1: Sub-Saharan Africa | AY1: =CONCATENATE(AX1,AY2) -> Sub-Saharan Africa1995 | AZ1: =CONCATENATE(AX1,AZ2) -> Sub-Saharan Africa2000 | BA1: =CONCATENATE(AX1,BA2) -> Sub-Saharan Africa2005 | BB1: =CONCATENATE(AX1,BB2) -> Sub-Saharan Africa2010 | BC1: =CONCATENATE(AX1,BC2) -> Sub-Saharan Africa2015 | BD1: =CONCATENATE(AX1,BD2) -> Sub-Saharan Africa2020
B2: Millions, chained 2019 USD | C2: 1995 | D2: 2000 | E2: 2005 | F2: 2010 | G2: 2015 | H2: 2020 | J2: Millions, chained 2019 USD | K2: 1995 | L2: 2000 | M2: 2005 | N2: 2010 | O2: 2015 | P2: 2020 | R2: Millions, chained 2019 USD | S2: 1995 | T2: 2000 | U2: 2005 | V2: 2010 | W2: 2015 | X2: 2020 | Z2: Millions, chained 2019 USD | AA2: 1995 | AB2: 2000 | AC2: 2005 | AD2: 2010 | AE2: 2015 | AF2: 2020 | AH2: Millions, chained 2019 USD | AI2: 1995 | AJ2: 2000 | AK2: 2005 | AL2: 2010 | AM2: 2015 | AN2: 2020 | AP2: Millions, chained 2019 USD | AQ2: 1995 | AR2: 2000 | AS2: 2005 | AT2: 2010 | AU2: 2015 | AV2: 2020 | AX2: Millions, chained 2019 USD | AY2: 1995 | AZ2: 2000 | BA2: 2005 | BB2: 2010 | BC2: 2015 | BD2: 2020
A3: 36 | B3: National comprehensive wealth index | C3: =VLOOKUP(C$1,reg_bal!$D$1:$CA$184,$A3,FALSE)/1000000 -> 1.3969194e+08 | D3: =VLOOKUP(D$1,reg_bal!$D$1:$CA$184,$A3,FALSE)/1000000 -> 1.5912838e+08 | E3: =VLOOKUP(E$1,reg_bal!$D$1:$CA$184,$A3,FALSE)/1000000 -> 1.7739095e+08 | F3: =VLOOKUP(F$1,reg_bal!$D$1:$CA$184,$A3,FALSE)/1000000 -> 2.0139761e+08 | G3: =VLOOKUP(G$1,reg_bal!$D$1:$CA$184,$A3,FALSE)/1000000 -> 2.2218824e+08 | H3: =VLOOKUP(H$1,reg_bal!$D$1:$CA$184,$A3,FALSE)/1000000 -> 2.4735288e+08 | J3: National comprehensive wealth index | K3: =VLOOKUP(K$1,reg_bal!$D$1:$CA$184,$A3,FALSE)/1000000 -> 1.5739827e+08 | L3: =VLOOKUP(L$1,reg_bal!$D$1:$CA$184,$A3,FALSE)/1000000 -> 1.7387068e+08 | M3: =VLOOKUP(M$1,reg_bal!$D$1:$CA$184,$A3,FALSE)/1000000 -> 1.8486707e+08 | N3: =VLOOKUP(N$1,reg_bal!$D$1:$CA$184,$A3,FALSE)/1000000 -> 1.9448715e+08 | O3: =VLOOKUP(O$1,reg_bal!$D$1:$CA$184,$A3,FALSE)/1000000 -> 2.0871002e+08 | P3: =VLOOKUP(P$1,reg_bal!$D$1:$CA$184,$A3,FALSE)/1000000 -> 2.2914641e+08 | R3: National comprehensive wealth index | S3: =VLOOKUP(S$1,reg_bal!$D$1:$CA$184,$A3,FALSE)/1000000 -> 19712792 | T3: =VLOOKUP(T$1,reg_bal!$D$1:$CA$184,$A3,FALSE)/1000000 -> 23981260 | U3: =VLOOKUP(U$1,reg_bal!$D$1:$CA$184,$A3,FALSE)/1000000 -> 29509409 | V3: =VLOOKUP(V$1,reg_bal!$D$1:$CA$184,$A3,FALSE)/1000000 -> 33434596 | W3: =VLOOKUP(W$1,reg_bal!$D$1:$CA$184,$A3,FALSE)/1000000 -> 39976709 | X3: =VLOOKUP(X$1,reg_bal!$D$1:$CA$184,$A3,FALSE)/1000000 -> 44660724 | Z3: National comprehensive wealth index | AA3: =VLOOKUP(AA$1,reg_bal!$D$1:$CA$184,$A3,FALSE)/1000000 -> 8208423.5 | AB3: =VLOOKUP(AB$1,reg_bal!$D$1:$CA$184,$A3,FALSE)/1000000 -> 12993472 | AC3: =VLOOKUP(AC$1,reg_bal!$D$1:$CA$184,$A3,FALSE)/1000000 -> 16554161 | AD3: =VLOOKUP(AD$1,reg_bal!$D$1:$CA$184,$A3,FALSE)/1000000 -> 21711813 | AE3: =VLOOKUP(AE$1,reg_bal!$D$1:$CA$184,$A3,FALSE)/1000000 -> 26444159 | AF3: =VLOOKUP(AF$1,reg_bal!$D$1:$CA$184,$A3,FALSE)/1000000 -> 29657201 | AH3: National comprehensive wealth index | AI3: =VLOOKUP(AI$1,reg_bal!$D$1:$CA$184,$A3,FALSE)/1000000 -> 1.7804259e+08 | AJ3: =VLOOKUP(AJ$1,reg_bal!$D$1:$CA$184,$A3,FALSE)/1000000 -> 2.0306474e+08 | AK3: =VLOOKUP(AK$1,reg_bal!$D$1:$CA$184,$A3,FALSE)/1000000 -> 2.2257549e+08 | AL3: =VLOOKUP(AL$1,reg_bal!$D$1:$CA$184,$A3,FALSE)/1000000 -> 2.3382974e+08 | AM3: =VLOOKUP(AM$1,reg_bal!$D$1:$CA$184,$A3,FALSE)/1000000 -> 2.5180111e+08 | AN3: =VLOOKUP(AN$1,reg_bal!$D$1:$CA$184,$A3,FALSE)/1000000 -> 2.7167418e+08 | AP3: National comprehensive wealth index | AQ3: =VLOOKUP(AQ$1,reg_bal!$D$1:$CA$184,$A3,FALSE)/1000000 -> 14943896 | AR3: =VLOOKUP(AR$1,reg_bal!$D$1:$CA$184,$A3,FALSE)/1000000 -> 18013765 | AS3: =VLOOKUP(AS$1,reg_bal!$D$1:$CA$184,$A3,FALSE)/1000000 -> 20163914 | AT3: =VLOOKUP(AT$1,reg_bal!$D$1:$CA$184,$A3,FALSE)/1000000 -> 22778952 | AU3: =VLOOKUP(AU$1,reg_bal!$D$1:$CA$184,$A3,FALSE)/1000000 -> 25427990 | AV3: =VLOOKUP(AV$1,reg_bal!$D$1:$CA$184,$A3,FALSE)/1000000 -> 27705965 | AX3: National comprehensive wealth index | AY3: =VLOOKUP(AY$1,reg_bal!$D$1:$CA$184,$A3,FALSE)/1000000 -> 8239433.9 | AZ3: =VLOOKUP(AZ$1,reg_bal!$D$1:$CA$184,$A3,FALSE)/1000000 -> 10495270 | BA3: =VLOOKUP(BA$1,reg_bal!$D$1:$CA$184,$A3,FALSE)/1000000 -> 13503130 | BB3: =VLOOKUP(BB$1,reg_bal!$D$1:$CA$184,$A3,FALSE)/1000000 -> 14964006 | BC3: =VLOOKUP(BC$1,reg_bal!$D$1:$CA$184,$A3,FALSE)/1000000 -> 16699672 | BD3: =VLOOKUP(BD$1,reg_bal!$D$1:$CA$184,$A3,FALSE)/1000000 -> 19352782
A4: 3 | B4: Produced capital | C4: =VLOOKUP(C$1,reg_bal!$D$1:$CA$184,$A4,FALSE)/1000000 -> 33360180 | D4: =VLOOKUP(D$1,reg_bal!$D$1:$CA$184,$A4,FALSE)/1000000 -> 39220179 | E4: =VLOOKUP(E$1,reg_bal!$D$1:$CA$184,$A4,FALSE)/1000000 -> 45514736 | F4: =VLOOKUP(F$1,reg_bal!$D$1:$CA$184,$A4,FALSE)/1000000 -> 52769626 | G4: =VLOOKUP(G$1,reg_bal!$D$1:$CA$184,$A4,FALSE)/1000000 -> 62806035 | H4: =VLOOKUP(H$1,reg_bal!$D$1:$CA$184,$A4,FALSE)/1000000 -> 76914559 | J4: Produced capital | K4: =VLOOKUP(K$1,reg_bal!$D$1:$CA$184,$A4,FALSE)/1000000 -> 46412123 | L4: =VLOOKUP(L$1,reg_bal!$D$1:$CA$184,$A4,FALSE)/1000000 -> 50993594 | M4: =VLOOKUP(M$1,reg_bal!$D$1:$CA$184,$A4,FALSE)/1000000 -> 56146630 | N4: =VLOOKUP(N$1,reg_bal!$D$1:$CA$184,$A4,FALSE)/1000000 -> 62150033 | O4: =VLOOKUP(O$1,reg_bal!$D$1:$CA$184,$A4,FALSE)/1000000 -> 66844173 | P4: =VLOOKUP(P$1,reg_bal!$D$1:$CA$184,$A4,FALSE)/1000000 -> 72980189 | R4: Produced capital | S4: =VLOOKUP(S$1,reg_bal!$D$1:$CA$184,$A4,FALSE)/1000000 -> 3314193.2 | T4: =VLOOKUP(T$1,reg_bal!$D$1:$CA$184,$A4,FALSE)/1000000 -> 4110388.2 | U4: =VLOOKUP(U$1,reg_bal!$D$1:$CA$184,$A4,FALSE)/1000000 -> 4765338.1 | V4: =VLOOKUP(V$1,reg_bal!$D$1:$CA$184,$A4,FALSE)/1000000 -> 5866126.3 | W4: =VLOOKUP(W$1,reg_bal!$D$1:$CA$184,$A4,FALSE)/1000000 -> 7277421.8 | X4: =VLOOKUP(X$1,reg_bal!$D$1:$CA$184,$A4,FALSE)/1000000 -> 8269952.1 | Z4: Produced capital | AA4: =VLOOKUP(AA$1,reg_bal!$D$1:$CA$184,$A4,FALSE)/1000000 -> 1022099.5 | AB4: =VLOOKUP(AB$1,reg_bal!$D$1:$CA$184,$A4,FALSE)/1000000 -> 1329999.8 | AC4: =VLOOKUP(AC$1,reg_bal!$D$1:$CA$184,$A4,FALSE)/1000000 -> 1700836.8 | AD4: =VLOOKUP(AD$1,reg_bal!$D$1:$CA$184,$A4,FALSE)/1000000 -> 2451869.7 | AE4: =VLOOKUP(AE$1,reg_bal!$D$1:$CA$184,$A4,FALSE)/1000000 -> 3265892.6 | AF4: =VLOOKUP(AF$1,reg_bal!$D$1:$CA$184,$A4,FALSE)/1000000 -> 4014551.4 | AH4: Produced capital | AI4: =VLOOKUP(AI$1,reg_bal!$D$1:$CA$184,$A4,FALSE)/1000000 -> 48554065 | AJ4: =VLOOKUP(AJ$1,reg_bal!$D$1:$CA$184,$A4,FALSE)/1000000 -> 60018292 | AK4: =VLOOKUP(AK$1,reg_bal!$D$1:$CA$184,$A4,FALSE)/1000000 -> 71815785 | AL4: =VLOOKUP(AL$1,reg_bal!$D$1:$CA$184,$A4,FALSE)/1000000 -> 81783392 | AM4: =VLOOKUP(AM$1,reg_bal!$D$1:$CA$184,$A4,FALSE)/1000000 -> 90429761 | AN4: =VLOOKUP(AN$1,reg_bal!$D$1:$CA$184,$A4,FALSE)/1000000 -> 1.0099927e+08 | AP4: Produced capital | AQ4: =VLOOKUP(AQ$1,reg_bal!$D$1:$CA$184,$A4,FALSE)/1000000 -> 296239.11 | AR4: =VLOOKUP(AR$1,reg_bal!$D$1:$CA$184,$A4,FALSE)/1000000 -> 429895.96 | AS4: =VLOOKUP(AS$1,reg_bal!$D$1:$CA$184,$A4,FALSE)/1000000 -> 657371.25 | AT4: =VLOOKUP(AT$1,reg_bal!$D$1:$CA$184,$A4,FALSE)/1000000 -> 1094607.9 | AU4: =VLOOKUP(AU$1,reg_bal!$D$1:$CA$184,$A4,FALSE)/1000000 -> 1736646.4 | AV4: =VLOOKUP(AV$1,reg_bal!$D$1:$CA$184,$A4,FALSE)/1000000 -> 2609051.4 | AX4: Produced capital | AY4: =VLOOKUP(AY$1,reg_bal!$D$1:$CA$184,$A4,FALSE)/1000000 -> 1184101.7 | AZ4: =VLOOKUP(AZ$1,reg_bal!$D$1:$CA$184,$A4,FALSE)/1000000 -> 1357848 | BA4: =VLOOKUP(BA$1,reg_bal!$D$1:$CA$184,$A4,FALSE)/1000000 -> 1532922.7 | BB4: =VLOOKUP(BB$1,reg_bal!$D$1:$CA$184,$A4,FALSE)/1000000 -> 1830275.1 | BC4: =VLOOKUP(BC$1,reg_bal!$D$1:$CA$184,$A4,FALSE)/1000000 -> 2259903.5 | BD4: =VLOOKUP(BD$1,reg_bal!$D$1:$CA$184,$A4,FALSE)/1000000 -> 2727092.5
A5: 33 | B5: Human capital | C5: =VLOOKUP(C$1,reg_bal!$D$1:$CA$184,$A5,FALSE)/1000000 -> 97951935 | D5: =VLOOKUP(D$1,reg_bal!$D$1:$CA$184,$A5,FALSE)/1000000 -> 1.0858926e+08 | E5: =VLOOKUP(E$1,reg_bal!$D$1:$CA$184,$A5,FALSE)/1000000 -> 1.158337e+08 | F5: =VLOOKUP(F$1,reg_bal!$D$1:$CA$184,$A5,FALSE)/1000000 -> 1.2155768e+08 | G5: =VLOOKUP(G$1,reg_bal!$D$1:$CA$184,$A5,FALSE)/1000000 -> 1.3080451e+08 | H5: =VLOOKUP(H$1,reg_bal!$D$1:$CA$184,$A5,FALSE)/1000000 -> 1.386964e+08 | J5: Human capital | K5: =VLOOKUP(K$1,reg_bal!$D$1:$CA$184,$A5,FALSE)/1000000 -> 1.0656958e+08 | L5: =VLOOKUP(L$1,reg_bal!$D$1:$CA$184,$A5,FALSE)/1000000 -> 1.1502888e+08 | M5: =VLOOKUP(M$1,reg_bal!$D$1:$CA$184,$A5,FALSE)/1000000 -> 1.2188506e+08 | N5: =VLOOKUP(N$1,reg_bal!$D$1:$CA$184,$A5,FALSE)/1000000 -> 1.2913855e+08 | O5: =VLOOKUP(O$1,reg_bal!$D$1:$CA$184,$A5,FALSE)/1000000 -> 1.3548696e+08 | P5: =VLOOKUP(P$1,reg_bal!$D$1:$CA$184,$A5,FALSE)/1000000 -> 1.4680292e+08 | R5: Human capital | S5: =VLOOKUP(S$1,reg_bal!$D$1:$CA$184,$A5,FALSE)/1000000 -> 14590676 | T5: =VLOOKUP(T$1,reg_bal!$D$1:$CA$184,$A5,FALSE)/1000000 -> 17217282 | U5: =VLOOKUP(U$1,reg_bal!$D$1:$CA$184,$A5,FALSE)/1000000 -> 20917216 | V5: =VLOOKUP(V$1,reg_bal!$D$1:$CA$184,$A5,FALSE)/1000000 -> 24291428 | W5: =VLOOKUP(W$1,reg_bal!$D$1:$CA$184,$A5,FALSE)/1000000 -> 28508728 | X5: =VLOOKUP(X$1,reg_bal!$D$1:$CA$184,$A5,FALSE)/1000000 -> 32158955 | Z5: Human capital | AA5: =VLOOKUP(AA$1,reg_bal!$D$1:$CA$184,$A5,FALSE)/1000000 -> 4246279.7 | AB5: =VLOOKUP(AB$1,reg_bal!$D$1:$CA$184,$A5,FALSE)/1000000 -> 5292099 | AC5: =VLOOKUP(AC$1,reg_bal!$D$1:$CA$184,$A5,FALSE)/1000000 -> 6622522.4 | AD5: =VLOOKUP(AD$1,reg_bal!$D$1:$CA$184,$A5,FALSE)/1000000 -> 9347257 | AE5: =VLOOKUP(AE$1,reg_bal!$D$1:$CA$184,$A5,FALSE)/1000000 -> 11408421 | AF5: =VLOOKUP(AF$1,reg_bal!$D$1:$CA$184,$A5,FALSE)/1000000 -> 12671658 | AH5: Human capital | AI5: =VLOOKUP(AI$1,reg_bal!$D$1:$CA$184,$A5,FALSE)/1000000 -> 1.2898673e+08 | AJ5: =VLOOKUP(AJ$1,reg_bal!$D$1:$CA$184,$A5,FALSE)/1000000 -> 1.4384835e+08 | AK5: =VLOOKUP(AK$1,reg_bal!$D$1:$CA$184,$A5,FALSE)/1000000 -> 1.5099931e+08 | AL5: =VLOOKUP(AL$1,reg_bal!$D$1:$CA$184,$A5,FALSE)/1000000 -> 1.5223253e+08 | AM5: =VLOOKUP(AM$1,reg_bal!$D$1:$CA$184,$A5,FALSE)/1000000 -> 1.6530073e+08 | AN5: =VLOOKUP(AN$1,reg_bal!$D$1:$CA$184,$A5,FALSE)/1000000 -> 1.8023651e+08 | AP5: Human capital | AQ5: =VLOOKUP(AQ$1,reg_bal!$D$1:$CA$184,$A5,FALSE)/1000000 -> 8377362 | AR5: =VLOOKUP(AR$1,reg_bal!$D$1:$CA$184,$A5,FALSE)/1000000 -> 10795887 | AS5: =VLOOKUP(AS$1,reg_bal!$D$1:$CA$184,$A5,FALSE)/1000000 -> 12145905 | AT5: =VLOOKUP(AT$1,reg_bal!$D$1:$CA$184,$A5,FALSE)/1000000 -> 14290990 | AU5: =VLOOKUP(AU$1,reg_bal!$D$1:$CA$184,$A5,FALSE)/1000000 -> 15674941 | AV5: =VLOOKUP(AV$1,reg_bal!$D$1:$CA$184,$A5,FALSE)/1000000 -> 17056621 | AX5: Human capital | AY5: =VLOOKUP(AY$1,reg_bal!$D$1:$CA$184,$A5,FALSE)/1000000 -> 3943206.1 | AZ5: =VLOOKUP(AZ$1,reg_bal!$D$1:$CA$184,$A5,FALSE)/1000000 -> 4765913.6 | BA5: =VLOOKUP(BA$1,reg_bal!$D$1:$CA$184,$A5,FALSE)/1000000 -> 5823685.7 | BB5: =VLOOKUP(BB$1,reg_bal!$D$1:$CA$184,$A5,FALSE)/1000000 -> 6756991 | BC5: =VLOOKUP(BC$1,reg_bal!$D$1:$CA$184,$A5,FALSE)/1000000 -> 8346567.5 | BD5: =VLOOKUP(BD$1,reg_bal!$D$1:$CA$184,$A5,FALSE)/1000000 -> 10047833
A6: 6 | B6: Renewable natural capital | C6: =VLOOKUP(C$1,reg_bal!$D$1:$CA$184,$A6,FALSE)/1000000 -> 19358285 | D6: =VLOOKUP(D$1,reg_bal!$D$1:$CA$184,$A6,FALSE)/1000000 -> 19532928 | E6: =VLOOKUP(E$1,reg_bal!$D$1:$CA$184,$A6,FALSE)/1000000 -> 19756011 | F6: =VLOOKUP(F$1,reg_bal!$D$1:$CA$184,$A6,FALSE)/1000000 -> 20279888 | G6: =VLOOKUP(G$1,reg_bal!$D$1:$CA$184,$A6,FALSE)/1000000 -> 20872601 | H6: =VLOOKUP(H$1,reg_bal!$D$1:$CA$184,$A6,FALSE)/1000000 -> 21210113 | J6: Renewable natural capital | K6: =VLOOKUP(K$1,reg_bal!$D$1:$CA$184,$A6,FALSE)/1000000 -> 4651123.5 | L6: =VLOOKUP(L$1,reg_bal!$D$1:$CA$184,$A6,FALSE)/1000000 -> 4648279.8 | M6: =VLOOKUP(M$1,reg_bal!$D$1:$CA$184,$A6,FALSE)/1000000 -> 4602638.9 | N6: =VLOOKUP(N$1,reg_bal!$D$1:$CA$184,$A6,FALSE)/1000000 -> 4670980.9 | O6: =VLOOKUP(O$1,reg_bal!$D$1:$CA$184,$A6,FALSE)/1000000 -> 4627592.1 | P6: =VLOOKUP(P$1,reg_bal!$D$1:$CA$184,$A6,FALSE)/1000000 -> 4621511.3 | R6: Renewable natural capital | S6: =VLOOKUP(S$1,reg_bal!$D$1:$CA$184,$A6,FALSE)/1000000 -> 3802429.1 | T6: =VLOOKUP(T$1,reg_bal!$D$1:$CA$184,$A6,FALSE)/1000000 -> 3966164.5 | U6: =VLOOKUP(U$1,reg_bal!$D$1:$CA$184,$A6,FALSE)/1000000 -> 3987509.6 | V6: =VLOOKUP(V$1,reg_bal!$D$1:$CA$184,$A6,FALSE)/1000000 -> 4091915.9 | W6: =VLOOKUP(W$1,reg_bal!$D$1:$CA$184,$A6,FALSE)/1000000 -> 4006208.7 | X6: =VLOOKUP(X$1,reg_bal!$D$1:$CA$184,$A6,FALSE)/1000000 -> 4033915.9 | Z6: Renewable natural capital | AA6: =VLOOKUP(AA$1,reg_bal!$D$1:$CA$184,$A6,FALSE)/1000000 -> 1869183.4 | AB6: =VLOOKUP(AB$1,reg_bal!$D$1:$CA$184,$A6,FALSE)/1000000 -> 1868777.5 | AC6: =VLOOKUP(AC$1,reg_bal!$D$1:$CA$184,$A6,FALSE)/1000000 -> 1807182.1 | AD6: =VLOOKUP(AD$1,reg_bal!$D$1:$CA$184,$A6,FALSE)/1000000 -> 1810097.5 | AE6: =VLOOKUP(AE$1,reg_bal!$D$1:$CA$184,$A6,FALSE)/1000000 -> 1831796.2 | AF6: =VLOOKUP(AF$1,reg_bal!$D$1:$CA$184,$A6,FALSE)/1000000 -> 1889691.3 | AH6: Renewable natural capital | AI6: =VLOOKUP(AI$1,reg_bal!$D$1:$CA$184,$A6,FALSE)/1000000 -> 2277053.7 | AJ6: =VLOOKUP(AJ$1,reg_bal!$D$1:$CA$184,$A6,FALSE)/1000000 -> 2297958 | AK6: =VLOOKUP(AK$1,reg_bal!$D$1:$CA$184,$A6,FALSE)/1000000 -> 2305432.4 | AL6: =VLOOKUP(AL$1,reg_bal!$D$1:$CA$184,$A6,FALSE)/1000000 -> 2293683 | AM6: =VLOOKUP(AM$1,reg_bal!$D$1:$CA$184,$A6,FALSE)/1000000 -> 2332502 | AN6: =VLOOKUP(AN$1,reg_bal!$D$1:$CA$184,$A6,FALSE)/1000000 -> 2345370.9 | AP6: Renewable natural capital | AQ6: =VLOOKUP(AQ$1,reg_bal!$D$1:$CA$184,$A6,FALSE)/1000000 -> 7882283.2 | AR6: =VLOOKUP(AR$1,reg_bal!$D$1:$CA$184,$A6,FALSE)/1000000 -> 7914888.4 | AS6: =VLOOKUP(AS$1,reg_bal!$D$1:$CA$184,$A6,FALSE)/1000000 -> 7903137.7 | AT6: =VLOOKUP(AT$1,reg_bal!$D$1:$CA$184,$A6,FALSE)/1000000 -> 7880692.1 | AU6: =VLOOKUP(AU$1,reg_bal!$D$1:$CA$184,$A6,FALSE)/1000000 -> 7927278.2 | AV6: =VLOOKUP(AV$1,reg_bal!$D$1:$CA$184,$A6,FALSE)/1000000 -> 7950704.3 | AX6: Renewable natural capital | AY6: =VLOOKUP(AY$1,reg_bal!$D$1:$CA$184,$A6,FALSE)/1000000 -> 4903226.4 | AZ6: =VLOOKUP(AZ$1,reg_bal!$D$1:$CA$184,$A6,FALSE)/1000000 -> 4972074.1 | BA6: =VLOOKUP(BA$1,reg_bal!$D$1:$CA$184,$A6,FALSE)/1000000 -> 5094108.1 | BB6: =VLOOKUP(BB$1,reg_bal!$D$1:$CA$184,$A6,FALSE)/1000000 -> 5212221.2 | BC6: =VLOOKUP(BC$1,reg_bal!$D$1:$CA$184,$A6,FALSE)/1000000 -> 5423690.7 | BD6: =VLOOKUP(BD$1,reg_bal!$D$1:$CA$184,$A6,FALSE)/1000000 -> 5553628.2
A7: 8 | B7: Forests, timber | C7: =VLOOKUP(C$1,reg_bal!$D$1:$CA$184,$A7,FALSE)/1000000 -> 843018.35 | D7: =VLOOKUP(D$1,reg_bal!$D$1:$CA$184,$A7,FALSE)/1000000 -> 831364.32 | E7: =VLOOKUP(E$1,reg_bal!$D$1:$CA$184,$A7,FALSE)/1000000 -> 841638.45 | F7: =VLOOKUP(F$1,reg_bal!$D$1:$CA$184,$A7,FALSE)/1000000 -> 851912.58 | G7: =VLOOKUP(G$1,reg_bal!$D$1:$CA$184,$A7,FALSE)/1000000 -> 873013.5 | H7: =VLOOKUP(H$1,reg_bal!$D$1:$CA$184,$A7,FALSE)/1000000 -> 887369.23 | J7: Forests, timber | K7: =VLOOKUP(K$1,reg_bal!$D$1:$CA$184,$A7,FALSE)/1000000 -> 416870.73 | L7: =VLOOKUP(L$1,reg_bal!$D$1:$CA$184,$A7,FALSE)/1000000 -> 415240.42 | M7: =VLOOKUP(M$1,reg_bal!$D$1:$CA$184,$A7,FALSE)/1000000 -> 416913.17 | N7: =VLOOKUP(N$1,reg_bal!$D$1:$CA$184,$A7,FALSE)/1000000 -> 425025.77 | O7: =VLOOKUP(O$1,reg_bal!$D$1:$CA$184,$A7,FALSE)/1000000 -> 427549.67 | P7: =VLOOKUP(P$1,reg_bal!$D$1:$CA$184,$A7,FALSE)/1000000 -> 416943.81 | R7: Forests, timber | S7: =VLOOKUP(S$1,reg_bal!$D$1:$CA$184,$A7,FALSE)/1000000 -> 549429.24 | T7: =VLOOKUP(T$1,reg_bal!$D$1:$CA$184,$A7,FALSE)/1000000 -> 536680.66 | U7: =VLOOKUP(U$1,reg_bal!$D$1:$CA$184,$A7,FALSE)/1000000 -> 522613.93 | V7: =VLOOKUP(V$1,reg_bal!$D$1:$CA$184,$A7,FALSE)/1000000 -> 508532.69 | W7: =VLOOKUP(W$1,reg_bal!$D$1:$CA$184,$A7,FALSE)/1000000 -> 503944.38 | X7: =VLOOKUP(X$1,reg_bal!$D$1:$CA$184,$A7,FALSE)/1000000 -> 499193.48 | Z7: Forests, timber | AA7: =VLOOKUP(AA$1,reg_bal!$D$1:$CA$184,$A7,FALSE)/1000000 -> 4958.9658 | AB7: =VLOOKUP(AB$1,reg_bal!$D$1:$CA$184,$A7,FALSE)/1000000 -> 5035.3422 | AC7: =VLOOKUP(AC$1,reg_bal!$D$1:$CA$184,$A7,FALSE)/1000000 -> 5343.1232 | AD7: =VLOOKUP(AD$1,reg_bal!$D$1:$CA$184,$A7,FALSE)/1000000 -> 5650.8993 | AE7: =VLOOKUP(AE$1,reg_bal!$D$1:$CA$184,$A7,FALSE)/1000000 -> 5645.1712 | AF7: =VLOOKUP(AF$1,reg_bal!$D$1:$CA$184,$A7,FALSE)/1000000 -> 5731.0256 | AH7: Forests, timber | AI7: =VLOOKUP(AI$1,reg_bal!$D$1:$CA$184,$A7,FALSE)/1000000 -> 227824.49 | AJ7: =VLOOKUP(AJ$1,reg_bal!$D$1:$CA$184,$A7,FALSE)/1000000 -> 228150.5 | AK7: =VLOOKUP(AK$1,reg_bal!$D$1:$CA$184,$A7,FALSE)/1000000 -> 229820.27 | AL7: =VLOOKUP(AL$1,reg_bal!$D$1:$CA$184,$A7,FALSE)/1000000 -> 231490.04 | AM7: =VLOOKUP(AM$1,reg_bal!$D$1:$CA$184,$A7,FALSE)/1000000 -> 232375.87 | AN7: =VLOOKUP(AN$1,reg_bal!$D$1:$CA$184,$A7,FALSE)/1000000 -> 229839.06 | AP7: Forests, timber | AQ7: =VLOOKUP(AQ$1,reg_bal!$D$1:$CA$184,$A7,FALSE)/1000000 -> 53008.086 | AR7: =VLOOKUP(AR$1,reg_bal!$D$1:$CA$184,$A7,FALSE)/1000000 -> 54084.585 | AS7: =VLOOKUP(AS$1,reg_bal!$D$1:$CA$184,$A7,FALSE)/1000000 -> 54629.941 | AT7: =VLOOKUP(AT$1,reg_bal!$D$1:$CA$184,$A7,FALSE)/1000000 -> 55175.297 | AU7: =VLOOKUP(AU$1,reg_bal!$D$1:$CA$184,$A7,FALSE)/1000000 -> 55981.882 | AV7: =VLOOKUP(AV$1,reg_bal!$D$1:$CA$184,$A7,FALSE)/1000000 -> 56744.726 | AX7: Forests, timber | AY7: =VLOOKUP(AY$1,reg_bal!$D$1:$CA$184,$A7,FALSE)/1000000 -> 796601.22 | AZ7: =VLOOKUP(AZ$1,reg_bal!$D$1:$CA$184,$A7,FALSE)/1000000 -> 778833.8 | BA7: =VLOOKUP(BA$1,reg_bal!$D$1:$CA$184,$A7,FALSE)/1000000 -> 760945.08 | BB7: =VLOOKUP(BB$1,reg_bal!$D$1:$CA$184,$A7,FALSE)/1000000 -> 742912.02 | BC7: =VLOOKUP(BC$1,reg_bal!$D$1:$CA$184,$A7,FALSE)/1000000 -> 692207.17 | BD7: =VLOOKUP(BD$1,reg_bal!$D$1:$CA$184,$A7,FALSE)/1000000 -> 733874.82
A8: 10 | B8: Forests, recreation, hunting, and fishing services (es1) | C8: =VLOOKUP(C$1,reg_bal!$D$1:$CA$184,$A8,FALSE)/1000000 -> 808161.35 | D8: =VLOOKUP(D$1,reg_bal!$D$1:$CA$184,$A8,FALSE)/1000000 -> 841873.37 | E8: =VLOOKUP(E$1,reg_bal!$D$1:$CA$184,$A8,FALSE)/1000000 -> 883202.26 | F8: =VLOOKUP(F$1,reg_bal!$D$1:$CA$184,$A8,FALSE)/1000000 -> 924531.14 | G8: =VLOOKUP(G$1,reg_bal!$D$1:$CA$184,$A8,FALSE)/1000000 -> 958464.16 | H8: =VLOOKUP(H$1,reg_bal!$D$1:$CA$184,$A8,FALSE)/1000000 -> 991583.27 | J8: Forests, recreation, hunting, and fishing services (es1) | K8: =VLOOKUP(K$1,reg_bal!$D$1:$CA$184,$A8,FALSE)/1000000 -> 432433.65 | L8: =VLOOKUP(L$1,reg_bal!$D$1:$CA$184,$A8,FALSE)/1000000 -> 444449.3 | M8: =VLOOKUP(M$1,reg_bal!$D$1:$CA$184,$A8,FALSE)/1000000 -> 454089.64 | N8: =VLOOKUP(N$1,reg_bal!$D$1:$CA$184,$A8,FALSE)/1000000 -> 466133.35 | O8: =VLOOKUP(O$1,reg_bal!$D$1:$CA$184,$A8,FALSE)/1000000 -> 471351.44 | P8: =VLOOKUP(P$1,reg_bal!$D$1:$CA$184,$A8,FALSE)/1000000 -> 475698.18 | R8: Forests, recreation, hunting, and fishing services (es1) | S8: =VLOOKUP(S$1,reg_bal!$D$1:$CA$184,$A8,FALSE)/1000000 -> 72253.26 | T8: =VLOOKUP(T$1,reg_bal!$D$1:$CA$184,$A8,FALSE)/1000000 -> 71582.602 | U8: =VLOOKUP(U$1,reg_bal!$D$1:$CA$184,$A8,FALSE)/1000000 -> 70514.987 | V8: =VLOOKUP(V$1,reg_bal!$D$1:$CA$184,$A8,FALSE)/1000000 -> 69447.373 | W8: =VLOOKUP(W$1,reg_bal!$D$1:$CA$184,$A8,FALSE)/1000000 -> 68913.282 | X8: =VLOOKUP(X$1,reg_bal!$D$1:$CA$184,$A8,FALSE)/1000000 -> 68201.039 | Z8: Forests, recreation, hunting, and fishing services (es1) | AA8: =VLOOKUP(AA$1,reg_bal!$D$1:$CA$184,$A8,FALSE)/1000000 -> 59988.051 | AB8: =VLOOKUP(AB$1,reg_bal!$D$1:$CA$184,$A8,FALSE)/1000000 -> 61255.588 | AC8: =VLOOKUP(AC$1,reg_bal!$D$1:$CA$184,$A8,FALSE)/1000000 -> 64285.446 | AD8: =VLOOKUP(AD$1,reg_bal!$D$1:$CA$184,$A8,FALSE)/1000000 -> 67315.304 | AE8: =VLOOKUP(AE$1,reg_bal!$D$1:$CA$184,$A8,FALSE)/1000000 -> 67819.276 | AF8: =VLOOKUP(AF$1,reg_bal!$D$1:$CA$184,$A8,FALSE)/1000000 -> 67150.045 | AH8: Forests, recreation, hunting, and fishing services (es1) | AI8: =VLOOKUP(AI$1,reg_bal!$D$1:$CA$184,$A8,FALSE)/1000000 -> 316340.39 | AJ8: =VLOOKUP(AJ$1,reg_bal!$D$1:$CA$184,$A8,FALSE)/1000000 -> 316551.38 | AK8: =VLOOKUP(AK$1,reg_bal!$D$1:$CA$184,$A8,FALSE)/1000000 -> 317924.81 | AL8: =VLOOKUP(AL$1,reg_bal!$D$1:$CA$184,$A8,FALSE)/1000000 -> 319298.25 | AM8: =VLOOKUP(AM$1,reg_bal!$D$1:$CA$184,$A8,FALSE)/1000000 -> 319994 | AN8: =VLOOKUP(AN$1,reg_bal!$D$1:$CA$184,$A8,FALSE)/1000000 -> 319745.82 | AP8: Forests, recreation, hunting, and fishing services (es1) | AQ8: =VLOOKUP(AQ$1,reg_bal!$D$1:$CA$184,$A8,FALSE)/1000000 -> 26727.615 | AR8: =VLOOKUP(AR$1,reg_bal!$D$1:$CA$184,$A8,FALSE)/1000000 -> 27148.097 | AS8: =VLOOKUP(AS$1,reg_bal!$D$1:$CA$184,$A8,FALSE)/1000000 -> 27352.937 | AT8: =VLOOKUP(AT$1,reg_bal!$D$1:$CA$184,$A8,FALSE)/1000000 -> 27576.542 | AU8: =VLOOKUP(AU$1,reg_bal!$D$1:$CA$184,$A8,FALSE)/1000000 -> 28016.653 | AV8: =VLOOKUP(AV$1,reg_bal!$D$1:$CA$184,$A8,FALSE)/1000000 -> 28382.281 | AX8: Forests, recreation, hunting, and fishing services (es1) | AY8: =VLOOKUP(AY$1,reg_bal!$D$1:$CA$184,$A8,FALSE)/1000000 -> 152492.1 | AZ8: =VLOOKUP(AZ$1,reg_bal!$D$1:$CA$184,$A8,FALSE)/1000000 -> 149355.39 | BA8: =VLOOKUP(BA$1,reg_bal!$D$1:$CA$184,$A8,FALSE)/1000000 -> 146323.66 | BB8: =VLOOKUP(BB$1,reg_bal!$D$1:$CA$184,$A8,FALSE)/1000000 -> 143291.94 | BC8: =VLOOKUP(BC$1,reg_bal!$D$1:$CA$184,$A8,FALSE)/1000000 -> 149961.9 | BD8: =VLOOKUP(BD$1,reg_bal!$D$1:$CA$184,$A8,FALSE)/1000000 -> 145260.44
A9: 11 | B9: Forests, non-wood forest products (es2) | C9: =VLOOKUP(C$1,reg_bal!$D$1:$CA$184,$A9,FALSE)/1000000 -> 173188.29 | D9: =VLOOKUP(D$1,reg_bal!$D$1:$CA$184,$A9,FALSE)/1000000 -> 175548.21 | E9: =VLOOKUP(E$1,reg_bal!$D$1:$CA$184,$A9,FALSE)/1000000 -> 180328.7 | F9: =VLOOKUP(F$1,reg_bal!$D$1:$CA$184,$A9,FALSE)/1000000 -> 185109.19 | G9: =VLOOKUP(G$1,reg_bal!$D$1:$CA$184,$A9,FALSE)/1000000 -> 188620.77 | H9: =VLOOKUP(H$1,reg_bal!$D$1:$CA$184,$A9,FALSE)/1000000 -> 192104.13 | J9: Forests, non-wood forest products (es2) | K9: =VLOOKUP(K$1,reg_bal!$D$1:$CA$184,$A9,FALSE)/1000000 -> 126164.06 | L9: =VLOOKUP(L$1,reg_bal!$D$1:$CA$184,$A9,FALSE)/1000000 -> 127440.6 | M9: =VLOOKUP(M$1,reg_bal!$D$1:$CA$184,$A9,FALSE)/1000000 -> 128729.77 | N9: =VLOOKUP(N$1,reg_bal!$D$1:$CA$184,$A9,FALSE)/1000000 -> 130366.71 | O9: =VLOOKUP(O$1,reg_bal!$D$1:$CA$184,$A9,FALSE)/1000000 -> 131281.04 | P9: =VLOOKUP(P$1,reg_bal!$D$1:$CA$184,$A9,FALSE)/1000000 -> 132062.42 | R9: Forests, non-wood forest products (es2) | S9: =VLOOKUP(S$1,reg_bal!$D$1:$CA$184,$A9,FALSE)/1000000 -> 164948.29 | T9: =VLOOKUP(T$1,reg_bal!$D$1:$CA$184,$A9,FALSE)/1000000 -> 160732.1 | U9: =VLOOKUP(U$1,reg_bal!$D$1:$CA$184,$A9,FALSE)/1000000 -> 156273.44 | V9: =VLOOKUP(V$1,reg_bal!$D$1:$CA$184,$A9,FALSE)/1000000 -> 151814.78 | W9: =VLOOKUP(W$1,reg_bal!$D$1:$CA$184,$A9,FALSE)/1000000 -> 149552.24 | X9: =VLOOKUP(X$1,reg_bal!$D$1:$CA$184,$A9,FALSE)/1000000 -> 147425.84 | Z9: Forests, non-wood forest products (es2) | AA9: =VLOOKUP(AA$1,reg_bal!$D$1:$CA$184,$A9,FALSE)/1000000 -> 3614.2435 | AB9: =VLOOKUP(AB$1,reg_bal!$D$1:$CA$184,$A9,FALSE)/1000000 -> 3662.144 | AC9: =VLOOKUP(AC$1,reg_bal!$D$1:$CA$184,$A9,FALSE)/1000000 -> 3797.8561 | AD9: =VLOOKUP(AD$1,reg_bal!$D$1:$CA$184,$A9,FALSE)/1000000 -> 3933.5682 | AE9: =VLOOKUP(AE$1,reg_bal!$D$1:$CA$184,$A9,FALSE)/1000000 -> 3950.8709 | AF9: =VLOOKUP(AF$1,reg_bal!$D$1:$CA$184,$A9,FALSE)/1000000 -> 3942.1827 | AH9: Forests, non-wood forest products (es2) | AI9: =VLOOKUP(AI$1,reg_bal!$D$1:$CA$184,$A9,FALSE)/1000000 -> 82953 | AJ9: =VLOOKUP(AJ$1,reg_bal!$D$1:$CA$184,$A9,FALSE)/1000000 -> 83052.852 | AK9: =VLOOKUP(AK$1,reg_bal!$D$1:$CA$184,$A9,FALSE)/1000000 -> 83579.721 | AL9: =VLOOKUP(AL$1,reg_bal!$D$1:$CA$184,$A9,FALSE)/1000000 -> 84106.59 | AM9: =VLOOKUP(AM$1,reg_bal!$D$1:$CA$184,$A9,FALSE)/1000000 -> 84381.581 | AN9: =VLOOKUP(AN$1,reg_bal!$D$1:$CA$184,$A9,FALSE)/1000000 -> 84308.366 | AP9: Forests, non-wood forest products (es2) | AQ9: =VLOOKUP(AQ$1,reg_bal!$D$1:$CA$184,$A9,FALSE)/1000000 -> 28216.965 | AR9: =VLOOKUP(AR$1,reg_bal!$D$1:$CA$184,$A9,FALSE)/1000000 -> 28767.813 | AS9: =VLOOKUP(AS$1,reg_bal!$D$1:$CA$184,$A9,FALSE)/1000000 -> 28944.974 | AT9: =VLOOKUP(AT$1,reg_bal!$D$1:$CA$184,$A9,FALSE)/1000000 -> 29185.809 | AU9: =VLOOKUP(AU$1,reg_bal!$D$1:$CA$184,$A9,FALSE)/1000000 -> 29579.627 | AV9: =VLOOKUP(AV$1,reg_bal!$D$1:$CA$184,$A9,FALSE)/1000000 -> 29934.035 | AX9: Forests, non-wood forest products (es2) | AY9: =VLOOKUP(AY$1,reg_bal!$D$1:$CA$184,$A9,FALSE)/1000000 -> 129266.22 | AZ9: =VLOOKUP(AZ$1,reg_bal!$D$1:$CA$184,$A9,FALSE)/1000000 -> 125825.14 | BA9: =VLOOKUP(BA$1,reg_bal!$D$1:$CA$184,$A9,FALSE)/1000000 -> 122536.93 | BB9: =VLOOKUP(BB$1,reg_bal!$D$1:$CA$184,$A9,FALSE)/1000000 -> 119248.71 | BC9: =VLOOKUP(BC$1,reg_bal!$D$1:$CA$184,$A9,FALSE)/1000000 -> 121315.78 | BD9: =VLOOKUP(BD$1,reg_bal!$D$1:$CA$184,$A9,FALSE)/1000000 -> 117600.36
A10: 12 | B10: Forests, water retention services (es3) | C10: =VLOOKUP(C$1,reg_bal!$D$1:$CA$184,$A10,FALSE)/1000000 -> 946800.49 | D10: =VLOOKUP(D$1,reg_bal!$D$1:$CA$184,$A10,FALSE)/1000000 -> 956308.82 | E10: =VLOOKUP(E$1,reg_bal!$D$1:$CA$184,$A10,FALSE)/1000000 -> 975222.21 | F10: =VLOOKUP(F$1,reg_bal!$D$1:$CA$184,$A10,FALSE)/1000000 -> 994135.6 | G10: =VLOOKUP(G$1,reg_bal!$D$1:$CA$184,$A10,FALSE)/1000000 -> 1016741.2 | H10: =VLOOKUP(H$1,reg_bal!$D$1:$CA$184,$A10,FALSE)/1000000 -> 1033921.6 | J10: Forests, water retention services (es3) | K10: =VLOOKUP(K$1,reg_bal!$D$1:$CA$184,$A10,FALSE)/1000000 -> 601734.64 | L10: =VLOOKUP(L$1,reg_bal!$D$1:$CA$184,$A10,FALSE)/1000000 -> 610036.74 | M10: =VLOOKUP(M$1,reg_bal!$D$1:$CA$184,$A10,FALSE)/1000000 -> 617225.91 | N10: =VLOOKUP(N$1,reg_bal!$D$1:$CA$184,$A10,FALSE)/1000000 -> 627036.19 | O10: =VLOOKUP(O$1,reg_bal!$D$1:$CA$184,$A10,FALSE)/1000000 -> 631483.53 | P10: =VLOOKUP(P$1,reg_bal!$D$1:$CA$184,$A10,FALSE)/1000000 -> 635101.56 | R10: Forests, water retention services (es3) | S10: =VLOOKUP(S$1,reg_bal!$D$1:$CA$184,$A10,FALSE)/1000000 -> 882892.21 | T10: =VLOOKUP(T$1,reg_bal!$D$1:$CA$184,$A10,FALSE)/1000000 -> 859640.87 | U10: =VLOOKUP(U$1,reg_bal!$D$1:$CA$184,$A10,FALSE)/1000000 -> 834435.72 | V10: =VLOOKUP(V$1,reg_bal!$D$1:$CA$184,$A10,FALSE)/1000000 -> 809230.58 | W10: =VLOOKUP(W$1,reg_bal!$D$1:$CA$184,$A10,FALSE)/1000000 -> 797429.29 | X10: =VLOOKUP(X$1,reg_bal!$D$1:$CA$184,$A10,FALSE)/1000000 -> 786724.14 | Z10: Forests, water retention services (es3) | AA10: =VLOOKUP(AA$1,reg_bal!$D$1:$CA$184,$A10,FALSE)/1000000 -> 28862.788 | AB10: =VLOOKUP(AB$1,reg_bal!$D$1:$CA$184,$A10,FALSE)/1000000 -> 29205.794 | AC10: =VLOOKUP(AC$1,reg_bal!$D$1:$CA$184,$A10,FALSE)/1000000 -> 30478.579 | AD10: =VLOOKUP(AD$1,reg_bal!$D$1:$CA$184,$A10,FALSE)/1000000 -> 31751.364 | AE10: =VLOOKUP(AE$1,reg_bal!$D$1:$CA$184,$A10,FALSE)/1000000 -> 31821.072 | AF10: =VLOOKUP(AF$1,reg_bal!$D$1:$CA$184,$A10,FALSE)/1000000 -> 31929.766 | AH10: Forests, water retention services (es3) | AI10: =VLOOKUP(AI$1,reg_bal!$D$1:$CA$184,$A10,FALSE)/1000000 -> 878948.92 | AJ10: =VLOOKUP(AJ$1,reg_bal!$D$1:$CA$184,$A10,FALSE)/1000000 -> 880110.41 | AK10: =VLOOKUP(AK$1,reg_bal!$D$1:$CA$184,$A10,FALSE)/1000000 -> 886080.46 | AL10: =VLOOKUP(AL$1,reg_bal!$D$1:$CA$184,$A10,FALSE)/1000000 -> 892050.5 | AM10: =VLOOKUP(AM$1,reg_bal!$D$1:$CA$184,$A10,FALSE)/1000000 -> 895179.33 | AN10: =VLOOKUP(AN$1,reg_bal!$D$1:$CA$184,$A10,FALSE)/1000000 -> 894384.65 | AP10: Forests, water retention services (es3) | AQ10: =VLOOKUP(AQ$1,reg_bal!$D$1:$CA$184,$A10,FALSE)/1000000 -> 95395.277 | AR10: =VLOOKUP(AR$1,reg_bal!$D$1:$CA$184,$A10,FALSE)/1000000 -> 97599.884 | AS10: =VLOOKUP(AS$1,reg_bal!$D$1:$CA$184,$A10,FALSE)/1000000 -> 98348.656 | AT10: =VLOOKUP(AT$1,reg_bal!$D$1:$CA$184,$A10,FALSE)/1000000 -> 99364.4 | AU10: =VLOOKUP(AU$1,reg_bal!$D$1:$CA$184,$A10,FALSE)/1000000 -> 100819.09 | AV10: =VLOOKUP(AV$1,reg_bal!$D$1:$CA$184,$A10,FALSE)/1000000 -> 102198.19 | AX10: Forests, water retention services (es3) | AY10: =VLOOKUP(AY$1,reg_bal!$D$1:$CA$184,$A10,FALSE)/1000000 -> 262441.83 | AZ10: =VLOOKUP(AZ$1,reg_bal!$D$1:$CA$184,$A10,FALSE)/1000000 -> 251308.36 | BA10: =VLOOKUP(BA$1,reg_bal!$D$1:$CA$184,$A10,FALSE)/1000000 -> 242956.84 | BB10: =VLOOKUP(BB$1,reg_bal!$D$1:$CA$184,$A10,FALSE)/1000000 -> 234605.32 | BC10: =VLOOKUP(BC$1,reg_bal!$D$1:$CA$184,$A10,FALSE)/1000000 -> 234830.24 | BD10: =VLOOKUP(BD$1,reg_bal!$D$1:$CA$184,$A10,FALSE)/1000000 -> 226631.96
A11: 9 | B11: Mangroves | C11: =VLOOKUP(C$1,reg_bal!$D$1:$CA$184,$A11,FALSE)/1000000 -> 579882.46 | D11: =VLOOKUP(D$1,reg_bal!$D$1:$CA$184,$A11,FALSE)/1000000 -> 561277.44 | E11: =VLOOKUP(E$1,reg_bal!$D$1:$CA$184,$A11,FALSE)/1000000 -> 542681.38 | F11: =VLOOKUP(F$1,reg_bal!$D$1:$CA$184,$A11,FALSE)/1000000 -> 524078.11 | G11: =VLOOKUP(G$1,reg_bal!$D$1:$CA$184,$A11,FALSE)/1000000 -> 525168.15 | H11: =VLOOKUP(H$1,reg_bal!$D$1:$CA$184,$A11,FALSE)/1000000 -> 525464.42 | J11: Mangroves | K11: =VLOOKUP(K$1,reg_bal!$D$1:$CA$184,$A11,FALSE)/1000000 -> 0 | L11: =VLOOKUP(L$1,reg_bal!$D$1:$CA$184,$A11,FALSE)/1000000 -> 0 | M11: =VLOOKUP(M$1,reg_bal!$D$1:$CA$184,$A11,FALSE)/1000000 -> 0 | N11: =VLOOKUP(N$1,reg_bal!$D$1:$CA$184,$A11,FALSE)/1000000 -> 0 | O11: =VLOOKUP(O$1,reg_bal!$D$1:$CA$184,$A11,FALSE)/1000000 -> 0 | P11: =VLOOKUP(P$1,reg_bal!$D$1:$CA$184,$A11,FALSE)/1000000 -> 0 | R11: Mangroves | S11: =VLOOKUP(S$1,reg_bal!$D$1:$CA$184,$A11,FALSE)/1000000 -> 78992.842 | T11: =VLOOKUP(T$1,reg_bal!$D$1:$CA$184,$A11,FALSE)/1000000 -> 78198.413 | U11: =VLOOKUP(U$1,reg_bal!$D$1:$CA$184,$A11,FALSE)/1000000 -> 77399.914 | V11: =VLOOKUP(V$1,reg_bal!$D$1:$CA$184,$A11,FALSE)/1000000 -> 76605.463 | W11: =VLOOKUP(W$1,reg_bal!$D$1:$CA$184,$A11,FALSE)/1000000 -> 76649.622 | X11: =VLOOKUP(X$1,reg_bal!$D$1:$CA$184,$A11,FALSE)/1000000 -> 76812.327 | Z11: Mangroves | AA11: =VLOOKUP(AA$1,reg_bal!$D$1:$CA$184,$A11,FALSE)/1000000 -> 14575.449 | AB11: =VLOOKUP(AB$1,reg_bal!$D$1:$CA$184,$A11,FALSE)/1000000 -> 14373.044 | AC11: =VLOOKUP(AC$1,reg_bal!$D$1:$CA$184,$A11,FALSE)/1000000 -> 14175.175 | AD11: =VLOOKUP(AD$1,reg_bal!$D$1:$CA$184,$A11,FALSE)/1000000 -> 13972.359 | AE11: =VLOOKUP(AE$1,reg_bal!$D$1:$CA$184,$A11,FALSE)/1000000 -> 12651.659 | AF11: =VLOOKUP(AF$1,reg_bal!$D$1:$CA$184,$A11,FALSE)/1000000 -> 13017.237 | AH11: Mangroves | AI11: =VLOOKUP(AI$1,reg_bal!$D$1:$CA$184,$A11,FALSE)/1000000 -> 55086.743 | AJ11: =VLOOKUP(AJ$1,reg_bal!$D$1:$CA$184,$A11,FALSE)/1000000 -> 54436.199 | AK11: =VLOOKUP(AK$1,reg_bal!$D$1:$CA$184,$A11,FALSE)/1000000 -> 53785.883 | AL11: =VLOOKUP(AL$1,reg_bal!$D$1:$CA$184,$A11,FALSE)/1000000 -> 53135.34 | AM11: =VLOOKUP(AM$1,reg_bal!$D$1:$CA$184,$A11,FALSE)/1000000 -> 52117.355 | AN11: =VLOOKUP(AN$1,reg_bal!$D$1:$CA$184,$A11,FALSE)/1000000 -> 52774.053 | AP11: Mangroves | AQ11: =VLOOKUP(AQ$1,reg_bal!$D$1:$CA$184,$A11,FALSE)/1000000 -> 66226.072 | AR11: =VLOOKUP(AR$1,reg_bal!$D$1:$CA$184,$A11,FALSE)/1000000 -> 65782.102 | AS11: =VLOOKUP(AS$1,reg_bal!$D$1:$CA$184,$A11,FALSE)/1000000 -> 65338.227 | AT11: =VLOOKUP(AT$1,reg_bal!$D$1:$CA$184,$A11,FALSE)/1000000 -> 64894.257 | AU11: =VLOOKUP(AU$1,reg_bal!$D$1:$CA$184,$A11,FALSE)/1000000 -> 65042.235 | AV11: =VLOOKUP(AV$1,reg_bal!$D$1:$CA$184,$A11,FALSE)/1000000 -> 64752.412 | AX11: Mangroves | AY11: =VLOOKUP(AY$1,reg_bal!$D$1:$CA$184,$A11,FALSE)/1000000 -> 12535.811 | AZ11: =VLOOKUP(AZ$1,reg_bal!$D$1:$CA$184,$A11,FALSE)/1000000 -> 12451.621 | BA11: =VLOOKUP(BA$1,reg_bal!$D$1:$CA$184,$A11,FALSE)/1000000 -> 12366.957 | BB11: =VLOOKUP(BB$1,reg_bal!$D$1:$CA$184,$A11,FALSE)/1000000 -> 12282.768 | BC11: =VLOOKUP(BC$1,reg_bal!$D$1:$CA$184,$A11,FALSE)/1000000 -> 12454.367 | BD11: =VLOOKUP(BD$1,reg_bal!$D$1:$CA$184,$A11,FALSE)/1000000 -> 12349.255
A12: 13 | B12: Fisheries | C12: =VLOOKUP(C$1,reg_bal!$D$1:$CA$184,$A12,FALSE)/1000000 -> 144435.13 | D12: =VLOOKUP(D$1,reg_bal!$D$1:$CA$184,$A12,FALSE)/1000000 -> 129096.8 | E12: =VLOOKUP(E$1,reg_bal!$D$1:$CA$184,$A12,FALSE)/1000000 -> 120967.97 | F12: =VLOOKUP(F$1,reg_bal!$D$1:$CA$184,$A12,FALSE)/1000000 -> 115386.49 | G12: =VLOOKUP(G$1,reg_bal!$D$1:$CA$184,$A12,FALSE)/1000000 -> 104012.26 | H12: =VLOOKUP(H$1,reg_bal!$D$1:$CA$184,$A12,FALSE)/1000000 -> 100715.78 | J12: Fisheries | K12: =VLOOKUP(K$1,reg_bal!$D$1:$CA$184,$A12,FALSE)/1000000 -> 37828.923 | L12: =VLOOKUP(L$1,reg_bal!$D$1:$CA$184,$A12,FALSE)/1000000 -> 35074.296 | M12: =VLOOKUP(M$1,reg_bal!$D$1:$CA$184,$A12,FALSE)/1000000 -> 33374.812 | N12: =VLOOKUP(N$1,reg_bal!$D$1:$CA$184,$A12,FALSE)/1000000 -> 33249.023 | O12: =VLOOKUP(O$1,reg_bal!$D$1:$CA$184,$A12,FALSE)/1000000 -> 32937.89 | P12: =VLOOKUP(P$1,reg_bal!$D$1:$CA$184,$A12,FALSE)/1000000 -> 32429.481 | R12: Fisheries | S12: =VLOOKUP(S$1,reg_bal!$D$1:$CA$184,$A12,FALSE)/1000000 -> 22460.654 | T12: =VLOOKUP(T$1,reg_bal!$D$1:$CA$184,$A12,FALSE)/1000000 -> 21394.071 | U12: =VLOOKUP(U$1,reg_bal!$D$1:$CA$184,$A12,FALSE)/1000000 -> 18877.246 | V12: =VLOOKUP(V$1,reg_bal!$D$1:$CA$184,$A12,FALSE)/1000000 -> 17804.083 | W12: =VLOOKUP(W$1,reg_bal!$D$1:$CA$184,$A12,FALSE)/1000000 -> 19635.778 | X12: =VLOOKUP(X$1,reg_bal!$D$1:$CA$184,$A12,FALSE)/1000000 -> 22713.293 | Z12: Fisheries | AA12: =VLOOKUP(AA$1,reg_bal!$D$1:$CA$184,$A12,FALSE)/1000000 -> 14421.011 | AB12: =VLOOKUP(AB$1,reg_bal!$D$1:$CA$184,$A12,FALSE)/1000000 -> 13628.192 | AC12: =VLOOKUP(AC$1,reg_bal!$D$1:$CA$184,$A12,FALSE)/1000000 -> 12189.036 | AD12: =VLOOKUP(AD$1,reg_bal!$D$1:$CA$184,$A12,FALSE)/1000000 -> 11402.826 | AE12: =VLOOKUP(AE$1,reg_bal!$D$1:$CA$184,$A12,FALSE)/1000000 -> 10119.056 | AF12: =VLOOKUP(AF$1,reg_bal!$D$1:$CA$184,$A12,FALSE)/1000000 -> 8625.1176 | AH12: Fisheries | AI12: =VLOOKUP(AI$1,reg_bal!$D$1:$CA$184,$A12,FALSE)/1000000 -> 24163.177 | AJ12: =VLOOKUP(AJ$1,reg_bal!$D$1:$CA$184,$A12,FALSE)/1000000 -> 23588.552 | AK12: =VLOOKUP(AK$1,reg_bal!$D$1:$CA$184,$A12,FALSE)/1000000 -> 22778.531 | AL12: =VLOOKUP(AL$1,reg_bal!$D$1:$CA$184,$A12,FALSE)/1000000 -> 22811.153 | AM12: =VLOOKUP(AM$1,reg_bal!$D$1:$CA$184,$A12,FALSE)/1000000 -> 21867.816 | AN12: =VLOOKUP(AN$1,reg_bal!$D$1:$CA$184,$A12,FALSE)/1000000 -> 21777.931 | AP12: Fisheries | AQ12: =VLOOKUP(AQ$1,reg_bal!$D$1:$CA$184,$A12,FALSE)/1000000 -> 23581.881 | AR12: =VLOOKUP(AR$1,reg_bal!$D$1:$CA$184,$A12,FALSE)/1000000 -> 22851.754 | AS12: =VLOOKUP(AS$1,reg_bal!$D$1:$CA$184,$A12,FALSE)/1000000 -> 20414.008 | AT12: =VLOOKUP(AT$1,reg_bal!$D$1:$CA$184,$A12,FALSE)/1000000 -> 18713.032 | AU12: =VLOOKUP(AU$1,reg_bal!$D$1:$CA$184,$A12,FALSE)/1000000 -> 16536.777 | AV12: =VLOOKUP(AV$1,reg_bal!$D$1:$CA$184,$A12,FALSE)/1000000 -> 14915.103 | AX12: Fisheries | AY12: =VLOOKUP(AY$1,reg_bal!$D$1:$CA$184,$A12,FALSE)/1000000 -> 25955.209 | AZ12: =VLOOKUP(AZ$1,reg_bal!$D$1:$CA$184,$A12,FALSE)/1000000 -> 24566.056 | BA12: =VLOOKUP(BA$1,reg_bal!$D$1:$CA$184,$A12,FALSE)/1000000 -> 22280.572 | BB12: =VLOOKUP(BB$1,reg_bal!$D$1:$CA$184,$A12,FALSE)/1000000 -> 21122.628 | BC12: =VLOOKUP(BC$1,reg_bal!$D$1:$CA$184,$A12,FALSE)/1000000 -> 19110.931 | BD12: =VLOOKUP(BD$1,reg_bal!$D$1:$CA$184,$A12,FALSE)/1000000 -> 17243.371
A13: 7 | B13: Agricultural land | C13: =VLOOKUP(C$1,reg_bal!$D$1:$CA$184,$A13,FALSE)/1000000 -> 15572853 | D13: =VLOOKUP(D$1,reg_bal!$D$1:$CA$184,$A13,FALSE)/1000000 -> 15751965 | E13: =VLOOKUP(E$1,reg_bal!$D$1:$CA$184,$A13,FALSE)/1000000 -> 15870663 | F13: =VLOOKUP(F$1,reg_bal!$D$1:$CA$184,$A13,FALSE)/1000000 -> 16084652 | G13: =VLOOKUP(G$1,reg_bal!$D$1:$CA$184,$A13,FALSE)/1000000 -> 16237968 | H13: =VLOOKUP(H$1,reg_bal!$D$1:$CA$184,$A13,FALSE)/1000000 -> 16343608 | J13: Agricultural land | K13: =VLOOKUP(K$1,reg_bal!$D$1:$CA$184,$A13,FALSE)/1000000 -> 2606832.9 | L13: =VLOOKUP(L$1,reg_bal!$D$1:$CA$184,$A13,FALSE)/1000000 -> 2583378.2 | M13: =VLOOKUP(M$1,reg_bal!$D$1:$CA$184,$A13,FALSE)/1000000 -> 2518858.2 | N13: =VLOOKUP(N$1,reg_bal!$D$1:$CA$184,$A13,FALSE)/1000000 -> 2491310 | O13: =VLOOKUP(O$1,reg_bal!$D$1:$CA$184,$A13,FALSE)/1000000 -> 2446972 | P13: =VLOOKUP(P$1,reg_bal!$D$1:$CA$184,$A13,FALSE)/1000000 -> 2424082.7 | R13: Agricultural land | S13: =VLOOKUP(S$1,reg_bal!$D$1:$CA$184,$A13,FALSE)/1000000 -> 1540477.3 | T13: =VLOOKUP(T$1,reg_bal!$D$1:$CA$184,$A13,FALSE)/1000000 -> 1540658.3 | U13: =VLOOKUP(U$1,reg_bal!$D$1:$CA$184,$A13,FALSE)/1000000 -> 1536898.6 | V13: =VLOOKUP(V$1,reg_bal!$D$1:$CA$184,$A13,FALSE)/1000000 -> 1509848.9 | W13: =VLOOKUP(W$1,reg_bal!$D$1:$CA$184,$A13,FALSE)/1000000 -> 1483953.5 | X13: =VLOOKUP(X$1,reg_bal!$D$1:$CA$184,$A13,FALSE)/1000000 -> 1468738.7 | Z13: Agricultural land | AA13: =VLOOKUP(AA$1,reg_bal!$D$1:$CA$184,$A13,FALSE)/1000000 -> 1734563.7 | AB13: =VLOOKUP(AB$1,reg_bal!$D$1:$CA$184,$A13,FALSE)/1000000 -> 1738829.9 | AC13: =VLOOKUP(AC$1,reg_bal!$D$1:$CA$184,$A13,FALSE)/1000000 -> 1652141.2 | AD13: =VLOOKUP(AD$1,reg_bal!$D$1:$CA$184,$A13,FALSE)/1000000 -> 1659281 | AE13: =VLOOKUP(AE$1,reg_bal!$D$1:$CA$184,$A13,FALSE)/1000000 -> 1685694.6 | AF13: =VLOOKUP(AF$1,reg_bal!$D$1:$CA$184,$A13,FALSE)/1000000 -> 1740211.7 | AH13: Agricultural land | AI13: =VLOOKUP(AI$1,reg_bal!$D$1:$CA$184,$A13,FALSE)/1000000 -> 188990.79 | AJ13: =VLOOKUP(AJ$1,reg_bal!$D$1:$CA$184,$A13,FALSE)/1000000 -> 186736.63 | AK13: =VLOOKUP(AK$1,reg_bal!$D$1:$CA$184,$A13,FALSE)/1000000 -> 186301.19 | AL13: =VLOOKUP(AL$1,reg_bal!$D$1:$CA$184,$A13,FALSE)/1000000 -> 182672.52 | AM13: =VLOOKUP(AM$1,reg_bal!$D$1:$CA$184,$A13,FALSE)/1000000 -> 181663.9 | AN13: =VLOOKUP(AN$1,reg_bal!$D$1:$CA$184,$A13,FALSE)/1000000 -> 182002.54 | AP13: Agricultural land | AQ13: =VLOOKUP(AQ$1,reg_bal!$D$1:$CA$184,$A13,FALSE)/1000000 -> 7603256.3 | AR13: =VLOOKUP(AR$1,reg_bal!$D$1:$CA$184,$A13,FALSE)/1000000 -> 7622220.7 | AS13: =VLOOKUP(AS$1,reg_bal!$D$1:$CA$184,$A13,FALSE)/1000000 -> 7576188.7 | AT13: =VLOOKUP(AT$1,reg_bal!$D$1:$CA$184,$A13,FALSE)/1000000 -> 7538764.5 | AU13: =VLOOKUP(AU$1,reg_bal!$D$1:$CA$184,$A13,FALSE)/1000000 -> 7572760.4 | AV13: =VLOOKUP(AV$1,reg_bal!$D$1:$CA$184,$A13,FALSE)/1000000 -> 7585026.6 | AX13: Agricultural land | AY13: =VLOOKUP(AY$1,reg_bal!$D$1:$CA$184,$A13,FALSE)/1000000 -> 3437976.6 | AZ13: =VLOOKUP(AZ$1,reg_bal!$D$1:$CA$184,$A13,FALSE)/1000000 -> 3508670.9 | BA13: =VLOOKUP(BA$1,reg_bal!$D$1:$CA$184,$A13,FALSE)/1000000 -> 3616634.6 | BB13: =VLOOKUP(BB$1,reg_bal!$D$1:$CA$184,$A13,FALSE)/1000000 -> 3734283.1 | BC13: =VLOOKUP(BC$1,reg_bal!$D$1:$CA$184,$A13,FALSE)/1000000 -> 3984418.8 | BD13: =VLOOKUP(BD$1,reg_bal!$D$1:$CA$184,$A13,FALSE)/1000000 -> 4026419.4
A14: 14 | B14: Hydropower energy | C14: =VLOOKUP(C$1,reg_bal!$D$1:$CA$184,$A14,FALSE)/1000000 -> 391236.47 | D14: =VLOOKUP(D$1,reg_bal!$D$1:$CA$184,$A14,FALSE)/1000000 -> 410854.48 | E14: =VLOOKUP(E$1,reg_bal!$D$1:$CA$184,$A14,FALSE)/1000000 -> 498816.97 | F14: =VLOOKUP(F$1,reg_bal!$D$1:$CA$184,$A14,FALSE)/1000000 -> 722906.44 | G14: =VLOOKUP(G$1,reg_bal!$D$1:$CA$184,$A14,FALSE)/1000000 -> 1000826 | H14: =VLOOKUP(H$1,reg_bal!$D$1:$CA$184,$A14,FALSE)/1000000 -> 1134986.7 | J14: Hydropower energy | K14: =VLOOKUP(K$1,reg_bal!$D$1:$CA$184,$A14,FALSE)/1000000 -> 424796.08 | L14: =VLOOKUP(L$1,reg_bal!$D$1:$CA$184,$A14,FALSE)/1000000 -> 461752.35 | M14: =VLOOKUP(M$1,reg_bal!$D$1:$CA$184,$A14,FALSE)/1000000 -> 424562.77 | N14: =VLOOKUP(N$1,reg_bal!$D$1:$CA$184,$A14,FALSE)/1000000 -> 483608.8 | O14: =VLOOKUP(O$1,reg_bal!$D$1:$CA$184,$A14,FALSE)/1000000 -> 476382.99 | P14: =VLOOKUP(P$1,reg_bal!$D$1:$CA$184,$A14,FALSE)/1000000 -> 504882.28 | R14: Hydropower energy | S14: =VLOOKUP(S$1,reg_bal!$D$1:$CA$184,$A14,FALSE)/1000000 -> 628449.48 | T14: =VLOOKUP(T$1,reg_bal!$D$1:$CA$184,$A14,FALSE)/1000000 -> 746861.71 | U14: =VLOOKUP(U$1,reg_bal!$D$1:$CA$184,$A14,FALSE)/1000000 -> 831375.13 | V14: =VLOOKUP(V$1,reg_bal!$D$1:$CA$184,$A14,FALSE)/1000000 -> 955056.29 | W14: =VLOOKUP(W$1,reg_bal!$D$1:$CA$184,$A14,FALSE)/1000000 -> 899429.44 | X14: =VLOOKUP(X$1,reg_bal!$D$1:$CA$184,$A14,FALSE)/1000000 -> 961672.66 | Z14: Hydropower energy | AA14: =VLOOKUP(AA$1,reg_bal!$D$1:$CA$184,$A14,FALSE)/1000000 -> 9013.7643 | AB14: =VLOOKUP(AB$1,reg_bal!$D$1:$CA$184,$A14,FALSE)/1000000 -> 8889.0799 | AC14: =VLOOKUP(AC$1,reg_bal!$D$1:$CA$184,$A14,FALSE)/1000000 -> 16552.445 | AD14: =VLOOKUP(AD$1,reg_bal!$D$1:$CA$184,$A14,FALSE)/1000000 -> 14287.472 | AE14: =VLOOKUP(AE$1,reg_bal!$D$1:$CA$184,$A14,FALSE)/1000000 -> 13720.619 | AF14: =VLOOKUP(AF$1,reg_bal!$D$1:$CA$184,$A14,FALSE)/1000000 -> 18557.274 | AH14: Hydropower energy | AI14: =VLOOKUP(AI$1,reg_bal!$D$1:$CA$184,$A14,FALSE)/1000000 -> 509041.87 | AJ14: =VLOOKUP(AJ$1,reg_bal!$D$1:$CA$184,$A14,FALSE)/1000000 -> 515332.31 | AK14: =VLOOKUP(AK$1,reg_bal!$D$1:$CA$184,$A14,FALSE)/1000000 -> 526230.87 | AL14: =VLOOKUP(AL$1,reg_bal!$D$1:$CA$184,$A14,FALSE)/1000000 -> 510070.59 | AM14: =VLOOKUP(AM$1,reg_bal!$D$1:$CA$184,$A14,FALSE)/1000000 -> 542594.53 | AN14: =VLOOKUP(AN$1,reg_bal!$D$1:$CA$184,$A14,FALSE)/1000000 -> 560620.75 | AP14: Hydropower energy | AQ14: =VLOOKUP(AQ$1,reg_bal!$D$1:$CA$184,$A14,FALSE)/1000000 -> 33798.768 | AR14: =VLOOKUP(AR$1,reg_bal!$D$1:$CA$184,$A14,FALSE)/1000000 -> 32456.803 | AS14: =VLOOKUP(AS$1,reg_bal!$D$1:$CA$184,$A14,FALSE)/1000000 -> 44671.732 | AT14: =VLOOKUP(AT$1,reg_bal!$D$1:$CA$184,$A14,FALSE)/1000000 -> 50293.221 | AU14: =VLOOKUP(AU$1,reg_bal!$D$1:$CA$184,$A14,FALSE)/1000000 -> 55423.687 | AV14: =VLOOKUP(AV$1,reg_bal!$D$1:$CA$184,$A14,FALSE)/1000000 -> 68474.49 | AX14: Hydropower energy | AY14: =VLOOKUP(AY$1,reg_bal!$D$1:$CA$184,$A14,FALSE)/1000000 -> 115954.76 | AZ14: =VLOOKUP(AZ$1,reg_bal!$D$1:$CA$184,$A14,FALSE)/1000000 -> 145303.96 | BA14: =VLOOKUP(BA$1,reg_bal!$D$1:$CA$184,$A14,FALSE)/1000000 -> 188608.05 | BB14: =VLOOKUP(BB$1,reg_bal!$D$1:$CA$184,$A14,FALSE)/1000000 -> 208083.94 | BC14: =VLOOKUP(BC$1,reg_bal!$D$1:$CA$184,$A14,FALSE)/1000000 -> 225848.71 | BD14: =VLOOKUP(BD$1,reg_bal!$D$1:$CA$184,$A14,FALSE)/1000000 -> 274548.51
... A22: 2 | B22: Population (millions) | C22: =VLOOKUP(C$1,reg_bal!$D$1:$CA$184,$A22,FALSE)/1000000 -> 1844.5032 | D22: =VLOOKUP(D$1,reg_bal!$D$1:$CA$184,$A22,FALSE)/1000000 -> 1946.393 | E22: =VLOOKUP(E$1,reg_bal!$D$1:$CA$184,$A22,FALSE)/1000000 -> 2026.8476 | F22: =VLOOKUP(F$1,reg_bal!$D$1:$CA$184,$A22,FALSE)/1000000 -> 2101.3535 | G22: =VLOOKUP(G$1,reg_bal!$D$1:$CA$184,$A22,FALSE)/1000000 -> 2182.1188 | H22: =VLOOKUP(H$1,reg_bal!$D$1:$CA$184,$A22,FALSE)/1000000 -> 2248.4472 | J22: Population (millions) | K22: =VLOOKUP(K$1,reg_bal!$D$1:$CA$184,$A22,FALSE)/1000000 -> 826.11729 | L22: =VLOOKUP(L$1,reg_bal!$D$1:$CA$184,$A22,FALSE)/1000000 -> 830.40956 | M22: =VLOOKUP(M$1,reg_bal!$D$1:$CA$184,$A22,FALSE)/1000000 -> 838.54593 | N22: =VLOOKUP(N$1,reg_bal!$D$1:$CA$184,$A22,FALSE)/1000000 -> 851.77562 | O22: =VLOOKUP(O$1,reg_bal!$D$1:$CA$184,$A22,FALSE)/1000000 -> 866.49134 | P22: =VLOOKUP(P$1,reg_bal!$D$1:$CA$184,$A22,FALSE)/1000000 -> 879.29048 | R22: Population (millions) | S22: =VLOOKUP(S$1,reg_bal!$D$1:$CA$184,$A22,FALSE)/1000000 -> 444.19734 | T22: =VLOOKUP(T$1,reg_bal!$D$1:$CA$184,$A22,FALSE)/1000000 -> 480.46701 | U22: =VLOOKUP(U$1,reg_bal!$D$1:$CA$184,$A22,FALSE)/1000000 -> 513.46715 | V22: =VLOOKUP(V$1,reg_bal!$D$1:$CA$184,$A22,FALSE)/1000000 -> 543.53444 | W22: =VLOOKUP(W$1,reg_bal!$D$1:$CA$184,$A22,FALSE)/1000000 -> 574.37268 | X22: =VLOOKUP(X$1,reg_bal!$D$1:$CA$184,$A22,FALSE)/1000000 -> 605.74934 | Z22: Population (millions) | AA22: =VLOOKUP(AA$1,reg_bal!$D$1:$CA$184,$A22,FALSE)/1000000 -> 223.0524 | AB22: =VLOOKUP(AB$1,reg_bal!$D$1:$CA$184,$A22,FALSE)/1000000 -> 247.24954 | AC22: =VLOOKUP(AC$1,reg_bal!$D$1:$CA$184,$A22,FALSE)/1000000 -> 272.44307 | AD22: =VLOOKUP(AD$1,reg_bal!$D$1:$CA$184,$A22,FALSE)/1000000 -> 304.78156 | AE22: =VLOOKUP(AE$1,reg_bal!$D$1:$CA$184,$A22,FALSE)/1000000 -> 342.77927 | AF22: =VLOOKUP(AF$1,reg_bal!$D$1:$CA$184,$A22,FALSE)/1000000 -> 372.00113 | AH22: Population (millions) | AI22: =VLOOKUP(AI$1,reg_bal!$D$1:$CA$184,$A22,FALSE)/1000000 -> 295.58031 | AJ22: =VLOOKUP(AJ$1,reg_bal!$D$1:$CA$184,$A22,FALSE)/1000000 -> 312.84814 | AK22: =VLOOKUP(AK$1,reg_bal!$D$1:$CA$184,$A22,FALSE)/1000000 -> 327.75933 | AL22: =VLOOKUP(AL$1,reg_bal!$D$1:$CA$184,$A22,FALSE)/1000000 -> 343.33305 | AM22: =VLOOKUP(AM$1,reg_bal!$D$1:$CA$184,$A22,FALSE)/1000000 -> 356.44349 | AN22: =VLOOKUP(AN$1,reg_bal!$D$1:$CA$184,$A22,FALSE)/1000000 -> 369.55557 | AP22: Population (millions) | AQ22: =VLOOKUP(AQ$1,reg_bal!$D$1:$CA$184,$A22,FALSE)/1000000 -> 1255.9313 | AR22: =VLOOKUP(AR$1,reg_bal!$D$1:$CA$184,$A22,FALSE)/1000000 -> 1386.8153 | AS22: =VLOOKUP(AS$1,reg_bal!$D$1:$CA$184,$A22,FALSE)/1000000 -> 1516.1894 | AT22: =VLOOKUP(AT$1,reg_bal!$D$1:$CA$184,$A22,FALSE)/1000000 -> 1631.651 | AU22: =VLOOKUP(AU$1,reg_bal!$D$1:$CA$184,$A22,FALSE)/1000000 -> 1741.0484 | AV22: =VLOOKUP(AV$1,reg_bal!$D$1:$CA$184,$A22,FALSE)/1000000 -> 1842.7869 | AX22: Population (millions) | AY22: =VLOOKUP(AY$1,reg_bal!$D$1:$CA$184,$A22,FALSE)/1000000 -> 573.61047 | AZ22: =VLOOKUP(AZ$1,reg_bal!$D$1:$CA$184,$A22,FALSE)/1000000 -> 652.75934 | BA22: =VLOOKUP(BA$1,reg_bal!$D$1:$CA$184,$A22,FALSE)/1000000 -> 744.57658 | BB22: =VLOOKUP(BB$1,reg_bal!$D$1:$CA$184,$A22,FALSE)/1000000 -> 853.20312 | BC22: =VLOOKUP(BC$1,reg_bal!$D$1:$CA$184,$A22,FALSE)/1000000 -> 978.40803 | BD22: =VLOOKUP(BD$1,reg_bal!$D$1:$CA$184,$A22,FALSE)/1000000 -> 1118.3258
B24: Per Capita, chained 2019 USD | C24: =C$2 -> 1995 | D24: =D$2 -> 2000 | E24: =E$2 -> 2005 | F24: =F$2 -> 2010 | G24: =G$2 -> 2015 | H24: =H$2 -> 2020 | J24: Per Capita, chained 2019 USD | K24: =K$2 -> 1995 | L24: =L$2 -> 2000 | M24: =M$2 -> 2005 | N24: =N$2 -> 2010 | O24: =O$2 -> 2015 | P24: =P$2 -> 2020 | R24: Per Capita, chained 2019 USD | S24: =S$2 -> 1995 | T24: =T$2 -> 2000 | U24: =U$2 -> 2005 | V24: =V$2 -> 2010 | W24: =W$2 -> 2015 | X24: =X$2 -> 2020 | Z24: Per Capita, chained 2019 USD | AA24: =AA$2 -> 1995 | AB24: =AB$2 -> 2000 | AC24: =AC$2 -> 2005 | AD24: =AD$2 -> 2010 | AE24: =AE$2 -> 2015 | AF24: =AF$2 -> 2020 | AH24: Per Capita, chained 2019 USD | AI24: =AI$2 -> 1995 | AJ24: =AJ$2 -> 2000 | AK24: =AK$2 -> 2005 | AL24: =AL$2 -> 2010 | AM24: =AM$2 -> 2015 | AN24: =AN$2 -> 2020 | AP24: Per Capita, chained 2019 USD | AQ24: =AQ$2 -> 1995 | AR24: =AR$2 -> 2000 | AS24: =AS$2 -> 2005 | AT24: =AT$2 -> 2010 | AU24: =AU$2 -> 2015 | AV24: =AV$2 -> 2020 | AX24: Per Capita, chained 2019 USD | AY24: =AY$2 -> 1995 | AZ24: =AZ$2 -> 2000 | BA24: =BA$2 -> 2005 | BB24: =BB$2 -> 2010 | BC24: =BC$2 -> 2015 | BD24: =BD$2 -> 2020
B25: National comprehensive wealth index | C25: =C3/C$22 -> 75734.182 | D25: =D3/D$22 -> 81755.526 | E25: =E3/E$22 -> 87520.619 | F25: =F3/F$22 -> 95841.85 | G25: =G3/G$22 -> 101822.25 | H25: =H3/H$22 -> 110010.53 | J25: National comprehensive wealth index | K25: =K3/K$22 -> 190527.76 | L25: =L3/L$22 -> 209379.43 | M25: =M3/M$22 -> 220461.47 | N25: =N3/N$22 -> 228331.44 | O25: =O3/O$22 -> 240867.98 | P25: =P3/P$22 -> 260603.76 | R25: National comprehensive wealth index | S25: =S3/S$22 -> 44378.456 | T25: =T3/T$22 -> 49912.397 | U25: =U3/U$22 -> 57470.88 | V25: =V3/V$22 -> 61513.297 | W25: =W3/W$22 -> 69600.645 | X25: =X3/X$22 -> 73728.062 | Z25: National comprehensive wealth index | AA25: =AA3/AA$22 -> 36800.426 | AB25: =AB3/AB$22 -> 52552.057 | AC25: =AC3/AC$22 -> 60761.91 | AD25: =AD3/AD$22 -> 71237.293 | AE25: =AE3/AE$22 -> 77146.319 | AF25: =AF3/AF$22 -> 79723.417 | AH25: National comprehensive wealth index | AI25: =AI3/AI$22 -> 602349.28 | AJ25: =AJ3/AJ$22 -> 649084.06 | AK25: =AK3/AK$22 -> 679082.09 | AL25: =AL3/AL$22 -> 681058.05 | AM25: =AM3/AM$22 -> 706426.46 | AN25: =AN3/AN$22 -> 735137.54 | AP25: National comprehensive wealth index | AQ25: =AQ3/AQ$22 -> 11898.657 | AR25: =AR3/AR$22 -> 12989.304 | AS25: =AS3/AS$22 -> 13299.074 | AT25: =AT3/AT$22 -> 13960.677 | AU25: =AU3/AU$22 -> 14604.987 | AV25: =AV3/AV$22 -> 15034.818 | AX25: National comprehensive wealth index | AY25: =AY3/AY$22 -> 14364.162 | AZ25: =AZ3/AZ$22 -> 16078.314 | BA25: =BA3/BA$22 -> 18135.314 | BB25: =BB3/BB$22 -> 17538.621 | BC25: =BC3/BC$22 -> 17068.208 | BD25: =BD3/BD$22 -> 17305.137
B26: Produced capital | C26: =C4/C$22 -> 18086.269 | D26: =D4/D$22 -> 20150.185 | E26: =E4/E$22 -> 22455.925 | F26: =F4/F$22 -> 25112.207 | G26: =G4/G$22 -> 28782.133 | H26: =H4/H$22 -> 34207.856 | J26: Produced capital | K26: =K4/K$22 -> 56181.033 | L26: =L4/L$22 -> 61407.764 | M26: =M4/M$22 -> 66957.131 | N26: =N4/N$22 -> 72965.265 | O26: =O4/O$22 -> 77143.498 | P26: =P4/P$22 -> 82998.953 | R26: Produced capital | S26: =S4/S$22 -> 7461.0828 | T26: =T4/T$22 -> 8554.9854 | U26: =U4/U$22 -> 9280.7068 | V26: =V4/V$22 -> 10792.557 | W26: =W4/W$22 -> 12670.209 | X26: =X4/X$22 -> 13652.433 | Z26: Produced capital | AA26: =AA4/AA$22 -> 4582.3291 | AB26: =AB4/AB$22 -> 5379.1802 | AC26: =AC4/AC$22 -> 6242.9071 | AD26: =AD4/AD$22 -> 8044.6786 | AE26: =AE4/AE$22 -> 9527.6841 | AF26: =AF4/AF$22 -> 10791.772 | AH26: Produced capital | AI26: =AI4/AI$22 -> 164266.91 | AJ26: =AJ4/AJ$22 -> 191844.81 | AK26: =AK4/AK$22 -> 219111.34 | AL26: =AL4/AL$22 -> 238204.25 | AM26: =AM4/AM$22 -> 253700.13 | AN26: =AN4/AN$22 -> 273299.27 | AP26: Produced capital | AQ26: =AQ4/AQ$22 -> 235.87207 | AR26: =AR4/AR$22 -> 309.9879 | AS26: =AS4/AS$22 -> 433.56803 | AT26: =AT4/AT$22 -> 670.8591 | AU26: =AU4/AU$22 -> 997.47164 | AV26: =AV4/AV$22 -> 1415.8183 | AX26: Produced capital | AY26: =AY4/AY$22 -> 2064.2958 | AZ26: =AZ4/AZ$22 -> 2080.1664 | BA26: =BA4/BA$22 -> 2058.7844 | BB26: =BB4/BB$22 -> 2145.1809 | BC26: =BC4/BC$22 -> 2309.7761 | BD26: =BD4/BD$22 -> 2438.5492
B27: Human capital | C27: =C5/C$22 -> 53104.78 | D27: =D5/D$22 -> 55790 | E27: =E5/E$22 -> 57149.686 | F27: =F5/F$22 -> 57847.323 | G27: =G5/G$22 -> 59943.806 | H27: =H5/H$22 -> 61685.416 | J27: Human capital | K27: =K5/K$22 -> 129000.55 | L27: =L5/L$22 -> 138520.66 | M27: =M5/M$22 -> 145352.87 | N27: =N5/N$22 -> 151611 | O27: =O5/O$22 -> 156362.74 | P27: =P5/P$22 -> 166956.11 | R27: Human capital | S27: =S5/S$22 -> 32847.283 | T27: =T5/T$22 -> 35834.474 | U27: =U5/U$22 -> 40737.203 | V27: =V5/V$22 -> 44691.607 | W27: =W5/W$22 -> 49634.547 | X27: =X5/X$22 -> 53089.543 | Z27: Human capital | AA27: =AA5/AA$22 -> 19037.139 | AB27: =AB5/AB$22 -> 21403.879 | AC27: =AC5/AC$22 -> 24307.913 | AD27: =AD5/AD$22 -> 30668.71 | AE27: =AE5/AE$22 -> 33282.12 | AF27: =AF5/AF$22 -> 34063.494 | AH27: Human capital | AI27: =AI5/AI$22 -> 436384.73 | AJ27: =AJ5/AJ$22 -> 459802.49 | AK27: =AK5/AK$22 -> 460701.79 | AL27: =AL5/AL$22 -> 443396.08 | AM27: =AM5/AM$22 -> 463750.16 | AN27: =AN5/AN$22 -> 487711.51 | AP27: Human capital | AQ27: =AQ5/AQ$22 -> 6670.239 | AR27: =AR5/AR$22 -> 7784.6611 | AS27: =AS5/AS$22 -> 8010.8102 | AT27: =AT5/AT$22 -> 8758.6071 | AU27: =AU5/AU$22 -> 9003.1622 | AV27: =AV5/AV$22 -> 9255.8836 | AX27: Human capital | AY27: =AY5/AY$22 -> 6874.3621 | AZ27: =AZ5/AZ$22 -> 7301.1802 | BA27: =BA5/BA$22 -> 7821.4732 | BB27: =BB5/BB$22 -> 7919.5573 | BC27: =BC5/BC$22 -> 8530.7635 | BD27: =BD5/BD$22 -> 8984.7094
B28: Renewable natural capital | C28: =C6/C$22 -> 10495.121 | D28: =D6/D$22 -> 10035.449 | E28: =E6/E$22 -> 9747.1616 | F28: =F6/F$22 -> 9650.8691 | G28: =G6/G$22 -> 9565.2906 | H28: =H6/H$22 -> 9433.2271 | J28: Renewable natural capital | K28: =K6/K$22 -> 5630.1006 | L28: =L6/L$22 -> 5597.575 | M28: =M6/M$22 -> 5488.8334 | N28: =N6/N$22 -> 5483.8161 | O28: =O6/O$22 -> 5340.6098 | P28: =P6/P$22 -> 5255.9551 | R28: Renewable natural capital | S28: =S6/S$22 -> 8560.2248 | T28: =T6/T$22 -> 8254.8114 | U28: =U6/U$22 -> 7765.8513 | V28: =V6/V$22 -> 7528.347 | W28: =W6/W$22 -> 6974.9291 | X28: =X6/X$22 -> 6659.3814 | Z28: Renewable natural capital | AA28: =AA6/AA$22 -> 8380.0191 | AB28: =AB6/AB$22 -> 7558.2651 | AC28: =AC6/AC$22 -> 6633.2468 | AD28: =AD6/AD$22 -> 5938.9993 | AE28: =AE6/AE$22 -> 5343.9528 | AF28: =AF6/AF$22 -> 5079.7999 | AH28: Renewable natural capital | AI28: =AI6/AI$22 -> 7703.6717 | AJ28: =AJ6/AJ$22 -> 7345.2826 | AK28: =AK6/AK$22 -> 7033.9185 | AL28: =AL6/AL$22 -> 6680.6358 | AM28: =AM6/AM$22 -> 6543.8198 | AN28: =AN6/AN$22 -> 6346.4634 | AP28: Renewable natural capital | AQ28: =AQ6/AQ$22 -> 6276.0465 | AR28: =AR6/AR$22 -> 5707.2404 | AS28: =AS6/AS$22 -> 5212.5003 | AT28: =AT6/AT$22 -> 4829.8885 | AU28: =AU6/AU$22 -> 4553.1636 | AV28: =AV6/AV$22 -> 4314.5002 | AX28: Renewable natural capital | AY28: =AY6/AY$22 -> 8548.0072 | AZ28: =AZ6/AZ$22 -> 7617.0095 | BA28: =BA6/BA$22 -> 6841.6175 | BB28: =BB6/BB$22 -> 6109.0039 | BC28: =BC6/BC$22 -> 5543.3832 | BD28: =BD6/BD$22 -> 4966.0198
B29: Forests, timber | C29: =C7/C$22 -> 457.04359 | D29: =D7/D$22 -> 427.13076 | E29: =E7/E$22 -> 415.24507 | F29: =F7/F$22 -> 405.41136 | G29: =G7/G$22 -> 400.07606 | H29: =H7/H$22 -> 394.65869 | J29: Forests, timber | K29: =K7/K$22 -> 504.61446 | L29: =L7/L$22 -> 500.04291 | M29: =M7/M$22 -> 497.18585 | N29: =N7/N$22 -> 498.98795 | O29: =O7/O$22 -> 493.42636 | P29: =P7/P$22 -> 474.1821 | R29: Forests, timber | S29: =S7/S$22 -> 1236.9035 | T29: =T7/T$22 -> 1116.9979 | U29: =U7/U$22 -> 1017.8138 | V29: =V7/V$22 -> 935.60342 | W29: =W7/W$22 -> 877.38222 | X29: =X7/X$22 -> 824.09249 | Z29: Forests, timber | AA29: =AA7/AA$22 -> 22.23229 | AB29: =AB7/AB$22 -> 20.365426 | AC29: =AC7/AC$22 -> 19.611889 | AD29: =AD7/AD$22 -> 18.540818 | AE29: =AE7/AE$22 -> 16.468823 | AF29: =AF7/AF$22 -> 15.405936 | AH29: Forests, timber | AI29: =AI7/AI$22 -> 770.77018 | AJ29: =AJ7/AJ$22 -> 729.26916 | AK29: =AK7/AK$22 -> 701.18605 | AL29: =AL7/AL$22 -> 674.2434 | AM29: =AM7/AM$22 -> 651.92907 | AN29: =AN7/AN$22 -> 621.93369 | AP29: Forests, timber | AQ29: =AQ7/AQ$22 -> 42.206199 | AR29: =AR7/AR$22 -> 38.999126 | AS29: =AS7/AS$22 -> 36.03108 | AT29: =AT7/AT$22 -> 33.815625 | AU29: =AU7/AU$22 -> 32.154121 | AV29: =AV7/AV$22 -> 30.792886 | AX29: Forests, timber | AY29: =AY7/AY$22 -> 1388.7494 | AZ29: =AZ7/AZ$22 -> 1193.1408 | BA29: =BA7/BA$22 -> 1021.9836 | BB29: =BB7/BB$22 -> 870.7329 | BC29: =BC7/BC$22 -> 707.48312 | BD29: =BD7/BD$22 -> 656.22631
B30: Forests, recreation, hunting, and fishing services (es1) | C30: =C8/C$22 -> 438.14582 | D30: =D8/D$22 -> 432.53001 | E30: =E8/E$22 -> 435.75169 | F30: =F8/F$22 -> 439.96935 | G30: =G8/G$22 -> 439.23555 | H30: =H8/H$22 -> 441.00803 | J30: Forests, recreation, hunting, and fishing services (es1) | K30: =K8/K$22 -> 523.45309 | L30: =L8/L$22 -> 535.21698 | M30: =M8/M$22 -> 541.5203 | N30: =N8/N$22 -> 547.24899 | O30: =O8/O$22 -> 543.97709 | P30: =P8/P$22 -> 541.00231 | R30: Forests, recreation, hunting, and fishing services (es1) | S30: =S8/S$22 -> 162.66027 | T30: =T8/T$22 -> 148.98547 | U30: =U8/U$22 -> 137.33106 | V30: =V8/V$22 -> 127.76996 | W30: =W8/W$22 -> 119.98008 | X30: =X8/X$22 -> 112.58954 | Z30: Forests, recreation, hunting, and fishing services (es1) | AA30: =AA8/AA$22 -> 268.94151 | AB30: =AB8/AB$22 -> 247.74804 | AC30: =AC8/AC$22 -> 235.95919 | AD30: =AD8/AD$22 -> 220.8641 | AE30: =AE8/AE$22 -> 197.85116 | AF30: =AF8/AF$22 -> 180.51033 | AH30: Forests, recreation, hunting, and fishing services (es1) | AI30: =AI8/AI$22 -> 1070.235 | AJ30: =AJ8/AJ$22 -> 1011.8372 | AK30: =AK8/AK$22 -> 969.9947 | AL30: =AL8/AL$22 -> 929.99568 | AM30: =AM8/AM$22 -> 897.74117 | AN30: =AN8/AN$22 -> 865.21715 | AP30: Forests, recreation, hunting, and fishing services (es1) | AQ30: =AQ8/AQ$22 -> 21.281113 | AR30: =AR8/AR$22 -> 19.575856 | AS30: =AS8/AS$22 -> 18.04058 | AT30: =AT8/AT$22 -> 16.901006 | AU30: =AU8/AU$22 -> 16.091829 | AV30: =AV8/AV$22 -> 15.401825 | AX30: Forests, recreation, hunting, and fishing services (es1) | AY30: =AY8/AY$22 -> 265.8461 | AZ30: =AZ8/AZ$22 -> 228.80621 | BA30: =BA8/BA$22 -> 196.51929 | BB30: =BB8/BB$22 -> 167.94587 | BC30: =BC8/BC$22 -> 153.27133 | BD30: =BD8/BD$22 -> 129.89098
B31: Forests, non-wood forest products (es2) | C31: =C9/C$22 -> 93.894274 | D31: =D9/D$22 -> 90.191555 | E31: =E9/E$22 -> 88.970035 | F31: =F9/F$22 -> 88.090455 | G31: =G9/G$22 -> 86.439277 | H31: =H9/H$22 -> 85.438579 | J31: Forests, non-wood forest products (es2) | K31: =K9/K$22 -> 152.7193 | L31: =L9/L$22 -> 153.46717 | M31: =M9/M$22 -> 153.51547 | N31: =N9/N$22 -> 153.05287 | O31: =O9/O$22 -> 151.50878 | P31: =P9/P$22 -> 150.19203 | R31: Forests, non-wood forest products (es2) | S31: =S9/S$22 -> 371.34011 | T31: =T9/T$22 -> 334.53307 | U31: =U9/U$22 -> 304.34945 | V31: =V9/V$22 -> 279.31033 | W31: =W9/W$22 -> 260.37492 | X31: =X9/X$22 -> 243.37764 | Z31: Forests, non-wood forest products (es2) | AA31: =AA9/AA$22 -> 16.203562 | AB31: =AB9/AB$22 -> 14.811531 | AC31: =AC9/AC$22 -> 13.939999 | AD31: =AD9/AD$22 -> 12.906189 | AE31: =AE9/AE$22 -> 11.525991 | AF31: =AF9/AF$22 -> 10.597233 | AH31: Forests, non-wood forest products (es2) | AI31: =AI9/AI$22 -> 280.64454 | AJ31: =AJ9/AJ$22 -> 265.47338 | AK31: =AK9/AK$22 -> 255.00333 | AL31: =AL9/AL$22 -> 244.97086 | AM31: =AM9/AM$22 -> 236.732 | AN31: =AN9/AN$22 -> 228.13447 | AP31: Forests, non-wood forest products (es2) | AQ31: =AQ9/AQ$22 -> 22.466965 | AR31: =AR9/AR$22 -> 20.743796 | AS31: =AS9/AS$22 -> 19.090606 | AT31: =AT9/AT$22 -> 17.887287 | AU31: =AU9/AU$22 -> 16.989549 | AV31: =AV9/AV$22 -> 16.243894 | AX31: Forests, non-wood forest products (es2) | AY31: =AY9/AY$22 -> 225.3554 | AZ31: =AZ9/AZ$22 -> 192.75885 | BA31: =BA9/BA$22 -> 164.57263 | BB31: =BB9/BB$22 -> 139.76591 | BC31: =BC9/BC$22 -> 123.99303 | BD31: =BD9/BD$22 -> 105.15751
B32: Forests, water retention services (es3) | C32: =C10/C$22 -> 513.30923 | D32: =D10/D$22 -> 491.32361 | E32: =E10/E$22 -> 481.15222 | F32: =F10/F$22 -> 473.09298 | G32: =G10/G$22 -> 465.94219 | H32: =H10/H$22 -> 459.83804 | J32: Forests, water retention services (es3) | K32: =K10/K$22 -> 728.38887 | L32: =L10/L$22 -> 734.62152 | M32: =M10/M$22 -> 736.06691 | N32: =N10/N$22 -> 736.15184 | O32: =O10/O$22 -> 728.78228 | P32: =P10/P$22 -> 722.28868 | R32: Forests, water retention services (es3) | S32: =S10/S$22 -> 1987.6125 | T32: =T10/T$22 -> 1789.1777 | U32: =U10/U$22 -> 1625.1005 | V32: =V10/V$22 -> 1488.8303 | W32: =W10/W$22 -> 1388.3482 | X32: =X10/X$22 -> 1298.7619 | Z32: Forests, water retention services (es3) | AA32: =AA10/AA$22 -> 129.39913 | AB32: =AB10/AB$22 -> 118.12274 | AC32: =AC10/AC$22 -> 111.87137 | AD32: =AD10/AD$22 -> 104.17745 | AE32: =AE10/AE$22 -> 92.832546 | AF32: =AF10/AF$22 -> 85.832443 | AH32: Forests, water retention services (es3) | AI32: =AI10/AI$22 -> 2973.6383 | AJ32: =AJ10/AJ$22 -> 2813.2192 | AK32: =AK10/AK$22 -> 2703.4485 | AL32: =AL10/AL$22 -> 2598.2075 | AM32: =AM10/AM$22 -> 2511.42 | AN32: =AN10/AN$22 -> 2420.1628 | AP32: Forests, water retention services (es3) | AQ32: =AQ10/AQ$22 -> 75.955809 | AR32: =AR10/AR$22 -> 70.376988 | AS32: =AS10/AS$22 -> 64.86568 | AT32: =AT10/AT$22 -> 60.898074 | AU32: =AU10/AU$22 -> 57.907113 | AV32: =AV10/AV$22 -> 55.458496 | AX32: Forests, water retention services (es3) | AY32: =AY10/AY$22 -> 457.52623 | AZ32: =AZ10/AZ$22 -> 384.99389 | BA32: =BA10/BA$22 -> 326.30202 | BB32: =BB10/BB$22 -> 274.97007 | BC32: =BC10/BC$22 -> 240.01259 | BD32: =BD10/BD$22 -> 202.65289
B33: Mangroves | C33: =C11/C$22 -> 314.38409 | D33: =D11/D$22 -> 288.368 | E33: =E11/E$22 -> 267.74652 | F33: =F11/F$22 -> 249.40026 | G33: =G11/G$22 -> 240.6689 | H33: =H11/H$22 -> 233.70103 | J33: Mangroves | K33: =K11/K$22 -> 0 | L33: =L11/L$22 -> 0 | M33: =M11/M$22 -> 0 | N33: =N11/N$22 -> 0 | O33: =O11/O$22 -> 0 | P33: =P11/P$22 -> 0 | R33: Mangroves | S33: =S11/S$22 -> 177.83277 | T33: =T11/T$22 -> 162.75501 | U33: =U11/U$22 -> 150.73976 | V33: =V11/V$22 -> 140.93948 | W33: =W11/W$22 -> 133.44928 | X33: =X11/X$22 -> 126.80547 | Z33: Mangroves | AA33: =AA11/AA$22 -> 65.345402 | AB33: =AB11/AB$22 -> 58.131732 | AC33: =AC11/AC$22 -> 52.029861 | AD33: =AD11/AD$22 -> 45.843848 | AE33: =AE11/AE$22 -> 36.909056 | AF33: =AF11/AF$22 -> 34.992467 | AH33: Mangroves | AI33: =AI11/AI$22 -> 186.36811 | AJ33: =AJ11/AJ$22 -> 174.00199 | AK33: =AK11/AK$22 -> 164.10176 | AL33: =AL11/AL$22 -> 154.76326 | AM33: =AM11/AM$22 -> 146.21491 | AN33: =AN11/AN$22 -> 142.80411 | AP33: Mangroves | AQ33: =AQ11/AQ$22 -> 52.730649 | AR33: =AR11/AR$22 -> 47.433931 | AS33: =AS11/AS$22 -> 43.093711 | AT33: =AT11/AT$22 -> 39.772144 | AU33: =AU11/AU$22 -> 37.358085 | AV33: =AV11/AV$22 -> 35.138308 | AX33: Mangroves | AY33: =AY11/AY$22 -> 21.854222 | AZ33: =AZ11/AZ$22 -> 19.075362 | BA33: =BA11/BA$22 -> 16.609383 | BB33: =BB11/BB$22 -> 14.396066 | BC33: =BC11/BC$22 -> 12.729216 | BD33: =BD11/BD$22 -> 11.042627
B34: Fisheries | C34: =C12/C$22 -> 78.305712 | D34: =D12/D$22 -> 66.326172 | E34: =E12/E$22 -> 59.682816 | F34: =F12/F$22 -> 54.910555 | G34: =G12/G$22 -> 47.665717 | H34: =H12/H$22 -> 44.793483 | J34: Fisheries | K34: =K12/K$22 -> 45.791225 | L34: =L12/L$22 -> 42.237346 | M34: =M12/M$22 -> 39.800816 | N34: =N12/N$22 -> 39.034955 | O34: =O12/O$22 -> 38.012948 | P34: =P12/P$22 -> 36.881419 | R34: Fisheries | S34: =S12/S$22 -> 50.564584 | T34: =T12/T$22 -> 44.527658 | U34: =U12/U$22 -> 36.764272 | V34: =V12/V$22 -> 32.756127 | W34: =W12/W$22 -> 34.186477 | X34: =X12/X$22 -> 37.496191 | Z34: Fisheries | AA34: =AA12/AA$22 -> 64.653018 | AB34: =AB12/AB$22 -> 55.11918 | AC34: =AC12/AC$22 -> 44.739755 | AD34: =AD12/AD$22 -> 37.41311 | AE34: =AE12/AE$22 -> 29.52062 | AF34: =AF12/AF$22 -> 23.185729 | AH34: Fisheries | AI34: =AI12/AI$22 -> 81.748264 | AJ34: =AJ12/AJ$22 -> 75.399369 | AK34: =AK12/AK$22 -> 69.497736 | AL34: =AL12/AL$22 -> 66.440306 | AM34: =AM12/AM$22 -> 61.350021 | AN34: =AN12/AN$22 -> 58.930059 | AP34: Fisheries | AQ34: =AQ12/AQ$22 -> 18.77641 | AR34: =AR12/AR$22 -> 16.477864 | AS34: =AS12/AS$22 -> 13.464022 | AT34: =AT12/AT$22 -> 11.468772 | AU34: =AU12/AU$22 -> 9.4981721 | AV34: =AV12/AV$22 -> 8.0937755 | AX34: Fisheries | AY34: =AY12/AY$22 -> 45.248842 | AZ34: =AZ12/AZ$22 -> 37.634169 | BA34: =BA12/BA$22 -> 29.923815 | BB34: =BB12/BB$22 -> 24.756857 | BC34: =BC12/BC$22 -> 19.53268 | BD34: =BD12/BD$22 -> 15.418916
B35: Agricultural land | C35: =C13/C$22 -> 8442.8443 | D35: =D13/D$22 -> 8092.9007 | E35: =E13/E$22 -> 7830.2204 | F35: =F13/F$22 -> 7654.4247 | G35: =G13/G$22 -> 7441.3766 | H35: =H13/H$22 -> 7268.842 | J35: Agricultural land | K35: =K13/K$22 -> 3155.524 | L35: =L13/L$22 -> 3110.9687 | M35: =M13/M$22 -> 3003.8405 | N35: =N13/N$22 -> 2924.843 | O35: =O13/O$22 -> 2824.0005 | P35: =P13/P$22 -> 2756.8622 | R35: Agricultural land | S35: =S13/S$22 -> 3468.002 | T35: =T13/T$22 -> 3206.585 | U35: =U13/U$22 -> 2993.1781 | V35: =V13/V$22 -> 2777.8349 | W35: =W13/W$22 -> 2583.6075 | X35: =X13/X$22 -> 2424.6642 | Z35: Agricultural land | AA35: =AA13/AA$22 -> 7776.4849 | AB35: =AB13/AB$22 -> 7032.6921 | AC35: =AC13/AC$22 -> 6064.1702 | AD35: =AD13/AD$22 -> 5444.1647 | AE35: =AE13/AE$22 -> 4917.7263 | AF35: =AF13/AF$22 -> 4677.9741 | AH35: Agricultural land | AI35: =AI13/AI$22 -> 639.38897 | AJ35: =AJ13/AJ$22 -> 596.89226 | AK35: =AK13/AK$22 -> 568.40851 | AL35: =AL13/AL$22 -> 532.05633 | AM35: =AM13/AM$22 -> 509.65693 | AN35: =AN13/AN$22 -> 492.49031 | AP35: Agricultural land | AQ35: =AQ13/AQ$22 -> 6053.8792 | AR35: =AR13/AR$22 -> 5496.2046 | AS35: =AS13/AS$22 -> 4996.8617 | AT35: =AT13/AT$22 -> 4620.3292 | AU35: =AU13/AU$22 -> 4349.5404 | AV35: =AV13/AV$22 -> 4116.0629 | AX35: Agricultural land | AY35: =AY13/AY$22 -> 5993.5736 | AZ35: =AZ13/AZ$22 -> 5375.137 | BA35: =BA13/BA$22 -> 4857.3037 | BB35: =BB13/BB$22 -> 4376.7809 | BC35: =BC13/BC$22 -> 4072.3488 | BD35: =BD13/BD$22 -> 3600.3992
B36: Hydropower energy | C36: =C14/C$22 -> 212.10941 | D36: =D14/D$22 -> 211.08506 | E36: =E14/E$22 -> 246.10483 | F36: =F14/F$22 -> 344.01943 | G36: =G14/G$22 -> 458.64871 | H36: =H14/H$22 -> 504.78692 | J36: Hydropower energy | K36: =K14/K$22 -> 514.20795 | L36: =L14/L$22 -> 556.05375 | M36: =M14/M$22 -> 506.30831 | N36: =N14/N$22 -> 567.76549 | O36: =O14/O$22 -> 549.7839 | P36: =P14/P$22 -> 574.19282 | R36: Hydropower energy | S36: =S14/S$22 -> 1414.7979 | T36: =T14/T$22 -> 1554.4495 | U36: =U14/U$22 -> 1619.1399 | V36: =V14/V$22 -> 1757.1219 | W36: =W14/W$22 -> 1565.9335 | X36: =X14/X$22 -> 1587.5753 | Z36: Hydropower energy | AA36: =AA14/AA$22 -> 40.410971 | AB36: =AB14/AB$22 -> 35.951857 | AC36: =AC14/AC$22 -> 60.755611 | AD36: =AD14/AD$22 -> 46.877744 | AE36: =AE14/AE$22 -> 40.027562 | AF36: =AF14/AF$22 -> 49.884993 | AH36: Hydropower energy | AI36: =AI14/AI$22 -> 1722.1779 | AJ36: =AJ14/AJ$22 -> 1647.2283 | AK36: =AK14/AK$22 -> 1605.5405 | AL36: =AL14/AL$22 -> 1485.6438 | AM36: =AM14/AM$22 -> 1522.2456 | AN36: =AN14/AN$22 -> 1517.0134 | AP36: Hydropower energy | AQ36: =AQ14/AQ$22 -> 26.911319 | AR36: =AR14/AR$22 -> 23.403839 | AS36: =AS14/AS$22 -> 29.463161 | AT36: =AT14/AT$22 -> 30.823517 | AU36: =AU14/AU$22 -> 31.833513 | AV36: =AV14/AV$22 -> 37.158116 | AX36: Hydropower energy | AY36: =AY14/AY$22 -> 202.14895 | AZ36: =AZ14/AZ$22 -> 222.59959 | BA36: =BA14/BA$22 -> 253.30914 | BB36: =BB14/BB$22 -> 243.88559 | BC36: =BC14/BC$22 -> 230.83285 | BD36: =BD14/BD$22 -> 245.49957
... B43: Foreign liabilities | C43: =C21/C$22 -> 2945.8964 | D43: =D21/D$22 -> 2896.3794 | E43: =E21/E$22 -> 4285.9093 | F43: =F21/F$22 -> 7123.692 | G43: =G21/G$22 -> 8400.1024 | H43: =H21/H$22 -> 11192.47 | J43: Foreign liabilities | K43: =K21/K$22 -> 24903.639 | L43: =L21/L$22 -> 35396.654 | M43: =M21/M$22 -> 67486.246 | N43: =N21/N$22 -> 98692.398 | O43: =O21/O$22 -> 94589.095 | P43: =P21/P$22 -> 112626.51 | R43: Foreign liabilities | S43: =S21/S$22 -> 10277.825 | T43: =T21/T$22 -> 9169.1302 | U43: =U21/U$22 -> 6817.2438 | V43: =V21/V$22 -> 10024.074 | W43: =W21/W$22 -> 8265.2443 | X43: =X21/X$22 -> 7599.8563 | Z43: Foreign liabilities | AA43: =AA21/AA$22 -> 10699.136 | AB43: =AB21/AB$22 -> 7747.0962 | AC43: =AC21/AC$22 -> 7323.8328 | AD43: =AD21/AD$22 -> 8893.5185 | AE43: =AE21/AE$22 -> 7451.2672 | AF43: =AF21/AF$22 -> 8911.3742 | AH43: Foreign liabilities | AI43: =AI21/AI$22 -> 28476.455 | AJ43: =AJ21/AJ$22 -> 47809.836 | AK43: =AK21/AK$22 -> 66838.718 | AL43: =AL21/AL$22 -> 91583.095 | AM43: =AM21/AM$22 -> 101518.74 | AN43: =AN21/AN$22 -> 136270.23 | AP43: Foreign liabilities | AQ43: =AQ21/AQ$22 -> 691.59671 | AR43: =AR21/AR$22 -> 521.81466 | AS43: =AS21/AS$22 -> 685.0846 | AT43: =AT21/AT$22 -> 1028.7254 | AU43: =AU21/AU$22 -> 900.40461 | AV43: =AV21/AV$22 -> 993.73583 | AX43: Foreign liabilities | AY43: =AY21/AY$22 -> 3542.0368 | AZ43: =AZ21/AZ$22 -> 2081.5737 | BA43: =BA21/BA$22 -> 1944.0318 | BB43: =BB21/BB$22 -> 2397.5952 | BC43: =BC21/BC$22 -> 2352.2896 | BD43: =BD21/BD$22 -> 1619.6644
B49: Nominal Wealth, current USD, Millions | C49: 1995 | D49: 2000 | E49: 2005 | F49: 2010 | G49: 2015 | H49: 2020 | J49: Nominal Wealth, current USD, Millions | K49: 1995 | L49: 2000 | M49: 2005 | N49: 2010 | O49: 2015 | P49: 2020 | R49: Nominal Wealth, current USD, Millions | S49: 1995 | T49: 2000 | U49: 2005 | V49: 2010 | W49: 2015 | X49: 2020 | Z49: Nominal Wealth, current USD, Millions | AA49: 1995 | AB49: 2000 | AC49: 2005 | AD49: 2010 | AE49: 2015 | AF49: 2020 | AH49: Nominal Wealth, current USD, Millions | AI49: 1995 | AJ49: 2000 | AK49: 2005 | AL49: 2010 | AM49: 2015 | AN49: 2020 | AP49: Nominal Wealth, current USD, Millions | AQ49: 1995 | AR49: 2000 | AS49: 2005 | AT49: 2010 | AU49: 2015 | AV49: 2020 | AX49: Nominal Wealth, current USD, Millions | AY49: 1995 | AZ49: 2000 | BA49: 2005 | BB49: 2010 | BC49: 2015 | BD49: 2020
A50: 38 | B50: Produced capital | C50: =VLOOKUP(C$1,reg_bal!$D$1:$CA$184,$A50,FALSE)/1000000 -> 30654518 | D50: =VLOOKUP(D$1,reg_bal!$D$1:$CA$184,$A50,FALSE)/1000000 -> 33524467 | E50: =VLOOKUP(E$1,reg_bal!$D$1:$CA$184,$A50,FALSE)/1000000 -> 38002444 | F50: =VLOOKUP(F$1,reg_bal!$D$1:$CA$184,$A50,FALSE)/1000000 -> 51929991 | G50: =VLOOKUP(G$1,reg_bal!$D$1:$CA$184,$A50,FALSE)/1000000 -> 56044356 | H50: =VLOOKUP(H$1,reg_bal!$D$1:$CA$184,$A50,FALSE)/1000000 -> 78802228 | J50: Produced capital | K50: =VLOOKUP(K$1,reg_bal!$D$1:$CA$184,$A50,FALSE)/1000000 -> 47476718 | L50: =VLOOKUP(L$1,reg_bal!$D$1:$CA$184,$A50,FALSE)/1000000 -> 46297978 | M50: =VLOOKUP(M$1,reg_bal!$D$1:$CA$184,$A50,FALSE)/1000000 -> 77751923 | N50: =VLOOKUP(N$1,reg_bal!$D$1:$CA$184,$A50,FALSE)/1000000 -> 76568551 | O50: =VLOOKUP(O$1,reg_bal!$D$1:$CA$184,$A50,FALSE)/1000000 -> 63698931 | P50: =VLOOKUP(P$1,reg_bal!$D$1:$CA$184,$A50,FALSE)/1000000 -> 74802268 | R50: Produced capital | S50: =VLOOKUP(S$1,reg_bal!$D$1:$CA$184,$A50,FALSE)/1000000 -> 4180508.8 | T50: =VLOOKUP(T$1,reg_bal!$D$1:$CA$184,$A50,FALSE)/1000000 -> 4868143.1 | U50: =VLOOKUP(U$1,reg_bal!$D$1:$CA$184,$A50,FALSE)/1000000 -> 5919511.3 | V50: =VLOOKUP(V$1,reg_bal!$D$1:$CA$184,$A50,FALSE)/1000000 -> 7051482.5 | W50: =VLOOKUP(W$1,reg_bal!$D$1:$CA$184,$A50,FALSE)/1000000 -> 7522344.5 | X50: =VLOOKUP(X$1,reg_bal!$D$1:$CA$184,$A50,FALSE)/1000000 -> 8461091.9 | Z50: Produced capital | AA50: =VLOOKUP(AA$1,reg_bal!$D$1:$CA$184,$A50,FALSE)/1000000 -> 1232033.6 | AB50: =VLOOKUP(AB$1,reg_bal!$D$1:$CA$184,$A50,FALSE)/1000000 -> 1273615.5 | AC50: =VLOOKUP(AC$1,reg_bal!$D$1:$CA$184,$A50,FALSE)/1000000 -> 1664084.7 | AD50: =VLOOKUP(AD$1,reg_bal!$D$1:$CA$184,$A50,FALSE)/1000000 -> 2567601 | AE50: =VLOOKUP(AE$1,reg_bal!$D$1:$CA$184,$A50,FALSE)/1000000 -> 3067692.3 | AF50: =VLOOKUP(AF$1,reg_bal!$D$1:$CA$184,$A50,FALSE)/1000000 -> 4125711.9 | AH50: Produced capital | AI50: =VLOOKUP(AI$1,reg_bal!$D$1:$CA$184,$A50,FALSE)/1000000 -> 29719568 | AJ50: =VLOOKUP(AJ$1,reg_bal!$D$1:$CA$184,$A50,FALSE)/1000000 -> 39437603 | AK50: =VLOOKUP(AK$1,reg_bal!$D$1:$CA$184,$A50,FALSE)/1000000 -> 57073157 | AL50: =VLOOKUP(AL$1,reg_bal!$D$1:$CA$184,$A50,FALSE)/1000000 -> 69006556 | AM50: =VLOOKUP(AM$1,reg_bal!$D$1:$CA$184,$A50,FALSE)/1000000 -> 82508833 | AN50: =VLOOKUP(AN$1,reg_bal!$D$1:$CA$184,$A50,FALSE)/1000000 -> 1.0313925e+08 | AP50: Produced capital | AQ50: =VLOOKUP(AQ$1,reg_bal!$D$1:$CA$184,$A50,FALSE)/1000000 -> 621530 | AR50: =VLOOKUP(AR$1,reg_bal!$D$1:$CA$184,$A50,FALSE)/1000000 -> 663674.97 | AS50: =VLOOKUP(AS$1,reg_bal!$D$1:$CA$184,$A50,FALSE)/1000000 -> 934241.35 | AT50: =VLOOKUP(AT$1,reg_bal!$D$1:$CA$184,$A50,FALSE)/1000000 -> 1325296.6 | AU50: =VLOOKUP(AU$1,reg_bal!$D$1:$CA$184,$A50,FALSE)/1000000 -> 1801533.6 | AV50: =VLOOKUP(AV$1,reg_bal!$D$1:$CA$184,$A50,FALSE)/1000000 -> 2633217.8 | AX50: Produced capital | AY50: =VLOOKUP(AY$1,reg_bal!$D$1:$CA$184,$A50,FALSE)/1000000 -> 1720575.4 | AZ50: =VLOOKUP(AZ$1,reg_bal!$D$1:$CA$184,$A50,FALSE)/1000000 -> 1381762.5 | BA50: =VLOOKUP(BA$1,reg_bal!$D$1:$CA$184,$A50,FALSE)/1000000 -> 1461445.3 | BB50: =VLOOKUP(BB$1,reg_bal!$D$1:$CA$184,$A50,FALSE)/1000000 -> 1398536.1 | BC50: =VLOOKUP(BC$1,reg_bal!$D$1:$CA$184,$A50,FALSE)/1000000 -> 1809173.4 | BD50: =VLOOKUP(BD$1,reg_bal!$D$1:$CA$184,$A50,FALSE)/1000000 -> 2776132.4
A51: 72 | B51: Human capital | C51: =VLOOKUP(C$1,reg_bal!$D$1:$CA$184,$A51,FALSE)/1000000 -> 54418921 | D51: =VLOOKUP(D$1,reg_bal!$D$1:$CA$184,$A51,FALSE)/1000000 -> 51039700 | E51: =VLOOKUP(E$1,reg_bal!$D$1:$CA$184,$A51,FALSE)/1000000 -> 58710487 | F51: =VLOOKUP(F$1,reg_bal!$D$1:$CA$184,$A51,FALSE)/1000000 -> 91669708 | G51: =VLOOKUP(G$1,reg_bal!$D$1:$CA$184,$A51,FALSE)/1000000 -> 1.1509596e+08 | H51: =VLOOKUP(H$1,reg_bal!$D$1:$CA$184,$A51,FALSE)/1000000 -> 1.3678323e+08 | J51: Human capital | K51: =VLOOKUP(K$1,reg_bal!$D$1:$CA$184,$A51,FALSE)/1000000 -> 72081291 | L51: =VLOOKUP(L$1,reg_bal!$D$1:$CA$184,$A51,FALSE)/1000000 -> 64708296 | M51: =VLOOKUP(M$1,reg_bal!$D$1:$CA$184,$A51,FALSE)/1000000 -> 1.0165373e+08 | N51: =VLOOKUP(N$1,reg_bal!$D$1:$CA$184,$A51,FALSE)/1000000 -> 1.2737741e+08 | O51: =VLOOKUP(O$1,reg_bal!$D$1:$CA$184,$A51,FALSE)/1000000 -> 1.2804908e+08 | P51: =VLOOKUP(P$1,reg_bal!$D$1:$CA$184,$A51,FALSE)/1000000 -> 1.4088097e+08 | R51: Human capital | S51: =VLOOKUP(S$1,reg_bal!$D$1:$CA$184,$A51,FALSE)/1000000 -> 11281066 | T51: =VLOOKUP(T$1,reg_bal!$D$1:$CA$184,$A51,FALSE)/1000000 -> 12648180 | U51: =VLOOKUP(U$1,reg_bal!$D$1:$CA$184,$A51,FALSE)/1000000 -> 15828504 | V51: =VLOOKUP(V$1,reg_bal!$D$1:$CA$184,$A51,FALSE)/1000000 -> 29993182 | W51: =VLOOKUP(W$1,reg_bal!$D$1:$CA$184,$A51,FALSE)/1000000 -> 30397099 | X51: =VLOOKUP(X$1,reg_bal!$D$1:$CA$184,$A51,FALSE)/1000000 -> 25871332 | Z51: Human capital | AA51: =VLOOKUP(AA$1,reg_bal!$D$1:$CA$184,$A51,FALSE)/1000000 -> 3035887.6 | AB51: =VLOOKUP(AB$1,reg_bal!$D$1:$CA$184,$A51,FALSE)/1000000 -> 3745814.6 | AC51: =VLOOKUP(AC$1,reg_bal!$D$1:$CA$184,$A51,FALSE)/1000000 -> 5076265.4 | AD51: =VLOOKUP(AD$1,reg_bal!$D$1:$CA$184,$A51,FALSE)/1000000 -> 9691279.3 | AE51: =VLOOKUP(AE$1,reg_bal!$D$1:$CA$184,$A51,FALSE)/1000000 -> 11668143 | AF51: =VLOOKUP(AF$1,reg_bal!$D$1:$CA$184,$A51,FALSE)/1000000 -> 11276730 | AH51: Human capital | AI51: =VLOOKUP(AI$1,reg_bal!$D$1:$CA$184,$A51,FALSE)/1000000 -> 70467209 | AJ51: =VLOOKUP(AJ$1,reg_bal!$D$1:$CA$184,$A51,FALSE)/1000000 -> 93360313 | AK51: =VLOOKUP(AK$1,reg_bal!$D$1:$CA$184,$A51,FALSE)/1000000 -> 1.0935068e+08 | AL51: =VLOOKUP(AL$1,reg_bal!$D$1:$CA$184,$A51,FALSE)/1000000 -> 1.1845329e+08 | AM51: =VLOOKUP(AM$1,reg_bal!$D$1:$CA$184,$A51,FALSE)/1000000 -> 1.496809e+08 | AN51: =VLOOKUP(AN$1,reg_bal!$D$1:$CA$184,$A51,FALSE)/1000000 -> 1.7523535e+08 | AP51: Human capital | AQ51: =VLOOKUP(AQ$1,reg_bal!$D$1:$CA$184,$A51,FALSE)/1000000 -> 2591726.5 | AR51: =VLOOKUP(AR$1,reg_bal!$D$1:$CA$184,$A51,FALSE)/1000000 -> 3361962.6 | AS51: =VLOOKUP(AS$1,reg_bal!$D$1:$CA$184,$A51,FALSE)/1000000 -> 5329117.2 | AT51: =VLOOKUP(AT$1,reg_bal!$D$1:$CA$184,$A51,FALSE)/1000000 -> 9644588.3 | AU51: =VLOOKUP(AU$1,reg_bal!$D$1:$CA$184,$A51,FALSE)/1000000 -> 12539888 | AV51: =VLOOKUP(AV$1,reg_bal!$D$1:$CA$184,$A51,FALSE)/1000000 -> 15957649 | AX51: Human capital | AY51: =VLOOKUP(AY$1,reg_bal!$D$1:$CA$184,$A51,FALSE)/1000000 -> 3057549.3 | AZ51: =VLOOKUP(AZ$1,reg_bal!$D$1:$CA$184,$A51,FALSE)/1000000 -> 2325009.5 | BA51: =VLOOKUP(BA$1,reg_bal!$D$1:$CA$184,$A51,FALSE)/1000000 -> 3844961.8 | BB51: =VLOOKUP(BB$1,reg_bal!$D$1:$CA$184,$A51,FALSE)/1000000 -> 8091177.2 | BC51: =VLOOKUP(BC$1,reg_bal!$D$1:$CA$184,$A51,FALSE)/1000000 -> 8451049.7 | BD51: =VLOOKUP(BD$1,reg_bal!$D$1:$CA$184,$A51,FALSE)/1000000 -> 9309443.2
A52: 43 | B52: Renewable natural capital | C52: =VLOOKUP(C$1,reg_bal!$D$1:$CA$184,$A52,FALSE)/1000000 -> 6013373.3 | D52: =VLOOKUP(D$1,reg_bal!$D$1:$CA$184,$A52,FALSE)/1000000 -> 5424940.3 | E52: =VLOOKUP(E$1,reg_bal!$D$1:$CA$184,$A52,FALSE)/1000000 -> 9214405.3 | F52: =VLOOKUP(F$1,reg_bal!$D$1:$CA$184,$A52,FALSE)/1000000 -> 15429527 | G52: =VLOOKUP(G$1,reg_bal!$D$1:$CA$184,$A52,FALSE)/1000000 -> 19549323 | H52: =VLOOKUP(H$1,reg_bal!$D$1:$CA$184,$A52,FALSE)/1000000 -> 22029603 | J52: Renewable natural capital | K52: =VLOOKUP(K$1,reg_bal!$D$1:$CA$184,$A52,FALSE)/1000000 -> 3543588.3 | L52: =VLOOKUP(L$1,reg_bal!$D$1:$CA$184,$A52,FALSE)/1000000 -> 2731371.7 | M52: =VLOOKUP(M$1,reg_bal!$D$1:$CA$184,$A52,FALSE)/1000000 -> 3590314.1 | N52: =VLOOKUP(N$1,reg_bal!$D$1:$CA$184,$A52,FALSE)/1000000 -> 5111534.1 | O52: =VLOOKUP(O$1,reg_bal!$D$1:$CA$184,$A52,FALSE)/1000000 -> 4299673.2 | P52: =VLOOKUP(P$1,reg_bal!$D$1:$CA$184,$A52,FALSE)/1000000 -> 4632571.1 | R52: Renewable natural capital | S52: =VLOOKUP(S$1,reg_bal!$D$1:$CA$184,$A52,FALSE)/1000000 -> 2287028.9 | T52: =VLOOKUP(T$1,reg_bal!$D$1:$CA$184,$A52,FALSE)/1000000 -> 2098102.4 | U52: =VLOOKUP(U$1,reg_bal!$D$1:$CA$184,$A52,FALSE)/1000000 -> 2287037.4 | V52: =VLOOKUP(V$1,reg_bal!$D$1:$CA$184,$A52,FALSE)/1000000 -> 3927170.3 | W52: =VLOOKUP(W$1,reg_bal!$D$1:$CA$184,$A52,FALSE)/1000000 -> 3686175.3 | X52: =VLOOKUP(X$1,reg_bal!$D$1:$CA$184,$A52,FALSE)/1000000 -> 3629176.1 | Z52: Renewable natural capital | AA52: =VLOOKUP(AA$1,reg_bal!$D$1:$CA$184,$A52,FALSE)/1000000 -> 634761.9 | AB52: =VLOOKUP(AB$1,reg_bal!$D$1:$CA$184,$A52,FALSE)/1000000 -> 627637.27 | AC52: =VLOOKUP(AC$1,reg_bal!$D$1:$CA$184,$A52,FALSE)/1000000 -> 821110.24 | AD52: =VLOOKUP(AD$1,reg_bal!$D$1:$CA$184,$A52,FALSE)/1000000 -> 1341565.8 | AE52: =VLOOKUP(AE$1,reg_bal!$D$1:$CA$184,$A52,FALSE)/1000000 -> 1503190.9 | AF52: =VLOOKUP(AF$1,reg_bal!$D$1:$CA$184,$A52,FALSE)/1000000 -> 2015345.6 | AH52: Renewable natural capital | AI52: =VLOOKUP(AI$1,reg_bal!$D$1:$CA$184,$A52,FALSE)/1000000 -> 1280432.4 | AJ52: =VLOOKUP(AJ$1,reg_bal!$D$1:$CA$184,$A52,FALSE)/1000000 -> 1257570 | AK52: =VLOOKUP(AK$1,reg_bal!$D$1:$CA$184,$A52,FALSE)/1000000 -> 1562015.3 | AL52: =VLOOKUP(AL$1,reg_bal!$D$1:$CA$184,$A52,FALSE)/1000000 -> 1783142.7 | AM52: =VLOOKUP(AM$1,reg_bal!$D$1:$CA$184,$A52,FALSE)/1000000 -> 2035519.3 | AN52: =VLOOKUP(AN$1,reg_bal!$D$1:$CA$184,$A52,FALSE)/1000000 -> 2233567.2 | AP52: Renewable natural capital | AQ52: =VLOOKUP(AQ$1,reg_bal!$D$1:$CA$184,$A52,FALSE)/1000000 -> 2062357.1 | AR52: =VLOOKUP(AR$1,reg_bal!$D$1:$CA$184,$A52,FALSE)/1000000 -> 1980048.4 | AS52: =VLOOKUP(AS$1,reg_bal!$D$1:$CA$184,$A52,FALSE)/1000000 -> 2657496.2 | AT52: =VLOOKUP(AT$1,reg_bal!$D$1:$CA$184,$A52,FALSE)/1000000 -> 4931515.1 | AU52: =VLOOKUP(AU$1,reg_bal!$D$1:$CA$184,$A52,FALSE)/1000000 -> 5966418.3 | AV52: =VLOOKUP(AV$1,reg_bal!$D$1:$CA$184,$A52,FALSE)/1000000 -> 9001970.8 | AX52: Renewable natural capital | AY52: =VLOOKUP(AY$1,reg_bal!$D$1:$CA$184,$A52,FALSE)/1000000 -> 1863670.4 | AZ52: =VLOOKUP(AZ$1,reg_bal!$D$1:$CA$184,$A52,FALSE)/1000000 -> 1725648.8 | BA52: =VLOOKUP(BA$1,reg_bal!$D$1:$CA$184,$A52,FALSE)/1000000 -> 2770897 | BB52: =VLOOKUP(BB$1,reg_bal!$D$1:$CA$184,$A52,FALSE)/1000000 -> 4349065.6 | BC52: =VLOOKUP(BC$1,reg_bal!$D$1:$CA$184,$A52,FALSE)/1000000 -> 5608124.6 | BD52: =VLOOKUP(BD$1,reg_bal!$D$1:$CA$184,$A52,FALSE)/1000000 -> 5683339.8
A53: 47 | B53: Forests, timber | C53: =VLOOKUP(C$1,reg_bal!$D$1:$CA$184,$A53,FALSE)/1000000 -> 507391.39 | D53: =VLOOKUP(D$1,reg_bal!$D$1:$CA$184,$A53,FALSE)/1000000 -> 264157.2 | E53: =VLOOKUP(E$1,reg_bal!$D$1:$CA$184,$A53,FALSE)/1000000 -> 338403.06 | F53: =VLOOKUP(F$1,reg_bal!$D$1:$CA$184,$A53,FALSE)/1000000 -> 747077.82 | G53: =VLOOKUP(G$1,reg_bal!$D$1:$CA$184,$A53,FALSE)/1000000 -> 740069.43 | H53: =VLOOKUP(H$1,reg_bal!$D$1:$CA$184,$A53,FALSE)/1000000 -> 865340.2 | J53: Forests, timber | K53: =VLOOKUP(K$1,reg_bal!$D$1:$CA$184,$A53,FALSE)/1000000 -> 210803.14 | L53: =VLOOKUP(L$1,reg_bal!$D$1:$CA$184,$A53,FALSE)/1000000 -> 195380.71 | M53: =VLOOKUP(M$1,reg_bal!$D$1:$CA$184,$A53,FALSE)/1000000 -> 244831.53 | N53: =VLOOKUP(N$1,reg_bal!$D$1:$CA$184,$A53,FALSE)/1000000 -> 363825.24 | O53: =VLOOKUP(O$1,reg_bal!$D$1:$CA$184,$A53,FALSE)/1000000 -> 352682.13 | P53: =VLOOKUP(P$1,reg_bal!$D$1:$CA$184,$A53,FALSE)/1000000 -> 446407.19 | R53: Forests, timber | S53: =VLOOKUP(S$1,reg_bal!$D$1:$CA$184,$A53,FALSE)/1000000 -> 196489.22 | T53: =VLOOKUP(T$1,reg_bal!$D$1:$CA$184,$A53,FALSE)/1000000 -> 120364.2 | U53: =VLOOKUP(U$1,reg_bal!$D$1:$CA$184,$A53,FALSE)/1000000 -> 155190.79 | V53: =VLOOKUP(V$1,reg_bal!$D$1:$CA$184,$A53,FALSE)/1000000 -> 458171.56 | W53: =VLOOKUP(W$1,reg_bal!$D$1:$CA$184,$A53,FALSE)/1000000 -> 520603.57 | X53: =VLOOKUP(X$1,reg_bal!$D$1:$CA$184,$A53,FALSE)/1000000 -> 550446.85 | Z53: Forests, timber | AA53: =VLOOKUP(AA$1,reg_bal!$D$1:$CA$184,$A53,FALSE)/1000000 -> 3764.5242 | AB53: =VLOOKUP(AB$1,reg_bal!$D$1:$CA$184,$A53,FALSE)/1000000 -> 2590.1452 | AC53: =VLOOKUP(AC$1,reg_bal!$D$1:$CA$184,$A53,FALSE)/1000000 -> 2907.9959 | AD53: =VLOOKUP(AD$1,reg_bal!$D$1:$CA$184,$A53,FALSE)/1000000 -> 4931.543 | AE53: =VLOOKUP(AE$1,reg_bal!$D$1:$CA$184,$A53,FALSE)/1000000 -> 7457.4009 | AF53: =VLOOKUP(AF$1,reg_bal!$D$1:$CA$184,$A53,FALSE)/1000000 -> 4696.6564 | AH53: Forests, timber | AI53: =VLOOKUP(AI$1,reg_bal!$D$1:$CA$184,$A53,FALSE)/1000000 -> 262606.14 | AJ53: =VLOOKUP(AJ$1,reg_bal!$D$1:$CA$184,$A53,FALSE)/1000000 -> 218652.85 | AK53: =VLOOKUP(AK$1,reg_bal!$D$1:$CA$184,$A53,FALSE)/1000000 -> 221841.51 | AL53: =VLOOKUP(AL$1,reg_bal!$D$1:$CA$184,$A53,FALSE)/1000000 -> 193098.74 | AM53: =VLOOKUP(AM$1,reg_bal!$D$1:$CA$184,$A53,FALSE)/1000000 -> 188975.56 | AN53: =VLOOKUP(AN$1,reg_bal!$D$1:$CA$184,$A53,FALSE)/1000000 -> 201274.08 | AP53: Forests, timber | AQ53: =VLOOKUP(AQ$1,reg_bal!$D$1:$CA$184,$A53,FALSE)/1000000 -> 22365.684 | AR53: =VLOOKUP(AR$1,reg_bal!$D$1:$CA$184,$A53,FALSE)/1000000 -> 21426.782 | AS53: =VLOOKUP(AS$1,reg_bal!$D$1:$CA$184,$A53,FALSE)/1000000 -> 22941.151 | AT53: =VLOOKUP(AT$1,reg_bal!$D$1:$CA$184,$A53,FALSE)/1000000 -> 79301.436 | AU53: =VLOOKUP(AU$1,reg_bal!$D$1:$CA$184,$A53,FALSE)/1000000 -> 79445.414 | AV53: =VLOOKUP(AV$1,reg_bal!$D$1:$CA$184,$A53,FALSE)/1000000 -> 65068.441 | AX53: Forests, timber | AY53: =VLOOKUP(AY$1,reg_bal!$D$1:$CA$184,$A53,FALSE)/1000000 -> 380092.62 | AZ53: =VLOOKUP(AZ$1,reg_bal!$D$1:$CA$184,$A53,FALSE)/1000000 -> 254856.86 | BA53: =VLOOKUP(BA$1,reg_bal!$D$1:$CA$184,$A53,FALSE)/1000000 -> 372905.57 | BB53: =VLOOKUP(BB$1,reg_bal!$D$1:$CA$184,$A53,FALSE)/1000000 -> 633395.33 | BC53: =VLOOKUP(BC$1,reg_bal!$D$1:$CA$184,$A53,FALSE)/1000000 -> 900262.34 | BD53: =VLOOKUP(BD$1,reg_bal!$D$1:$CA$184,$A53,FALSE)/1000000 -> 761331.41
A54: 49 | B54: Forests, recreation, hunting, and fishing services (es1) | C54: =VLOOKUP(C$1,reg_bal!$D$1:$CA$184,$A54,FALSE)/1000000 -> 272736.21 | D54: =VLOOKUP(D$1,reg_bal!$D$1:$CA$184,$A54,FALSE)/1000000 -> 97905.546 | E54: =VLOOKUP(E$1,reg_bal!$D$1:$CA$184,$A54,FALSE)/1000000 -> 439396.09 | F54: =VLOOKUP(F$1,reg_bal!$D$1:$CA$184,$A54,FALSE)/1000000 -> 595822.07 | G54: =VLOOKUP(G$1,reg_bal!$D$1:$CA$184,$A54,FALSE)/1000000 -> 769175.28 | H54: =VLOOKUP(H$1,reg_bal!$D$1:$CA$184,$A54,FALSE)/1000000 -> 894637.27 | J54: Forests, recreation, hunting, and fishing services (es1) | K54: =VLOOKUP(K$1,reg_bal!$D$1:$CA$184,$A54,FALSE)/1000000 -> 308174.45 | L54: =VLOOKUP(L$1,reg_bal!$D$1:$CA$184,$A54,FALSE)/1000000 -> 334574.29 | M54: =VLOOKUP(M$1,reg_bal!$D$1:$CA$184,$A54,FALSE)/1000000 -> 270571.49 | N54: =VLOOKUP(N$1,reg_bal!$D$1:$CA$184,$A54,FALSE)/1000000 -> 383625.77 | O54: =VLOOKUP(O$1,reg_bal!$D$1:$CA$184,$A54,FALSE)/1000000 -> 400920.36 | P54: =VLOOKUP(P$1,reg_bal!$D$1:$CA$184,$A54,FALSE)/1000000 -> 429449.52 | R54: Forests, recreation, hunting, and fishing services (es1) | S54: =VLOOKUP(S$1,reg_bal!$D$1:$CA$184,$A54,FALSE)/1000000 -> 14633.078 | T54: =VLOOKUP(T$1,reg_bal!$D$1:$CA$184,$A54,FALSE)/1000000 -> 23059.905 | U54: =VLOOKUP(U$1,reg_bal!$D$1:$CA$184,$A54,FALSE)/1000000 -> 30546.017 | V54: =VLOOKUP(V$1,reg_bal!$D$1:$CA$184,$A54,FALSE)/1000000 -> 40800.17 | W54: =VLOOKUP(W$1,reg_bal!$D$1:$CA$184,$A54,FALSE)/1000000 -> 56301.011 | X54: =VLOOKUP(X$1,reg_bal!$D$1:$CA$184,$A54,FALSE)/1000000 -> 36048.477 | Z54: Forests, recreation, hunting, and fishing services (es1) | AA54: =VLOOKUP(AA$1,reg_bal!$D$1:$CA$184,$A54,FALSE)/1000000 -> 4848.9293 | AB54: =VLOOKUP(AB$1,reg_bal!$D$1:$CA$184,$A54,FALSE)/1000000 -> 6950.1683 | AC54: =VLOOKUP(AC$1,reg_bal!$D$1:$CA$184,$A54,FALSE)/1000000 -> 11796.615 | AD54: =VLOOKUP(AD$1,reg_bal!$D$1:$CA$184,$A54,FALSE)/1000000 -> 17794.518 | AE54: =VLOOKUP(AE$1,reg_bal!$D$1:$CA$184,$A54,FALSE)/1000000 -> 21657.149 | AF54: =VLOOKUP(AF$1,reg_bal!$D$1:$CA$184,$A54,FALSE)/1000000 -> 58719.182 | AH54: Forests, recreation, hunting, and fishing services (es1) | AI54: =VLOOKUP(AI$1,reg_bal!$D$1:$CA$184,$A54,FALSE)/1000000 -> 75660.9 | AJ54: =VLOOKUP(AJ$1,reg_bal!$D$1:$CA$184,$A54,FALSE)/1000000 -> 96562.684 | AK54: =VLOOKUP(AK$1,reg_bal!$D$1:$CA$184,$A54,FALSE)/1000000 -> 97461.037 | AL54: =VLOOKUP(AL$1,reg_bal!$D$1:$CA$184,$A54,FALSE)/1000000 -> 132518.87 | AM54: =VLOOKUP(AM$1,reg_bal!$D$1:$CA$184,$A54,FALSE)/1000000 -> 300427.92 | AN54: =VLOOKUP(AN$1,reg_bal!$D$1:$CA$184,$A54,FALSE)/1000000 -> 207609.65 | AP54: Forests, recreation, hunting, and fishing services (es1) | AQ54: =VLOOKUP(AQ$1,reg_bal!$D$1:$CA$184,$A54,FALSE)/1000000 -> 48796.163 | AR54: =VLOOKUP(AR$1,reg_bal!$D$1:$CA$184,$A54,FALSE)/1000000 -> 6277.3911 | AS54: =VLOOKUP(AS$1,reg_bal!$D$1:$CA$184,$A54,FALSE)/1000000 -> 6953.0484 | AT54: =VLOOKUP(AT$1,reg_bal!$D$1:$CA$184,$A54,FALSE)/1000000 -> 87165.209 | AU54: =VLOOKUP(AU$1,reg_bal!$D$1:$CA$184,$A54,FALSE)/1000000 -> 19866.913 | AV54: =VLOOKUP(AV$1,reg_bal!$D$1:$CA$184,$A54,FALSE)/1000000 -> 11549.133 | AX54: Forests, recreation, hunting, and fishing services (es1) | AY54: =VLOOKUP(AY$1,reg_bal!$D$1:$CA$184,$A54,FALSE)/1000000 -> 33991.442 | AZ54: =VLOOKUP(AZ$1,reg_bal!$D$1:$CA$184,$A54,FALSE)/1000000 -> 34448.56 | BA54: =VLOOKUP(BA$1,reg_bal!$D$1:$CA$184,$A54,FALSE)/1000000 -> 26155.531 | BB54: =VLOOKUP(BB$1,reg_bal!$D$1:$CA$184,$A54,FALSE)/1000000 -> 28709.538 | BC54: =VLOOKUP(BC$1,reg_bal!$D$1:$CA$184,$A54,FALSE)/1000000 -> 41282.921 | BD54: =VLOOKUP(BD$1,reg_bal!$D$1:$CA$184,$A54,FALSE)/1000000 -> 171331.84
A55: 50 | B55: Forests, non-wood forest products (es2) | C55: =VLOOKUP(C$1,reg_bal!$D$1:$CA$184,$A55,FALSE)/1000000 -> 125074.36 | D55: =VLOOKUP(D$1,reg_bal!$D$1:$CA$184,$A55,FALSE)/1000000 -> 137460.76 | E55: =VLOOKUP(E$1,reg_bal!$D$1:$CA$184,$A55,FALSE)/1000000 -> 155760.2 | F55: =VLOOKUP(F$1,reg_bal!$D$1:$CA$184,$A55,FALSE)/1000000 -> 165496.21 | G55: =VLOOKUP(G$1,reg_bal!$D$1:$CA$184,$A55,FALSE)/1000000 -> 177116.76 | H55: =VLOOKUP(H$1,reg_bal!$D$1:$CA$184,$A55,FALSE)/1000000 -> 193986.67 | J55: Forests, non-wood forest products (es2) | K55: =VLOOKUP(K$1,reg_bal!$D$1:$CA$184,$A55,FALSE)/1000000 -> 87210.914 | L55: =VLOOKUP(L$1,reg_bal!$D$1:$CA$184,$A55,FALSE)/1000000 -> 93613.663 | M55: =VLOOKUP(M$1,reg_bal!$D$1:$CA$184,$A55,FALSE)/1000000 -> 98848.526 | N55: =VLOOKUP(N$1,reg_bal!$D$1:$CA$184,$A55,FALSE)/1000000 -> 111913.84 | O55: =VLOOKUP(O$1,reg_bal!$D$1:$CA$184,$A55,FALSE)/1000000 -> 122445.61 | P55: =VLOOKUP(P$1,reg_bal!$D$1:$CA$184,$A55,FALSE)/1000000 -> 134038.01 | R55: Forests, non-wood forest products (es2) | S55: =VLOOKUP(S$1,reg_bal!$D$1:$CA$184,$A55,FALSE)/1000000 -> 105200.7 | T55: =VLOOKUP(T$1,reg_bal!$D$1:$CA$184,$A55,FALSE)/1000000 -> 112886.47 | U55: =VLOOKUP(U$1,reg_bal!$D$1:$CA$184,$A55,FALSE)/1000000 -> 118757.49 | V55: =VLOOKUP(V$1,reg_bal!$D$1:$CA$184,$A55,FALSE)/1000000 -> 131349.65 | W55: =VLOOKUP(W$1,reg_bal!$D$1:$CA$184,$A55,FALSE)/1000000 -> 139122.88 | X55: =VLOOKUP(X$1,reg_bal!$D$1:$CA$184,$A55,FALSE)/1000000 -> 149744.07 | Z55: Forests, non-wood forest products (es2) | AA55: =VLOOKUP(AA$1,reg_bal!$D$1:$CA$184,$A55,FALSE)/1000000 -> 3496.4651 | AB55: =VLOOKUP(AB$1,reg_bal!$D$1:$CA$184,$A55,FALSE)/1000000 -> 3466.2035 | AC55: =VLOOKUP(AC$1,reg_bal!$D$1:$CA$184,$A55,FALSE)/1000000 -> 3895.4987 | AD55: =VLOOKUP(AD$1,reg_bal!$D$1:$CA$184,$A55,FALSE)/1000000 -> 3545.6571 | AE55: =VLOOKUP(AE$1,reg_bal!$D$1:$CA$184,$A55,FALSE)/1000000 -> 3775.5589 | AF55: =VLOOKUP(AF$1,reg_bal!$D$1:$CA$184,$A55,FALSE)/1000000 -> 4002.627 | AH55: Forests, non-wood forest products (es2) | AI55: =VLOOKUP(AI$1,reg_bal!$D$1:$CA$184,$A55,FALSE)/1000000 -> 53952.029 | AJ55: =VLOOKUP(AJ$1,reg_bal!$D$1:$CA$184,$A55,FALSE)/1000000 -> 58671.014 | AK55: =VLOOKUP(AK$1,reg_bal!$D$1:$CA$184,$A55,FALSE)/1000000 -> 63122.348 | AL55: =VLOOKUP(AL$1,reg_bal!$D$1:$CA$184,$A55,FALSE)/1000000 -> 72393.095 | AM55: =VLOOKUP(AM$1,reg_bal!$D$1:$CA$184,$A55,FALSE)/1000000 -> 79196.719 | AN55: =VLOOKUP(AN$1,reg_bal!$D$1:$CA$184,$A55,FALSE)/1000000 -> 85601.993 | AP55: Forests, non-wood forest products (es2) | AQ55: =VLOOKUP(AQ$1,reg_bal!$D$1:$CA$184,$A55,FALSE)/1000000 -> 30464.546 | AR55: =VLOOKUP(AR$1,reg_bal!$D$1:$CA$184,$A55,FALSE)/1000000 -> 33357.698 | AS55: =VLOOKUP(AS$1,reg_bal!$D$1:$CA$184,$A55,FALSE)/1000000 -> 28359.556 | AT55: =VLOOKUP(AT$1,reg_bal!$D$1:$CA$184,$A55,FALSE)/1000000 -> 30668.016 | AU55: =VLOOKUP(AU$1,reg_bal!$D$1:$CA$184,$A55,FALSE)/1000000 -> 29023.008 | AV55: =VLOOKUP(AV$1,reg_bal!$D$1:$CA$184,$A55,FALSE)/1000000 -> 29942.82 | AX55: Forests, non-wood forest products (es2) | AY55: =VLOOKUP(AY$1,reg_bal!$D$1:$CA$184,$A55,FALSE)/1000000 -> 63315.378 | AZ55: =VLOOKUP(AZ$1,reg_bal!$D$1:$CA$184,$A55,FALSE)/1000000 -> 71672.842 | BA55: =VLOOKUP(BA$1,reg_bal!$D$1:$CA$184,$A55,FALSE)/1000000 -> 72477.507 | BB55: =VLOOKUP(BB$1,reg_bal!$D$1:$CA$184,$A55,FALSE)/1000000 -> 93689.904 | BC55: =VLOOKUP(BC$1,reg_bal!$D$1:$CA$184,$A55,FALSE)/1000000 -> 109163.02 | BD55: =VLOOKUP(BD$1,reg_bal!$D$1:$CA$184,$A55,FALSE)/1000000 -> 118575.86
A56: 51 | B56: Forests, water retention services (es3) | C56: =VLOOKUP(C$1,reg_bal!$D$1:$CA$184,$A56,FALSE)/1000000 -> 432946.9 | D56: =VLOOKUP(D$1,reg_bal!$D$1:$CA$184,$A56,FALSE)/1000000 -> 486698.88 | E56: =VLOOKUP(E$1,reg_bal!$D$1:$CA$184,$A56,FALSE)/1000000 -> 655775.69 | F56: =VLOOKUP(F$1,reg_bal!$D$1:$CA$184,$A56,FALSE)/1000000 -> 838303.96 | G56: =VLOOKUP(G$1,reg_bal!$D$1:$CA$184,$A56,FALSE)/1000000 -> 957545.71 | H56: =VLOOKUP(H$1,reg_bal!$D$1:$CA$184,$A56,FALSE)/1000000 -> 1025523 | J56: Forests, water retention services (es3) | K56: =VLOOKUP(K$1,reg_bal!$D$1:$CA$184,$A56,FALSE)/1000000 -> 327312.51 | L56: =VLOOKUP(L$1,reg_bal!$D$1:$CA$184,$A56,FALSE)/1000000 -> 317887.86 | M56: =VLOOKUP(M$1,reg_bal!$D$1:$CA$184,$A56,FALSE)/1000000 -> 463413.99 | N56: =VLOOKUP(N$1,reg_bal!$D$1:$CA$184,$A56,FALSE)/1000000 -> 537052.77 | O56: =VLOOKUP(O$1,reg_bal!$D$1:$CA$184,$A56,FALSE)/1000000 -> 588200.5 | P56: =VLOOKUP(P$1,reg_bal!$D$1:$CA$184,$A56,FALSE)/1000000 -> 642896.03 | R56: Forests, water retention services (es3) | S56: =VLOOKUP(S$1,reg_bal!$D$1:$CA$184,$A56,FALSE)/1000000 -> 369825.94 | T56: =VLOOKUP(T$1,reg_bal!$D$1:$CA$184,$A56,FALSE)/1000000 -> 354207.99 | U56: =VLOOKUP(U$1,reg_bal!$D$1:$CA$184,$A56,FALSE)/1000000 -> 438178.65 | V56: =VLOOKUP(V$1,reg_bal!$D$1:$CA$184,$A56,FALSE)/1000000 -> 746466.16 | W56: =VLOOKUP(W$1,reg_bal!$D$1:$CA$184,$A56,FALSE)/1000000 -> 745166.78 | X56: =VLOOKUP(X$1,reg_bal!$D$1:$CA$184,$A56,FALSE)/1000000 -> 692625.05 | Z56: Forests, water retention services (es3) | AA56: =VLOOKUP(AA$1,reg_bal!$D$1:$CA$184,$A56,FALSE)/1000000 -> 19069.638 | AB56: =VLOOKUP(AB$1,reg_bal!$D$1:$CA$184,$A56,FALSE)/1000000 -> 20928.456 | AC56: =VLOOKUP(AC$1,reg_bal!$D$1:$CA$184,$A56,FALSE)/1000000 -> 25071.301 | AD56: =VLOOKUP(AD$1,reg_bal!$D$1:$CA$184,$A56,FALSE)/1000000 -> 27764.586 | AE56: =VLOOKUP(AE$1,reg_bal!$D$1:$CA$184,$A56,FALSE)/1000000 -> 30057.312 | AF56: =VLOOKUP(AF$1,reg_bal!$D$1:$CA$184,$A56,FALSE)/1000000 -> 32268.04 | AH56: Forests, water retention services (es3) | AI56: =VLOOKUP(AI$1,reg_bal!$D$1:$CA$184,$A56,FALSE)/1000000 -> 562993.5 | AJ56: =VLOOKUP(AJ$1,reg_bal!$D$1:$CA$184,$A56,FALSE)/1000000 -> 611763.41 | AK56: =VLOOKUP(AK$1,reg_bal!$D$1:$CA$184,$A56,FALSE)/1000000 -> 668448.09 | AL56: =VLOOKUP(AL$1,reg_bal!$D$1:$CA$184,$A56,FALSE)/1000000 -> 761273.3 | AM56: =VLOOKUP(AM$1,reg_bal!$D$1:$CA$184,$A56,FALSE)/1000000 -> 831799.01 | AN56: =VLOOKUP(AN$1,reg_bal!$D$1:$CA$184,$A56,FALSE)/1000000 -> 905468.8 | AP56: Forests, water retention services (es3) | AQ56: =VLOOKUP(AQ$1,reg_bal!$D$1:$CA$184,$A56,FALSE)/1000000 -> 57025.554 | AR56: =VLOOKUP(AR$1,reg_bal!$D$1:$CA$184,$A56,FALSE)/1000000 -> 63531.132 | AS56: =VLOOKUP(AS$1,reg_bal!$D$1:$CA$184,$A56,FALSE)/1000000 -> 69080.641 | AT56: =VLOOKUP(AT$1,reg_bal!$D$1:$CA$184,$A56,FALSE)/1000000 -> 81736.796 | AU56: =VLOOKUP(AU$1,reg_bal!$D$1:$CA$184,$A56,FALSE)/1000000 -> 92058.582 | AV56: =VLOOKUP(AV$1,reg_bal!$D$1:$CA$184,$A56,FALSE)/1000000 -> 103171.05 | AX56: Forests, water retention services (es3) | AY56: =VLOOKUP(AY$1,reg_bal!$D$1:$CA$184,$A56,FALSE)/1000000 -> 73963.135 | AZ56: =VLOOKUP(AZ$1,reg_bal!$D$1:$CA$184,$A56,FALSE)/1000000 -> 85626.28 | BA56: =VLOOKUP(BA$1,reg_bal!$D$1:$CA$184,$A56,FALSE)/1000000 -> 92063.724 | BB56: =VLOOKUP(BB$1,reg_bal!$D$1:$CA$184,$A56,FALSE)/1000000 -> 169450.15 | BC56: =VLOOKUP(BC$1,reg_bal!$D$1:$CA$184,$A56,FALSE)/1000000 -> 213388.22 | BD56: =VLOOKUP(BD$1,reg_bal!$D$1:$CA$184,$A56,FALSE)/1000000 -> 220103.9
A57: 48 | B57: Mangroves | C57: =VLOOKUP(C$1,reg_bal!$D$1:$CA$184,$A57,FALSE)/1000000 -> 58942.493 | D57: =VLOOKUP(D$1,reg_bal!$D$1:$CA$184,$A57,FALSE)/1000000 -> 66436.002 | E57: =VLOOKUP(E$1,reg_bal!$D$1:$CA$184,$A57,FALSE)/1000000 -> 101960.09 | F57: =VLOOKUP(F$1,reg_bal!$D$1:$CA$184,$A57,FALSE)/1000000 -> 195140.5 | G57: =VLOOKUP(G$1,reg_bal!$D$1:$CA$184,$A57,FALSE)/1000000 -> 332968.15 | H57: =VLOOKUP(H$1,reg_bal!$D$1:$CA$184,$A57,FALSE)/1000000 -> 568443.67 | J57: Mangroves | K57: =VLOOKUP(K$1,reg_bal!$D$1:$CA$184,$A57,FALSE)/1000000 -> 0 | L57: =VLOOKUP(L$1,reg_bal!$D$1:$CA$184,$A57,FALSE)/1000000 -> 0 | M57: =VLOOKUP(M$1,reg_bal!$D$1:$CA$184,$A57,FALSE)/1000000 -> 0 | N57: =VLOOKUP(N$1,reg_bal!$D$1:$CA$184,$A57,FALSE)/1000000 -> 0 | O57: =VLOOKUP(O$1,reg_bal!$D$1:$CA$184,$A57,FALSE)/1000000 -> 0 | P57: =VLOOKUP(P$1,reg_bal!$D$1:$CA$184,$A57,FALSE)/1000000 -> 0 | R57: Mangroves | S57: =VLOOKUP(S$1,reg_bal!$D$1:$CA$184,$A57,FALSE)/1000000 -> 17322.169 | T57: =VLOOKUP(T$1,reg_bal!$D$1:$CA$184,$A57,FALSE)/1000000 -> 21419.204 | U57: =VLOOKUP(U$1,reg_bal!$D$1:$CA$184,$A57,FALSE)/1000000 -> 27802.141 | V57: =VLOOKUP(V$1,reg_bal!$D$1:$CA$184,$A57,FALSE)/1000000 -> 44748.158 | W57: =VLOOKUP(W$1,reg_bal!$D$1:$CA$184,$A57,FALSE)/1000000 -> 48835.272 | X57: =VLOOKUP(X$1,reg_bal!$D$1:$CA$184,$A57,FALSE)/1000000 -> 75434.269 | Z57: Mangroves | AA57: =VLOOKUP(AA$1,reg_bal!$D$1:$CA$184,$A57,FALSE)/1000000 -> 4210.92 | AB57: =VLOOKUP(AB$1,reg_bal!$D$1:$CA$184,$A57,FALSE)/1000000 -> 4944.0062 | AC57: =VLOOKUP(AC$1,reg_bal!$D$1:$CA$184,$A57,FALSE)/1000000 -> 6468.0079 | AD57: =VLOOKUP(AD$1,reg_bal!$D$1:$CA$184,$A57,FALSE)/1000000 -> 8948.6317 | AE57: =VLOOKUP(AE$1,reg_bal!$D$1:$CA$184,$A57,FALSE)/1000000 -> 8723.7562 | AF57: =VLOOKUP(AF$1,reg_bal!$D$1:$CA$184,$A57,FALSE)/1000000 -> 12266.903 | AH57: Mangroves | AI57: =VLOOKUP(AI$1,reg_bal!$D$1:$CA$184,$A57,FALSE)/1000000 -> 19778.558 | AJ57: =VLOOKUP(AJ$1,reg_bal!$D$1:$CA$184,$A57,FALSE)/1000000 -> 21057.464 | AK57: =VLOOKUP(AK$1,reg_bal!$D$1:$CA$184,$A57,FALSE)/1000000 -> 23134.751 | AL57: =VLOOKUP(AL$1,reg_bal!$D$1:$CA$184,$A57,FALSE)/1000000 -> 24896.135 | AM57: =VLOOKUP(AM$1,reg_bal!$D$1:$CA$184,$A57,FALSE)/1000000 -> 25595.89 | AN57: =VLOOKUP(AN$1,reg_bal!$D$1:$CA$184,$A57,FALSE)/1000000 -> 59707.371 | AP57: Mangroves | AQ57: =VLOOKUP(AQ$1,reg_bal!$D$1:$CA$184,$A57,FALSE)/1000000 -> 6759.2628 | AR57: =VLOOKUP(AR$1,reg_bal!$D$1:$CA$184,$A57,FALSE)/1000000 -> 8650.0224 | AS57: =VLOOKUP(AS$1,reg_bal!$D$1:$CA$184,$A57,FALSE)/1000000 -> 13093.993 | AT57: =VLOOKUP(AT$1,reg_bal!$D$1:$CA$184,$A57,FALSE)/1000000 -> 22083.102 | AU57: =VLOOKUP(AU$1,reg_bal!$D$1:$CA$184,$A57,FALSE)/1000000 -> 29617.476 | AV57: =VLOOKUP(AV$1,reg_bal!$D$1:$CA$184,$A57,FALSE)/1000000 -> 73691.627 | AX57: Mangroves | AY57: =VLOOKUP(AY$1,reg_bal!$D$1:$CA$184,$A57,FALSE)/1000000 -> 1614.8381 | AZ57: =VLOOKUP(AZ$1,reg_bal!$D$1:$CA$184,$A57,FALSE)/1000000 -> 1712.9971 | BA57: =VLOOKUP(BA$1,reg_bal!$D$1:$CA$184,$A57,FALSE)/1000000 -> 2718.9411 | BB57: =VLOOKUP(BB$1,reg_bal!$D$1:$CA$184,$A57,FALSE)/1000000 -> 4505.2458 | BC57: =VLOOKUP(BC$1,reg_bal!$D$1:$CA$184,$A57,FALSE)/1000000 -> 7028.8421 | BD57: =VLOOKUP(BD$1,reg_bal!$D$1:$CA$184,$A57,FALSE)/1000000 -> 13445.991
A58: 52 | B58: Fisheries | C58: =VLOOKUP(C$1,reg_bal!$D$1:$CA$184,$A58,FALSE)/1000000 -> 348012.27 | D58: =VLOOKUP(D$1,reg_bal!$D$1:$CA$184,$A58,FALSE)/1000000 -> 353273.01 | E58: =VLOOKUP(E$1,reg_bal!$D$1:$CA$184,$A58,FALSE)/1000000 -> 309392.94 | F58: =VLOOKUP(F$1,reg_bal!$D$1:$CA$184,$A58,FALSE)/1000000 -> 90463.989 | G58: =VLOOKUP(G$1,reg_bal!$D$1:$CA$184,$A58,FALSE)/1000000 -> 90471.755 | H58: =VLOOKUP(H$1,reg_bal!$D$1:$CA$184,$A58,FALSE)/1000000 -> 105083.49 | J58: Fisheries | K58: =VLOOKUP(K$1,reg_bal!$D$1:$CA$184,$A58,FALSE)/1000000 -> 37442.899 | L58: =VLOOKUP(L$1,reg_bal!$D$1:$CA$184,$A58,FALSE)/1000000 -> 16255.956 | M58: =VLOOKUP(M$1,reg_bal!$D$1:$CA$184,$A58,FALSE)/1000000 -> 128047.07 | N58: =VLOOKUP(N$1,reg_bal!$D$1:$CA$184,$A58,FALSE)/1000000 -> 43233.775 | O58: =VLOOKUP(O$1,reg_bal!$D$1:$CA$184,$A58,FALSE)/1000000 -> 40232.902 | P58: =VLOOKUP(P$1,reg_bal!$D$1:$CA$184,$A58,FALSE)/1000000 -> 33624.136 | R58: Fisheries | S58: =VLOOKUP(S$1,reg_bal!$D$1:$CA$184,$A58,FALSE)/1000000 -> 133909.33 | T58: =VLOOKUP(T$1,reg_bal!$D$1:$CA$184,$A58,FALSE)/1000000 -> 188084.8 | U58: =VLOOKUP(U$1,reg_bal!$D$1:$CA$184,$A58,FALSE)/1000000 -> 129632.42 | V58: =VLOOKUP(V$1,reg_bal!$D$1:$CA$184,$A58,FALSE)/1000000 -> 17429.189 | W58: =VLOOKUP(W$1,reg_bal!$D$1:$CA$184,$A58,FALSE)/1000000 -> 13269.35 | X58: =VLOOKUP(X$1,reg_bal!$D$1:$CA$184,$A58,FALSE)/1000000 -> 25979.76 | Z58: Fisheries | AA58: =VLOOKUP(AA$1,reg_bal!$D$1:$CA$184,$A58,FALSE)/1000000 -> 1492.0922 | AB58: =VLOOKUP(AB$1,reg_bal!$D$1:$CA$184,$A58,FALSE)/1000000 -> 1539.8489 | AC58: =VLOOKUP(AC$1,reg_bal!$D$1:$CA$184,$A58,FALSE)/1000000 -> 9087.6118 | AD58: =VLOOKUP(AD$1,reg_bal!$D$1:$CA$184,$A58,FALSE)/1000000 -> 6765.0947 | AE58: =VLOOKUP(AE$1,reg_bal!$D$1:$CA$184,$A58,FALSE)/1000000 -> 6879.9815 | AF58: =VLOOKUP(AF$1,reg_bal!$D$1:$CA$184,$A58,FALSE)/1000000 -> 9648.2908 | AH58: Fisheries | AI58: =VLOOKUP(AI$1,reg_bal!$D$1:$CA$184,$A58,FALSE)/1000000 -> 22065.831 | AJ58: =VLOOKUP(AJ$1,reg_bal!$D$1:$CA$184,$A58,FALSE)/1000000 -> 13845.966 | AK58: =VLOOKUP(AK$1,reg_bal!$D$1:$CA$184,$A58,FALSE)/1000000 -> 112951.55 | AL58: =VLOOKUP(AL$1,reg_bal!$D$1:$CA$184,$A58,FALSE)/1000000 -> 39730.273 | AM58: =VLOOKUP(AM$1,reg_bal!$D$1:$CA$184,$A58,FALSE)/1000000 -> 21999.522 | AN58: =VLOOKUP(AN$1,reg_bal!$D$1:$CA$184,$A58,FALSE)/1000000 -> 21112.174 | AP58: Fisheries | AQ58: =VLOOKUP(AQ$1,reg_bal!$D$1:$CA$184,$A58,FALSE)/1000000 -> 1303.3467 | AR58: =VLOOKUP(AR$1,reg_bal!$D$1:$CA$184,$A58,FALSE)/1000000 -> 1784.6913 | AS58: =VLOOKUP(AS$1,reg_bal!$D$1:$CA$184,$A58,FALSE)/1000000 -> 4744.3451 | AT58: =VLOOKUP(AT$1,reg_bal!$D$1:$CA$184,$A58,FALSE)/1000000 -> 8943.198 | AU58: =VLOOKUP(AU$1,reg_bal!$D$1:$CA$184,$A58,FALSE)/1000000 -> 13466.066 | AV58: =VLOOKUP(AV$1,reg_bal!$D$1:$CA$184,$A58,FALSE)/1000000 -> 15027.791 | AX58: Fisheries | AY58: =VLOOKUP(AY$1,reg_bal!$D$1:$CA$184,$A58,FALSE)/1000000 -> 9189.0153 | AZ58: =VLOOKUP(AZ$1,reg_bal!$D$1:$CA$184,$A58,FALSE)/1000000 -> 10788.726 | BA58: =VLOOKUP(BA$1,reg_bal!$D$1:$CA$184,$A58,FALSE)/1000000 -> 13978.744 | BB58: =VLOOKUP(BB$1,reg_bal!$D$1:$CA$184,$A58,FALSE)/1000000 -> 8641.9757 | BC58: =VLOOKUP(BC$1,reg_bal!$D$1:$CA$184,$A58,FALSE)/1000000 -> 11961.317 | BD58: =VLOOKUP(BD$1,reg_bal!$D$1:$CA$184,$A58,FALSE)/1000000 -> 18262.824
A59: 44 | B59: Agricultural land | C59: =VLOOKUP(C$1,reg_bal!$D$1:$CA$184,$A59,FALSE)/1000000 -> 3904644.1 | D59: =VLOOKUP(D$1,reg_bal!$D$1:$CA$184,$A59,FALSE)/1000000 -> 3773026.2 | E59: =VLOOKUP(E$1,reg_bal!$D$1:$CA$184,$A59,FALSE)/1000000 -> 6943908.2 | F59: =VLOOKUP(F$1,reg_bal!$D$1:$CA$184,$A59,FALSE)/1000000 -> 12175228 | G59: =VLOOKUP(G$1,reg_bal!$D$1:$CA$184,$A59,FALSE)/1000000 -> 15306731 | H59: =VLOOKUP(H$1,reg_bal!$D$1:$CA$184,$A59,FALSE)/1000000 -> 17199745 | J59: Agricultural land | K59: =VLOOKUP(K$1,reg_bal!$D$1:$CA$184,$A59,FALSE)/1000000 -> 2185902.6 | L59: =VLOOKUP(L$1,reg_bal!$D$1:$CA$184,$A59,FALSE)/1000000 -> 1623977.5 | M59: =VLOOKUP(M$1,reg_bal!$D$1:$CA$184,$A59,FALSE)/1000000 -> 2060406.1 | N59: =VLOOKUP(N$1,reg_bal!$D$1:$CA$184,$A59,FALSE)/1000000 -> 2996705.9 | O59: =VLOOKUP(O$1,reg_bal!$D$1:$CA$184,$A59,FALSE)/1000000 -> 2358586.9 | P59: =VLOOKUP(P$1,reg_bal!$D$1:$CA$184,$A59,FALSE)/1000000 -> 2498646.1 | R59: Agricultural land | S59: =VLOOKUP(S$1,reg_bal!$D$1:$CA$184,$A59,FALSE)/1000000 -> 695878.5 | T59: =VLOOKUP(T$1,reg_bal!$D$1:$CA$184,$A59,FALSE)/1000000 -> 666867.34 | U59: =VLOOKUP(U$1,reg_bal!$D$1:$CA$184,$A59,FALSE)/1000000 -> 657604.58 | V59: =VLOOKUP(V$1,reg_bal!$D$1:$CA$184,$A59,FALSE)/1000000 -> 1189496.1 | W59: =VLOOKUP(W$1,reg_bal!$D$1:$CA$184,$A59,FALSE)/1000000 -> 1336799.9 | X59: =VLOOKUP(X$1,reg_bal!$D$1:$CA$184,$A59,FALSE)/1000000 -> 1422946.1 | Z59: Agricultural land | AA59: =VLOOKUP(AA$1,reg_bal!$D$1:$CA$184,$A59,FALSE)/1000000 -> 592298.2 | AB59: =VLOOKUP(AB$1,reg_bal!$D$1:$CA$184,$A59,FALSE)/1000000 -> 584407.8 | AC59: =VLOOKUP(AC$1,reg_bal!$D$1:$CA$184,$A59,FALSE)/1000000 -> 752457.53 | AD59: =VLOOKUP(AD$1,reg_bal!$D$1:$CA$184,$A59,FALSE)/1000000 -> 1261814.8 | AE59: =VLOOKUP(AE$1,reg_bal!$D$1:$CA$184,$A59,FALSE)/1000000 -> 1419271 | AF59: =VLOOKUP(AF$1,reg_bal!$D$1:$CA$184,$A59,FALSE)/1000000 -> 1874062.1 | AH59: Agricultural land | AI59: =VLOOKUP(AI$1,reg_bal!$D$1:$CA$184,$A59,FALSE)/1000000 -> 98551.909 | AJ59: =VLOOKUP(AJ$1,reg_bal!$D$1:$CA$184,$A59,FALSE)/1000000 -> 90818.852 | AK59: =VLOOKUP(AK$1,reg_bal!$D$1:$CA$184,$A59,FALSE)/1000000 -> 102519.5 | AL59: =VLOOKUP(AL$1,reg_bal!$D$1:$CA$184,$A59,FALSE)/1000000 -> 184726.75 | AM59: =VLOOKUP(AM$1,reg_bal!$D$1:$CA$184,$A59,FALSE)/1000000 -> 178138.53 | AN59: =VLOOKUP(AN$1,reg_bal!$D$1:$CA$184,$A59,FALSE)/1000000 -> 205579.71 | AP59: Agricultural land | AQ59: =VLOOKUP(AQ$1,reg_bal!$D$1:$CA$184,$A59,FALSE)/1000000 -> 1844127 | AR59: =VLOOKUP(AR$1,reg_bal!$D$1:$CA$184,$A59,FALSE)/1000000 -> 1818747.2 | AS59: =VLOOKUP(AS$1,reg_bal!$D$1:$CA$184,$A59,FALSE)/1000000 -> 2471873.9 | AT59: =VLOOKUP(AT$1,reg_bal!$D$1:$CA$184,$A59,FALSE)/1000000 -> 4547008.4 | AU59: =VLOOKUP(AU$1,reg_bal!$D$1:$CA$184,$A59,FALSE)/1000000 -> 5616497.4 | AV59: =VLOOKUP(AV$1,reg_bal!$D$1:$CA$184,$A59,FALSE)/1000000 -> 8625677.9 | AX59: Agricultural land | AY59: =VLOOKUP(AY$1,reg_bal!$D$1:$CA$184,$A59,FALSE)/1000000 -> 1219356.1 | AZ59: =VLOOKUP(AZ$1,reg_bal!$D$1:$CA$184,$A59,FALSE)/1000000 -> 1191228.6 | BA59: =VLOOKUP(BA$1,reg_bal!$D$1:$CA$184,$A59,FALSE)/1000000 -> 2044820.8 | BB59: =VLOOKUP(BB$1,reg_bal!$D$1:$CA$184,$A59,FALSE)/1000000 -> 3186967.4 | BC59: =VLOOKUP(BC$1,reg_bal!$D$1:$CA$184,$A59,FALSE)/1000000 -> 4096342.4 | BD59: =VLOOKUP(BD$1,reg_bal!$D$1:$CA$184,$A59,FALSE)/1000000 -> 4109457.8
A60: 53 | B60: Hydropower energy | C60: =VLOOKUP(C$1,reg_bal!$D$1:$CA$184,$A60,FALSE)/1000000 -> 363625.56 | D60: =VLOOKUP(D$1,reg_bal!$D$1:$CA$184,$A60,FALSE)/1000000 -> 245982.7 | E60: =VLOOKUP(E$1,reg_bal!$D$1:$CA$184,$A60,FALSE)/1000000 -> 269808.98 | F60: =VLOOKUP(F$1,reg_bal!$D$1:$CA$184,$A60,FALSE)/1000000 -> 621995.03 | G60: =VLOOKUP(G$1,reg_bal!$D$1:$CA$184,$A60,FALSE)/1000000 -> 1175244.5 | H60: =VLOOKUP(H$1,reg_bal!$D$1:$CA$184,$A60,FALSE)/1000000 -> 1176843.2 | J60: Hydropower energy | K60: =VLOOKUP(K$1,reg_bal!$D$1:$CA$184,$A60,FALSE)/1000000 -> 386741.78 | L60: =VLOOKUP(L$1,reg_bal!$D$1:$CA$184,$A60,FALSE)/1000000 -> 149681.74 | M60: =VLOOKUP(M$1,reg_bal!$D$1:$CA$184,$A60,FALSE)/1000000 -> 324195.43 | N60: =VLOOKUP(N$1,reg_bal!$D$1:$CA$184,$A60,FALSE)/1000000 -> 675176.89 | O60: =VLOOKUP(O$1,reg_bal!$D$1:$CA$184,$A60,FALSE)/1000000 -> 436604.76 | P60: =VLOOKUP(P$1,reg_bal!$D$1:$CA$184,$A60,FALSE)/1000000 -> 447510.2 | R60: Hydropower energy | S60: =VLOOKUP(S$1,reg_bal!$D$1:$CA$184,$A60,FALSE)/1000000 -> 753769.94 | T60: =VLOOKUP(T$1,reg_bal!$D$1:$CA$184,$A60,FALSE)/1000000 -> 611212.46 | U60: =VLOOKUP(U$1,reg_bal!$D$1:$CA$184,$A60,FALSE)/1000000 -> 729325.33 | V60: =VLOOKUP(V$1,reg_bal!$D$1:$CA$184,$A60,FALSE)/1000000 -> 1298709.3 | W60: =VLOOKUP(W$1,reg_bal!$D$1:$CA$184,$A60,FALSE)/1000000 -> 826076.52 | X60: =VLOOKUP(X$1,reg_bal!$D$1:$CA$184,$A60,FALSE)/1000000 -> 675951.47 | Z60: Hydropower energy | AA60: =VLOOKUP(AA$1,reg_bal!$D$1:$CA$184,$A60,FALSE)/1000000 -> 5581.1354 | AB60: =VLOOKUP(AB$1,reg_bal!$D$1:$CA$184,$A60,FALSE)/1000000 -> 2810.6413 | AC60: =VLOOKUP(AC$1,reg_bal!$D$1:$CA$184,$A60,FALSE)/1000000 -> 9425.6798 | AD60: =VLOOKUP(AD$1,reg_bal!$D$1:$CA$184,$A60,FALSE)/1000000 -> 10001.034 | AE60: =VLOOKUP(AE$1,reg_bal!$D$1:$CA$184,$A60,FALSE)/1000000 -> 5368.8185 | AF60: =VLOOKUP(AF$1,reg_bal!$D$1:$CA$184,$A60,FALSE)/1000000 -> 19681.757 | AH60: Hydropower energy | AI60: =VLOOKUP(AI$1,reg_bal!$D$1:$CA$184,$A60,FALSE)/1000000 -> 184823.59 | AJ60: =VLOOKUP(AJ$1,reg_bal!$D$1:$CA$184,$A60,FALSE)/1000000 -> 146197.72 | AK60: =VLOOKUP(AK$1,reg_bal!$D$1:$CA$184,$A60,FALSE)/1000000 -> 272536.56 | AL60: =VLOOKUP(AL$1,reg_bal!$D$1:$CA$184,$A60,FALSE)/1000000 -> 374505.53 | AM60: =VLOOKUP(AM$1,reg_bal!$D$1:$CA$184,$A60,FALSE)/1000000 -> 409386.15 | AN60: =VLOOKUP(AN$1,reg_bal!$D$1:$CA$184,$A60,FALSE)/1000000 -> 547213.46 | AP60: Hydropower energy | AQ60: =VLOOKUP(AQ$1,reg_bal!$D$1:$CA$184,$A60,FALSE)/1000000 -> 51515.607 | AR60: =VLOOKUP(AR$1,reg_bal!$D$1:$CA$184,$A60,FALSE)/1000000 -> 26273.429 | AS60: =VLOOKUP(AS$1,reg_bal!$D$1:$CA$184,$A60,FALSE)/1000000 -> 40449.498 | AT60: =VLOOKUP(AT$1,reg_bal!$D$1:$CA$184,$A60,FALSE)/1000000 -> 74609.037 | AU60: =VLOOKUP(AU$1,reg_bal!$D$1:$CA$184,$A60,FALSE)/1000000 -> 86443.38 | AV60: =VLOOKUP(AV$1,reg_bal!$D$1:$CA$184,$A60,FALSE)/1000000 -> 77842.046 | AX60: Hydropower energy | AY60: =VLOOKUP(AY$1,reg_bal!$D$1:$CA$184,$A60,FALSE)/1000000 -> 82147.883 | AZ60: =VLOOKUP(AZ$1,reg_bal!$D$1:$CA$184,$A60,FALSE)/1000000 -> 75313.938 | BA60: =VLOOKUP(BA$1,reg_bal!$D$1:$CA$184,$A60,FALSE)/1000000 -> 145776.13 | BB60: =VLOOKUP(BB$1,reg_bal!$D$1:$CA$184,$A60,FALSE)/1000000 -> 223706.03 | BC60: =VLOOKUP(BC$1,reg_bal!$D$1:$CA$184,$A60,FALSE)/1000000 -> 228695.55 | BD60: =VLOOKUP(BD$1,reg_bal!$D$1:$CA$184,$A60,FALSE)/1000000 -> 270830.21
A61: 54 | B61: Nonrenewable natural capital | C61: =VLOOKUP(C$1,reg_bal!$D$1:$CA$184,$A61,FALSE)/1000000 -> 757894.22 | D61: =VLOOKUP(D$1,reg_bal!$D$1:$CA$184,$A61,FALSE)/1000000 -> 827546.7 | E61: =VLOOKUP(E$1,reg_bal!$D$1:$CA$184,$A61,FALSE)/1000000 -> 3043523.4 | F61: =VLOOKUP(F$1,reg_bal!$D$1:$CA$184,$A61,FALSE)/1000000 -> 8204367.5 | G61: =VLOOKUP(G$1,reg_bal!$D$1:$CA$184,$A61,FALSE)/1000000 -> 2272400.9 | H61: =VLOOKUP(H$1,reg_bal!$D$1:$CA$184,$A61,FALSE)/1000000 -> 4563026.2 | J61: Nonrenewable natural capital | K61: =VLOOKUP(K$1,reg_bal!$D$1:$CA$184,$A61,FALSE)/1000000 -> 1298252.8 | L61: =VLOOKUP(L$1,reg_bal!$D$1:$CA$184,$A61,FALSE)/1000000 -> 965341.51 | M61: =VLOOKUP(M$1,reg_bal!$D$1:$CA$184,$A61,FALSE)/1000000 -> 2164010.8 | N61: =VLOOKUP(N$1,reg_bal!$D$1:$CA$184,$A61,FALSE)/1000000 -> 6730481.8 | O61: =VLOOKUP(O$1,reg_bal!$D$1:$CA$184,$A61,FALSE)/1000000 -> 2321860.7 | P61: =VLOOKUP(P$1,reg_bal!$D$1:$CA$184,$A61,FALSE)/1000000 -> 4114711.5 | R61: Nonrenewable natural capital | S61: =VLOOKUP(S$1,reg_bal!$D$1:$CA$184,$A61,FALSE)/1000000 -> 414189.66 | T61: =VLOOKUP(T$1,reg_bal!$D$1:$CA$184,$A61,FALSE)/1000000 -> 629829.88 | U61: =VLOOKUP(U$1,reg_bal!$D$1:$CA$184,$A61,FALSE)/1000000 -> 1518228.7 | V61: =VLOOKUP(V$1,reg_bal!$D$1:$CA$184,$A61,FALSE)/1000000 -> 2430403.4 | W61: =VLOOKUP(W$1,reg_bal!$D$1:$CA$184,$A61,FALSE)/1000000 -> 707599.34 | X61: =VLOOKUP(X$1,reg_bal!$D$1:$CA$184,$A61,FALSE)/1000000 -> 1576734.8 | Z61: Nonrenewable natural capital | AA61: =VLOOKUP(AA$1,reg_bal!$D$1:$CA$184,$A61,FALSE)/1000000 -> 1006495.2 | AB61: =VLOOKUP(AB$1,reg_bal!$D$1:$CA$184,$A61,FALSE)/1000000 -> 2333139.6 | AC61: =VLOOKUP(AC$1,reg_bal!$D$1:$CA$184,$A61,FALSE)/1000000 -> 4805158.6 | AD61: =VLOOKUP(AD$1,reg_bal!$D$1:$CA$184,$A61,FALSE)/1000000 -> 7997884.7 | AE61: =VLOOKUP(AE$1,reg_bal!$D$1:$CA$184,$A61,FALSE)/1000000 -> 5599767.9 | AF61: =VLOOKUP(AF$1,reg_bal!$D$1:$CA$184,$A61,FALSE)/1000000 -> 4344970.7 | AH61: Nonrenewable natural capital | AI61: =VLOOKUP(AI$1,reg_bal!$D$1:$CA$184,$A61,FALSE)/1000000 -> 751859.07 | AJ61: =VLOOKUP(AJ$1,reg_bal!$D$1:$CA$184,$A61,FALSE)/1000000 -> 1339807.8 | AK61: =VLOOKUP(AK$1,reg_bal!$D$1:$CA$184,$A61,FALSE)/1000000 -> 3521670.8 | AL61: =VLOOKUP(AL$1,reg_bal!$D$1:$CA$184,$A61,FALSE)/1000000 -> 4250228.6 | AM61: =VLOOKUP(AM$1,reg_bal!$D$1:$CA$184,$A61,FALSE)/1000000 -> 1392785.6 | AN61: =VLOOKUP(AN$1,reg_bal!$D$1:$CA$184,$A61,FALSE)/1000000 -> 1853548.4 | AP61: Nonrenewable natural capital | AQ61: =VLOOKUP(AQ$1,reg_bal!$D$1:$CA$184,$A61,FALSE)/1000000 -> 121373.93 | AR61: =VLOOKUP(AR$1,reg_bal!$D$1:$CA$184,$A61,FALSE)/1000000 -> 175788.31 | AS61: =VLOOKUP(AS$1,reg_bal!$D$1:$CA$184,$A61,FALSE)/1000000 -> 608476.01 | AT61: =VLOOKUP(AT$1,reg_bal!$D$1:$CA$184,$A61,FALSE)/1000000 -> 1480431.3 | AU61: =VLOOKUP(AU$1,reg_bal!$D$1:$CA$184,$A61,FALSE)/1000000 -> 579199.78 | AV61: =VLOOKUP(AV$1,reg_bal!$D$1:$CA$184,$A61,FALSE)/1000000 -> 790619.29 | AX61: Nonrenewable natural capital | AY61: =VLOOKUP(AY$1,reg_bal!$D$1:$CA$184,$A61,FALSE)/1000000 -> 241990.55 | AZ61: =VLOOKUP(AZ$1,reg_bal!$D$1:$CA$184,$A61,FALSE)/1000000 -> 517317.67 | BA61: =VLOOKUP(BA$1,reg_bal!$D$1:$CA$184,$A61,FALSE)/1000000 -> 1433533.3 | BB61: =VLOOKUP(BB$1,reg_bal!$D$1:$CA$184,$A61,FALSE)/1000000 -> 2164799.6 | BC61: =VLOOKUP(BC$1,reg_bal!$D$1:$CA$184,$A61,FALSE)/1000000 -> 921836.18 | BD61: =VLOOKUP(BD$1,reg_bal!$D$1:$CA$184,$A61,FALSE)/1000000 -> 925904.85
... A65: 58 | B65: Metals and minerals | C65: =VLOOKUP(C$1,reg_bal!$D$1:$CA$184,$A65,FALSE)/1000000 -> 343118.47 | D65: =VLOOKUP(D$1,reg_bal!$D$1:$CA$184,$A65,FALSE)/1000000 -> 198400.83 | E65: =VLOOKUP(E$1,reg_bal!$D$1:$CA$184,$A65,FALSE)/1000000 -> 755581.86 | F65: =VLOOKUP(F$1,reg_bal!$D$1:$CA$184,$A65,FALSE)/1000000 -> 2660583.1 | G65: =VLOOKUP(G$1,reg_bal!$D$1:$CA$184,$A65,FALSE)/1000000 -> 1007712.3 | H65: =VLOOKUP(H$1,reg_bal!$D$1:$CA$184,$A65,FALSE)/1000000 -> 3101469.6 | J65: Metals and minerals | K65: =VLOOKUP(K$1,reg_bal!$D$1:$CA$184,$A65,FALSE)/1000000 -> 213296.74 | L65: =VLOOKUP(L$1,reg_bal!$D$1:$CA$184,$A65,FALSE)/1000000 -> 117324.65 | M65: =VLOOKUP(M$1,reg_bal!$D$1:$CA$184,$A65,FALSE)/1000000 -> 318644.45 | N65: =VLOOKUP(N$1,reg_bal!$D$1:$CA$184,$A65,FALSE)/1000000 -> 881766.71 | O65: =VLOOKUP(O$1,reg_bal!$D$1:$CA$184,$A65,FALSE)/1000000 -> 395716.46 | P65: =VLOOKUP(P$1,reg_bal!$D$1:$CA$184,$A65,FALSE)/1000000 -> 1262012.9 | R65: Metals and minerals | S65: =VLOOKUP(S$1,reg_bal!$D$1:$CA$184,$A65,FALSE)/1000000 -> 194753.21 | T65: =VLOOKUP(T$1,reg_bal!$D$1:$CA$184,$A65,FALSE)/1000000 -> 121157.16 | U65: =VLOOKUP(U$1,reg_bal!$D$1:$CA$184,$A65,FALSE)/1000000 -> 658396.19 | V65: =VLOOKUP(V$1,reg_bal!$D$1:$CA$184,$A65,FALSE)/1000000 -> 1995797.8 | W65: =VLOOKUP(W$1,reg_bal!$D$1:$CA$184,$A65,FALSE)/1000000 -> 419668.63 | X65: =VLOOKUP(X$1,reg_bal!$D$1:$CA$184,$A65,FALSE)/1000000 -> 1525167.5 | Z65: Metals and minerals | AA65: =VLOOKUP(AA$1,reg_bal!$D$1:$CA$184,$A65,FALSE)/1000000 -> 11275.757 | AB65: =VLOOKUP(AB$1,reg_bal!$D$1:$CA$184,$A65,FALSE)/1000000 -> 7247.0262 | AC65: =VLOOKUP(AC$1,reg_bal!$D$1:$CA$184,$A65,FALSE)/1000000 -> 30336.151 | AD65: =VLOOKUP(AD$1,reg_bal!$D$1:$CA$184,$A65,FALSE)/1000000 -> 155369.35 | AE65: =VLOOKUP(AE$1,reg_bal!$D$1:$CA$184,$A65,FALSE)/1000000 -> 90000.366 | AF65: =VLOOKUP(AF$1,reg_bal!$D$1:$CA$184,$A65,FALSE)/1000000 -> 145212.69 | AH65: Metals and minerals | AI65: =VLOOKUP(AI$1,reg_bal!$D$1:$CA$184,$A65,FALSE)/1000000 -> 118591.46 | AJ65: =VLOOKUP(AJ$1,reg_bal!$D$1:$CA$184,$A65,FALSE)/1000000 -> 70924.094 | AK65: =VLOOKUP(AK$1,reg_bal!$D$1:$CA$184,$A65,FALSE)/1000000 -> 312317.6 | AL65: =VLOOKUP(AL$1,reg_bal!$D$1:$CA$184,$A65,FALSE)/1000000 -> 433601.65 | AM65: =VLOOKUP(AM$1,reg_bal!$D$1:$CA$184,$A65,FALSE)/1000000 -> 118572.75 | AN65: =VLOOKUP(AN$1,reg_bal!$D$1:$CA$184,$A65,FALSE)/1000000 -> 372188.26 | AP65: Metals and minerals | AQ65: =VLOOKUP(AQ$1,reg_bal!$D$1:$CA$184,$A65,FALSE)/1000000 -> 25804.334 | AR65: =VLOOKUP(AR$1,reg_bal!$D$1:$CA$184,$A65,FALSE)/1000000 -> 28333.391 | AS65: =VLOOKUP(AS$1,reg_bal!$D$1:$CA$184,$A65,FALSE)/1000000 -> 162071.06 | AT65: =VLOOKUP(AT$1,reg_bal!$D$1:$CA$184,$A65,FALSE)/1000000 -> 486942.14 | AU65: =VLOOKUP(AU$1,reg_bal!$D$1:$CA$184,$A65,FALSE)/1000000 -> 134889.9 | AV65: =VLOOKUP(AV$1,reg_bal!$D$1:$CA$184,$A65,FALSE)/1000000 -> 328662.32 | AX65: Metals and minerals | AY65: =VLOOKUP(AY$1,reg_bal!$D$1:$CA$184,$A65,FALSE)/1000000 -> 38473.769 | AZ65: =VLOOKUP(AZ$1,reg_bal!$D$1:$CA$184,$A65,FALSE)/1000000 -> 36151.89 | BA65: =VLOOKUP(BA$1,reg_bal!$D$1:$CA$184,$A65,FALSE)/1000000 -> 78669.116 | BB65: =VLOOKUP(BB$1,reg_bal!$D$1:$CA$184,$A65,FALSE)/1000000 -> 309568.85 | BC65: =VLOOKUP(BC$1,reg_bal!$D$1:$CA$184,$A65,FALSE)/1000000 -> 93961.509 | BD65: =VLOOKUP(BD$1,reg_bal!$D$1:$CA$184,$A65,FALSE)/1000000 -> 486007.83
B67: Shares of wealth (based on nominal wealth) | C67: =C$2 -> 1995 | D67: =D$2 -> 2000 | E67: =E$2 -> 2005 | F67: =F$2 -> 2010 | G67: =G$2 -> 2015 | H67: =H$2 -> 2020 | J67: Shares of wealth (based on nominal wealth) | K67: =K$2 -> 1995 | L67: =L$2 -> 2000 | M67: =M$2 -> 2005 | N67: =N$2 -> 2010 | O67: =O$2 -> 2015 | P67: =P$2 -> 2020 | R67: Shares of wealth (based on nominal wealth) | S67: =S$2 -> 1995 | T67: =T$2 -> 2000 | U67: =U$2 -> 2005 | V67: =V$2 -> 2010 | W67: =W$2 -> 2015 | X67: =X$2 -> 2020 | Z67: Shares of wealth (based on nominal wealth) | AA67: =AA$2 -> 1995 | AB67: =AB$2 -> 2000 | AC67: =AC$2 -> 2005 | AD67: =AD$2 -> 2010 | AE67: =AE$2 -> 2015 | AF67: =AF$2 -> 2020 | AH67: Shares of wealth (based on nominal wealth) | AI67: =AI$2 -> 1995 | AJ67: =AJ$2 -> 2000 | AK67: =AK$2 -> 2005 | AL67: =AL$2 -> 2010 | AM67: =AM$2 -> 2015 | AN67: =AN$2 -> 2020 | AP67: Shares of wealth (based on nominal wealth) | AQ67: =AQ$2 -> 1995 | AR67: =AR$2 -> 2000 | AS67: =AS$2 -> 2005 | AT67: =AT$2 -> 2010 | AU67: =AU$2 -> 2015 | AV67: =AV$2 -> 2020 | AX67: Shares of wealth (based on nominal wealth) | AY67: =AY$2 -> 1995 | AZ67: =AZ$2 -> 2000 | BA67: =BA$2 -> 2005 | BB67: =BB$2 -> 2010 | BC67: =BC$2 -> 2015 | BD67: =BD$2 -> 2020
B68: Produced capital | C68: =IFERROR(C50/SUM(C50,C51,C52,C61), "..") -> 0.33376467 | D68: =IFERROR(D50/SUM(D50,D51,D52,D61), "..") -> 0.36914449 | E68: =IFERROR(E50/SUM(E50,E51,E52,E61), "..") -> 0.34873951 | F68: =IFERROR(F50/SUM(F50,F51,F52,F61), "..") -> 0.31052368 | G68: =IFERROR(G50/SUM(G50,G51,G52,G61), "..") -> 0.2904424 | H68: =IFERROR(H50/SUM(H50,H51,H52,H61), "..") -> 0.32538959 | J68: Produced capital | K68: =IFERROR(K50/SUM(K50,K51,K52,K61), "..") -> 0.3816461 | L68: =IFERROR(L50/SUM(L50,L51,L52,L61), "..") -> 0.40363358 | M68: =IFERROR(M50/SUM(M50,M51,M52,M61), "..") -> 0.41991755 | N68: =IFERROR(N50/SUM(N50,N51,N52,N61), "..") -> 0.35483233 | O68: =IFERROR(O50/SUM(O50,O51,O52,O61), "..") -> 0.32111246 | P68: =IFERROR(P50/SUM(P50,P51,P52,P61), "..") -> 0.33329811 | R68: Produced capital | S68: =IFERROR(S50/SUM(S50,S51,S52,S61), "..") -> 0.23016883 | T68: =IFERROR(T50/SUM(T50,T51,T52,T61), "..") -> 0.24047035 | U68: =IFERROR(U50/SUM(U50,U51,U52,U61), "..") -> 0.23165366 | V68: =IFERROR(V50/SUM(V50,V51,V52,V61), "..") -> 0.16246818 | W68: =IFERROR(W50/SUM(W50,W51,W52,W61), "..") -> 0.17777765 | X68: =IFERROR(X50/SUM(X50,X51,X52,X61), "..") -> 0.21399717 | Z68: Produced capital | AA68: =IFERROR(AA50/SUM(AA50,AA51,AA52,AA61), "..") -> 0.2084949 | AB68: =IFERROR(AB50/SUM(AB50,AB51,AB52,AB61), "..") -> 0.1595968 | AC68: =IFERROR(AC50/SUM(AC50,AC51,AC52,AC61), "..") -> 0.13456263 | AD68: =IFERROR(AD50/SUM(AD50,AD51,AD52,AD61), "..") -> 0.1188796 | AE68: =IFERROR(AE50/SUM(AE50,AE51,AE52,AE61), "..") -> 0.14046986 | AF68: =IFERROR(AF50/SUM(AF50,AF51,AF52,AF61), "..") -> 0.1895767 | AH68: Produced capital | AI68: =IFERROR(AI50/SUM(AI50,AI51,AI52,AI61), "..") -> 0.29074388 | AJ68: =IFERROR(AJ50/SUM(AJ50,AJ51,AJ52,AJ61), "..") -> 0.2912775 | AK68: =IFERROR(AK50/SUM(AK50,AK51,AK52,AK61), "..") -> 0.33277349 | AL68: =IFERROR(AL50/SUM(AL50,AL51,AL52,AL61), "..") -> 0.35663554 | AM68: =IFERROR(AM50/SUM(AM50,AM51,AM52,AM61), "..") -> 0.35018047 | AN68: =IFERROR(AN50/SUM(AN50,AN51,AN52,AN61), "..") -> 0.36514417 | AP68: Produced capital | AQ68: =IFERROR(AQ50/SUM(AQ50,AQ51,AQ52,AQ61), "..") -> 0.11516239 | AR68: =IFERROR(AR50/SUM(AR50,AR51,AR52,AR61), "..") -> 0.10736516 | AS68: =IFERROR(AS50/SUM(AS50,AS51,AS52,AS61), "..") -> 0.098038506 | AT68: =IFERROR(AT50/SUM(AT50,AT51,AT52,AT61), "..") -> 0.076246084 | AU68: =IFERROR(AU50/SUM(AU50,AU51,AU52,AU61), "..") -> 0.086251265 | AV68: =IFERROR(AV50/SUM(AV50,AV51,AV52,AV61), "..") -> 0.092772976 | AX68: Produced capital | AY68: =IFERROR(AY50/SUM(AY50,AY51,AY52,AY61), "..") -> 0.2499461 | AZ68: =IFERROR(AZ50/SUM(AZ50,AZ51,AZ52,AZ61), "..") -> 0.23223919 | BA68: =IFERROR(BA50/SUM(BA50,BA51,BA52,BA61), "..") -> 0.15366106 | BB68: =IFERROR(BB50/SUM(BB50,BB51,BB52,BB61), "..") -> 0.087388963 | BC68: =IFERROR(BC50/SUM(BC50,BC51,BC52,BC61), "..") -> 0.10775185 | BD68: =IFERROR(BD50/SUM(BD50,BD51,BD52,BD61), "..") -> 0.14849741
